Workbook

Sheet Summary
A1: Data lineage and record-count reconciliation - independent validation
A2: Counts are live formulas over the 'Checks' sheet (COUNTIF on the status column). INFO rows are observations, not tests.
A4: Status | B4: Checks
A5: PASS | B5: =COUNTIF(Checks!$K$4:$K$118,A5) -> 101
A6: FAIL | B6: =COUNTIF(Checks!$K$4:$K$118,A6) -> 0
A7: BLOCKED | B7: =COUNTIF(Checks!$K$4:$K$118,A7) -> 0
A8: NOT TESTED | B8: =COUNTIF(Checks!$K$4:$K$118,A8) -> 0
A9: INFO | B9: =COUNTIF(Checks!$K$4:$K$118,A9) -> 14
A10: Total | B10: =SUM(B5:B9) -> 115

Sheet Checks
A1: Lineage checks (independent re-derivation from the raw file)
A3: id | B3: area | C3: check | D3: population | E3: definition | F3: expected | G3: actual | H3: abs_diff | I3: rel_diff | J3: tolerance | K3: status | L3: explanation / evidence note | M3: evidence | N3: Recheck |diff| (formula) | O3: Recheck status (formula)
A4: L00 | B4: Data lineage & record reconciliation | C4: Raw CSV SHA-256 equals approved hash | F4: 1 | G4: 1 | H4: 0 | I4: 0 | J4: 0 | K4: PASS | L4: approved a0e6eddde25280aa27a60c5955743d3243b14138d876eedac0547e24a1cc6fff | N4: =IF(AND(ISNUMBER(F4),ISNUMBER(G4)),ABS(G4-F4),"") -> 0 | O4: =IF(AND(ISNUMBER(N4),ISNUMBER(J4)),IF(N4<=J4,"PASS","FAIL"),"n/a") -> PASS
A5: L01 | B5: Data lineage & record reconciliation | C5: Cleaned CSV SHA-256 equals approved hash | F5: 1 | G5: 1 | H5: 0 | I5: 0 | J5: 0 | K5: PASS | L5: approved c184b677bacc6f23086e3b5eedd71836643cb75064e428a1ebfee4c075fa9b47 | N5: =IF(AND(ISNUMBER(F5),ISNUMBER(G5)),ABS(G5-F5),"") -> 0 | O5: =IF(AND(ISNUMBER(N5),ISNUMBER(J5)),IF(N5<=J5,"PASS","FAIL"),"n/a") -> PASS
A6: L02 | B6: Data lineage & record reconciliation | C6: Raw rows | E6: data rows excl. header | F6: 152682 | G6: 152682 | H6: 0 | I6: 0 | J6: 0 | K6: PASS | N6: =IF(AND(ISNUMBER(F6),ISNUMBER(G6)),ABS(G6-F6),"") -> 0 | O6: =IF(AND(ISNUMBER(N6),ISNUMBER(J6)),IF(N6<=J6,"PASS","FAIL"),"n/a") -> PASS
A7: L03 | B7: Data lineage & record reconciliation | C7: Raw columns | F7: 43 | G7: 43 | H7: 0 | I7: 0 | J7: 0 | K7: PASS | N7: =IF(AND(ISNUMBER(F7),ISNUMBER(G7)),ABS(G7-F7),"") -> 0 | O7: =IF(AND(ISNUMBER(N7),ISNUMBER(J7)),IF(N7<=J7,"PASS","FAIL"),"n/a") -> PASS
A8: L04 | B8: Data lineage & record reconciliation | C8: Cleaned rows | F8: 152682 | G8: 152682 | H8: 0 | I8: 0 | J8: 0 | K8: PASS | N8: =IF(AND(ISNUMBER(F8),ISNUMBER(G8)),ABS(G8-F8),"") -> 0 | O8: =IF(AND(ISNUMBER(N8),ISNUMBER(J8)),IF(N8<=J8,"PASS","FAIL"),"n/a") -> PASS
A9: L05 | B9: Data lineage & record reconciliation | C9: Cleaned columns | F9: 192 | G9: 192 | H9: 0 | I9: 0 | J9: 0 | K9: PASS | N9: =IF(AND(ISNUMBER(F9),ISNUMBER(G9)),ABS(G9-F9),"") -> 0 | O9: =IF(AND(ISNUMBER(N9),ISNUMBER(J9)),IF(N9<=J9,"PASS","FAIL"),"n/a") -> PASS
A10: L06 | B10: Data lineage & record reconciliation | C10: Raw row_id unique | F10: 152682 | G10: 152682 | H10: 0 | I10: 0 | J10: 0 | K10: PASS | N10: =IF(AND(ISNUMBER(F10),ISNUMBER(G10)),ABS(G10-F10),"") -> 0 | O10: =IF(AND(ISNUMBER(N10),ISNUMBER(J10)),IF(N10<=J10,"PASS","FAIL"),"n/a") -> PASS
A11: L07 | B11: Data lineage & record reconciliation | C11: Cleaned row_id unique | F11: 152682 | G11: 152682 | H11: 0 | I11: 0 | J11: 0 | K11: PASS | N11: =IF(AND(ISNUMBER(F11),ISNUMBER(G11)),ABS(G11-F11),"") -> 0 | O11: =IF(AND(ISNUMBER(N11),ISNUMBER(J11)),IF(N11<=J11,"PASS","FAIL"),"n/a") -> PASS
A12: L08 | B12: Data lineage & record reconciliation | C12: Raw row_id set == cleaned row_id set (no row lost or added) | E12: symmetric difference of the two id sets | F12: 0 | G12: 0 | H12: 0 | J12: 0 | K12: PASS | N12: =IF(AND(ISNUMBER(F12),ISNUMBER(G12)),ABS(G12-F12),"") -> 0 | O12: =IF(AND(ISNUMBER(N12),ISNUMBER(J12)),IF(N12<=J12,"PASS","FAIL"),"n/a") -> PASS
A13: L09 | B13: Data lineage & record reconciliation | C13: source_row_number = raw file line (row order preserved, 2..152683) | F13: 0 | G13: 0 | H13: 0 | J13: 0 | K13: PASS | N13: =IF(AND(ISNUMBER(F13),ISNUMBER(G13)),ABS(G13-F13),"") -> 0 | O13: =IF(AND(ISNUMBER(N13),ISNUMBER(J13)),IF(N13<=J13,"PASS","FAIL"),"n/a") -> PASS
A14: L10 | B14: Data lineage & record reconciliation | C14: row_id at the same position in raw and cleaned | F14: 0 | G14: 0 | H14: 0 | J14: 0 | K14: PASS | N14: =IF(AND(ISNUMBER(F14),ISNUMBER(G14)),ABS(G14-F14),"") -> 0 | O14: =IF(AND(ISNUMBER(N14),ISNUMBER(J14)),IF(N14<=J14,"PASS","FAIL"),"n/a") -> PASS
A15: L11 | B15: Data lineage & record reconciliation | C15: Exact duplicate rows in raw (all 43 columns) | F15: 0 | G15: 0 | H15: 0 | J15: 0 | K15: PASS | L15: 0 means no fully identical raw records; duplicate CANDIDATES are a separate, unresolved topic | N15: =IF(AND(ISNUMBER(F15),ISNUMBER(G15)),ABS(G15-F15),"") -> 0 | O15: =IF(AND(ISNUMBER(N15),ISNUMBER(J15)),IF(N15<=J15,"PASS","FAIL"),"n/a") -> PASS
A16: L12 | B16: Data lineage & record reconciliation | C16: Cleaned columns that are entirely blank | G16: 0 | K16: INFO | N16: =IF(AND(ISNUMBER(F16),ISNUMBER(G16)),ABS(G16-F16),"") | O16: =IF(AND(ISNUMBER(N16),ISNUMBER(J16)),IF(N16<=J16,"PASS","FAIL"),"n/a") -> n/a
A17: L13.row_id | B17: Data lineage & record reconciliation | C17: Raw value preserved byte-for-byte: row_id -> row_id | F17: 0 | G17: 0 | H17: 0 | J17: 0 | K17: PASS | N17: =IF(AND(ISNUMBER(F17),ISNUMBER(G17)),ABS(G17-F17),"") -> 0 | O17: =IF(AND(ISNUMBER(N17),ISNUMBER(J17)),IF(N17<=J17,"PASS","FAIL"),"n/a") -> PASS
A18: L13.extract_batch | B18: Data lineage & record reconciliation | C18: Raw value preserved byte-for-byte: extract_batch -> extract_batch_raw | F18: 0 | G18: 0 | H18: 0 | J18: 0 | K18: PASS | N18: =IF(AND(ISNUMBER(F18),ISNUMBER(G18)),ABS(G18-F18),"") -> 0 | O18: =IF(AND(ISNUMBER(N18),ISNUMBER(J18)),IF(N18<=J18,"PASS","FAIL"),"n/a") -> PASS
A19: L13.fiscal_year | B19: Data lineage & record reconciliation | C19: Raw value preserved byte-for-byte: fiscal_year -> fiscal_year_raw | F19: 0 | G19: 0 | H19: 0 | J19: 0 | K19: PASS | N19: =IF(AND(ISNUMBER(F19),ISNUMBER(G19)),ABS(G19-F19),"") -> 0 | O19: =IF(AND(ISNUMBER(N19),ISNUMBER(J19)),IF(N19<=J19,"PASS","FAIL"),"n/a") -> PASS
A20: L13.fiscal_period | B20: Data lineage & record reconciliation | C20: Raw value preserved byte-for-byte: fiscal_period -> fiscal_period_raw | F20: 0 | G20: 0 | H20: 0 | J20: 0 | K20: PASS | N20: =IF(AND(ISNUMBER(F20),ISNUMBER(G20)),ABS(G20-F20),"") -> 0 | O20: =IF(AND(ISNUMBER(N20),ISNUMBER(J20)),IF(N20<=J20,"PASS","FAIL"),"n/a") -> PASS
A21: L13.legal_entity | B21: Data lineage & record reconciliation | C21: Raw value preserved byte-for-byte: legal_entity -> legal_entity_raw | F21: 0 | G21: 0 | H21: 0 | J21: 0 | K21: PASS | N21: =IF(AND(ISNUMBER(F21),ISNUMBER(G21)),ABS(G21-F21),"") -> 0 | O21: =IF(AND(ISNUMBER(N21),ISNUMBER(J21)),IF(N21<=J21,"PASS","FAIL"),"n/a") -> PASS
A22: L13.entity_code | B22: Data lineage & record reconciliation | C22: Raw value preserved byte-for-byte: entity_code -> entity_code_raw | F22: 0 | G22: 0 | H22: 0 | J22: 0 | K22: PASS | N22: =IF(AND(ISNUMBER(F22),ISNUMBER(G22)),ABS(G22-F22),"") -> 0 | O22: =IF(AND(ISNUMBER(N22),ISNUMBER(J22)),IF(N22<=J22,"PASS","FAIL"),"n/a") -> PASS
A23: L13.gl_account | B23: Data lineage & record reconciliation | C23: Raw value preserved byte-for-byte: gl_account -> gl_account_raw | F23: 0 | G23: 0 | H23: 0 | J23: 0 | K23: PASS | N23: =IF(AND(ISNUMBER(F23),ISNUMBER(G23)),ABS(G23-F23),"") -> 0 | O23: =IF(AND(ISNUMBER(N23),ISNUMBER(J23)),IF(N23<=J23,"PASS","FAIL"),"n/a") -> PASS
A24: L13.currency | B24: Data lineage & record reconciliation | C24: Raw value preserved byte-for-byte: currency -> currency_raw | F24: 0 | G24: 0 | H24: 0 | J24: 0 | K24: PASS | N24: =IF(AND(ISNUMBER(F24),ISNUMBER(G24)),ABS(G24-F24),"") -> 0 | O24: =IF(AND(ISNUMBER(N24),ISNUMBER(J24)),IF(N24<=J24,"PASS","FAIL"),"n/a") -> PASS
A25: L13.amount_local_raw | B25: Data lineage & record reconciliation | C25: Raw value preserved byte-for-byte: amount_local_raw -> amount_local_raw | F25: 0 | G25: 0 | H25: 0 | J25: 0 | K25: PASS | N25: =IF(AND(ISNUMBER(F25),ISNUMBER(G25)),ABS(G25-F25),"") -> 0 | O25: =IF(AND(ISNUMBER(N25),ISNUMBER(J25)),IF(N25<=J25,"PASS","FAIL"),"n/a") -> PASS
A26: L13.fx_rate_raw | B26: Data lineage & record reconciliation | C26: Raw value preserved byte-for-byte: fx_rate_raw -> fx_rate_raw | F26: 0 | G26: 0 | H26: 0 | J26: 0 | K26: PASS | N26: =IF(AND(ISNUMBER(F26),ISNUMBER(G26)),ABS(G26-F26),"") -> 0 | O26: =IF(AND(ISNUMBER(N26),ISNUMBER(J26)),IF(N26<=J26,"PASS","FAIL"),"n/a") -> PASS
A27: L13.actual_usd_raw | B27: Data lineage & record reconciliation | C27: Raw value preserved byte-for-byte: actual_usd_raw -> actual_usd_raw | F27: 0 | G27: 0 | H27: 0 | J27: 0 | K27: PASS | N27: =IF(AND(ISNUMBER(F27),ISNUMBER(G27)),ABS(G27-F27),"") -> 0 | O27: =IF(AND(ISNUMBER(N27),ISNUMBER(J27)),IF(N27<=J27,"PASS","FAIL"),"n/a") -> PASS
A28: L13.budget_usd_raw | B28: Data lineage & record reconciliation | C28: Raw value preserved byte-for-byte: budget_usd_raw -> budget_usd_raw | F28: 0 | G28: 0 | H28: 0 | J28: 0 | K28: PASS | N28: =IF(AND(ISNUMBER(F28),ISNUMBER(G28)),ABS(G28-F28),"") -> 0 | O28: =IF(AND(ISNUMBER(N28),ISNUMBER(J28)),IF(N28<=J28,"PASS","FAIL"),"n/a") -> PASS
... A35: L13.report_scale | B35: Data lineage & record reconciliation | C35: Raw value preserved byte-for-byte: report_scale -> report_scale_raw | F35: 0 | G35: 0 | H35: 0 | J35: 0 | K35: PASS | N35: =IF(AND(ISNUMBER(F35),ISNUMBER(G35)),ABS(G35-F35),"") -> 0 | O35: =IF(AND(ISNUMBER(N35),ISNUMBER(J35)),IF(N35<=J35,"PASS","FAIL"),"n/a") -> PASS
A36: L14 | B36: Data lineage & record reconciliation | C36: Cleaned (normalised) columns: rows whose value differs from raw | G36: 428020 | K36: INFO | L36: source_system:2038; division:49554; country:0; region:6180; cost_center_code:7405; cost_center_name:7307; cost_center_owner:0; account_name:9004; account_group:3681; fs_line:3747; statement:121962; cost_nature:4510; product_family:0; customer_segment:0; channel:5733; uom:3689; user_id:18689; line_text:21902; intercompany:102625; accrual:7922; elimination_status:30000; scenario_tag:0; approval_status:22072; notes:0 | M36: evidence/work/raw_preservation.csv | N36: =IF(AND(ISNUMBER(F36),ISNUMBER(G36)),ABS(G36-F36),"") | O36: =IF(AND(ISNUMBER(N36),ISNUMBER(J36)),IF(N36<=J36,"PASS","FAIL"),"n/a") -> n/a
A37: L20.amount_local | B37: Data lineage & record reconciliation | C37: Independent raw parse of amount_local: missing/placeholder agreement | E37: placeholders ###, ＃N/A, NA, N/A, n/a, null, -, blank -> missing | F37: 0 | G37: 0 | H37: 0 | J37: 0 | K37: PASS | N37: =IF(AND(ISNUMBER(F37),ISNUMBER(G37)),ABS(G37-F37),"") -> 0 | O37: =IF(AND(ISNUMBER(N37),ISNUMBER(J37)),IF(N37<=J37,"PASS","FAIL"),"n/a") -> PASS
A38: L21.amount_local | B38: Data lineage & record reconciliation | C38: Independent raw parse of amount_local: value agreement (|diff| <= 1e-9) | E38: US 1,234.56 / EU 1.234,56 / decimal comma 54,78 / thousands comma 4,579 / ($) / parentheses negative | F38: 0 | G38: 0 | H38: 0 | J38: 0 | K38: PASS | N38: =IF(AND(ISNUMBER(F38),ISNUMBER(G38)),ABS(G38-F38),"") -> 0 | O38: =IF(AND(ISNUMBER(N38),ISNUMBER(J38)),IF(N38<=J38,"PASS","FAIL"),"n/a") -> PASS
A39: L22.amount_local | B39: Data lineage & record reconciliation | C39: Ambiguous 'n,nnn' strings in amount_local read as thousands (not 3-dp decimal comma) | G39: 9128 | K39: INFO | L39: Same reading as the cleaner. The alternative reading would shrink each value 1000x; no field in the data can settle it. Accepted limitation (disclosed). | N39: =IF(AND(ISNUMBER(F39),ISNUMBER(G39)),ABS(G39-F39),"") | O39: =IF(AND(ISNUMBER(N39),ISNUMBER(J39)),IF(N39<=J39,"PASS","FAIL"),"n/a") -> n/a
A40: L20.actual_usd | B40: Data lineage & record reconciliation | C40: Independent raw parse of actual_usd: missing/placeholder agreement | E40: placeholders ###, ＃N/A, NA, N/A, n/a, null, -, blank -> missing | F40: 0 | G40: 0 | H40: 0 | J40: 0 | K40: PASS | N40: =IF(AND(ISNUMBER(F40),ISNUMBER(G40)),ABS(G40-F40),"") -> 0 | O40: =IF(AND(ISNUMBER(N40),ISNUMBER(J40)),IF(N40<=J40,"PASS","FAIL"),"n/a") -> PASS
A41: L21.actual_usd | B41: Data lineage & record reconciliation | C41: Independent raw parse of actual_usd: value agreement (|diff| <= 1e-9) | E41: US 1,234.56 / EU 1.234,56 / decimal comma 54,78 / thousands comma 4,579 / ($) / parentheses negative | F41: 0 | G41: 0 | H41: 0 | J41: 0 | K41: PASS | N41: =IF(AND(ISNUMBER(F41),ISNUMBER(G41)),ABS(G41-F41),"") -> 0 | O41: =IF(AND(ISNUMBER(N41),ISNUMBER(J41)),IF(N41<=J41,"PASS","FAIL"),"n/a") -> PASS
A42: L22.actual_usd | B42: Data lineage & record reconciliation | C42: Ambiguous 'n,nnn' strings in actual_usd read as thousands (not 3-dp decimal comma) | G42: 9317 | K42: INFO | L42: Same reading as the cleaner. The alternative reading would shrink each value 1000x; no field in the data can settle it. Accepted limitation (disclosed). | N42: =IF(AND(ISNUMBER(F42),ISNUMBER(G42)),ABS(G42-F42),"") | O42: =IF(AND(ISNUMBER(N42),ISNUMBER(J42)),IF(N42<=J42,"PASS","FAIL"),"n/a") -> n/a
A43: L20.budget_usd | B43: Data lineage & record reconciliation | C43: Independent raw parse of budget_usd: missing/placeholder agreement | E43: placeholders ###, ＃N/A, NA, N/A, n/a, null, -, blank -> missing | F43: 0 | G43: 0 | H43: 0 | J43: 0 | K43: PASS | N43: =IF(AND(ISNUMBER(F43),ISNUMBER(G43)),ABS(G43-F43),"") -> 0 | O43: =IF(AND(ISNUMBER(N43),ISNUMBER(J43)),IF(N43<=J43,"PASS","FAIL"),"n/a") -> PASS
A44: L21.budget_usd | B44: Data lineage & record reconciliation | C44: Independent raw parse of budget_usd: value agreement (|diff| <= 1e-9) | E44: US 1,234.56 / EU 1.234,56 / decimal comma 54,78 / thousands comma 4,579 / ($) / parentheses negative | F44: 0 | G44: 0 | H44: 0 | J44: 0 | K44: PASS | N44: =IF(AND(ISNUMBER(F44),ISNUMBER(G44)),ABS(G44-F44),"") -> 0 | O44: =IF(AND(ISNUMBER(N44),ISNUMBER(J44)),IF(N44<=J44,"PASS","FAIL"),"n/a") -> PASS
A45: L22.budget_usd | B45: Data lineage & record reconciliation | C45: Ambiguous 'n,nnn' strings in budget_usd read as thousands (not 3-dp decimal comma) | G45: 9123 | K45: INFO | L45: Same reading as the cleaner. The alternative reading would shrink each value 1000x; no field in the data can settle it. Accepted limitation (disclosed). | N45: =IF(AND(ISNUMBER(F45),ISNUMBER(G45)),ABS(G45-F45),"") | O45: =IF(AND(ISNUMBER(N45),ISNUMBER(J45)),IF(N45<=J45,"PASS","FAIL"),"n/a") -> n/a
A46: L20.forecast_usd | B46: Data lineage & record reconciliation | C46: Independent raw parse of forecast_usd: missing/placeholder agreement | E46: placeholders ###, ＃N/A, NA, N/A, n/a, null, -, blank -> missing | F46: 0 | G46: 0 | H46: 0 | J46: 0 | K46: PASS | N46: =IF(AND(ISNUMBER(F46),ISNUMBER(G46)),ABS(G46-F46),"") -> 0 | O46: =IF(AND(ISNUMBER(N46),ISNUMBER(J46)),IF(N46<=J46,"PASS","FAIL"),"n/a") -> PASS
A47: L21.forecast_usd | B47: Data lineage & record reconciliation | C47: Independent raw parse of forecast_usd: value agreement (|diff| <= 1e-9) | E47: US 1,234.56 / EU 1.234,56 / decimal comma 54,78 / thousands comma 4,579 / ($) / parentheses negative | F47: 0 | G47: 0 | H47: 0 | J47: 0 | K47: PASS | N47: =IF(AND(ISNUMBER(F47),ISNUMBER(G47)),ABS(G47-F47),"") -> 0 | O47: =IF(AND(ISNUMBER(N47),ISNUMBER(J47)),IF(N47<=J47,"PASS","FAIL"),"n/a") -> PASS
A48: L22.forecast_usd | B48: Data lineage & record reconciliation | C48: Ambiguous 'n,nnn' strings in forecast_usd read as thousands (not 3-dp decimal comma) | G48: 9260 | K48: INFO | L48: Same reading as the cleaner. The alternative reading would shrink each value 1000x; no field in the data can settle it. Accepted limitation (disclosed). | N48: =IF(AND(ISNUMBER(F48),ISNUMBER(G48)),ABS(G48-F48),"") | O48: =IF(AND(ISNUMBER(N48),ISNUMBER(J48)),IF(N48<=J48,"PASS","FAIL"),"n/a") -> n/a
A49: L20.prior_year_usd | B49: Data lineage & record reconciliation | C49: Independent raw parse of prior_year_usd: missing/placeholder agreement | E49: placeholders ###, ＃N/A, NA, N/A, n/a, null, -, blank -> missing | F49: 0 | G49: 0 | H49: 0 | J49: 0 | K49: PASS | N49: =IF(AND(ISNUMBER(F49),ISNUMBER(G49)),ABS(G49-F49),"") -> 0 | O49: =IF(AND(ISNUMBER(N49),ISNUMBER(J49)),IF(N49<=J49,"PASS","FAIL"),"n/a") -> PASS
A50: L21.prior_year_usd | B50: Data lineage & record reconciliation | C50: Independent raw parse of prior_year_usd: value agreement (|diff| <= 1e-9) | E50: US 1,234.56 / EU 1.234,56 / decimal comma 54,78 / thousands comma 4,579 / ($) / parentheses negative | F50: 0 | G50: 0 | H50: 0 | J50: 0 | K50: PASS | N50: =IF(AND(ISNUMBER(F50),ISNUMBER(G50)),ABS(G50-F50),"") -> 0 | O50: =IF(AND(ISNUMBER(N50),ISNUMBER(J50)),IF(N50<=J50,"PASS","FAIL"),"n/a") -> PASS
A51: L22.prior_year_usd | B51: Data lineage & record reconciliation | C51: Ambiguous 'n,nnn' strings in prior_year_usd read as thousands (not 3-dp decimal comma) | G51: 9058 | K51: INFO | L51: Same reading as the cleaner. The alternative reading would shrink each value 1000x; no field in the data can settle it. Accepted limitation (disclosed). | N51: =IF(AND(ISNUMBER(F51),ISNUMBER(G51)),ABS(G51-F51),"") | O51: =IF(AND(ISNUMBER(N51),ISNUMBER(J51)),IF(N51<=J51,"PASS","FAIL"),"n/a") -> n/a
A52: L30 | B52: Data lineage & record reconciliation | C52: scale_factor_applied consistent with scale_decision (1 / 1e3 / 1e5; blank otherwise) | F52: 0 | G52: 0 | H52: 0 | J52: 0 | K52: PASS | N52: =IF(AND(ISNUMBER(F52),ISNUMBER(G52)),ABS(G52-F52),"") -> 0 | O52: =IF(AND(ISNUMBER(N52),ISNUMBER(J52)),IF(N52<=J52,"PASS","FAIL"),"n/a") -> PASS
A53: L31.actual_usd | B53: Data lineage & record reconciliation | C53: actual_usd_adj == independently parsed raw x scale factor | E53: rows with a scale decision; undetermined/non-posting rows must be blank | F53: 0 | G53: 0 | H53: 0 | J53: 0 | K53: PASS | N53: =IF(AND(ISNUMBER(F53),ISNUMBER(G53)),ABS(G53-F53),"") -> 0 | O53: =IF(AND(ISNUMBER(N53),ISNUMBER(J53)),IF(N53<=J53,"PASS","FAIL"),"n/a") -> PASS
A54: L31.budget_usd | B54: Data lineage & record reconciliation | C54: budget_usd_adj == independently parsed raw x scale factor | E54: rows with a scale decision; undetermined/non-posting rows must be blank | F54: 0 | G54: 0 | H54: 0 | J54: 0 | K54: PASS | N54: =IF(AND(ISNUMBER(F54),ISNUMBER(G54)),ABS(G54-F54),"") -> 0 | O54: =IF(AND(ISNUMBER(N54),ISNUMBER(J54)),IF(N54<=J54,"PASS","FAIL"),"n/a") -> PASS
A55: L31.forecast_usd | B55: Data lineage & record reconciliation | C55: forecast_usd_adj == independently parsed raw x scale factor | E55: rows with a scale decision; undetermined/non-posting rows must be blank | F55: 0 | G55: 0 | H55: 0 | J55: 0 | K55: PASS | N55: =IF(AND(ISNUMBER(F55),ISNUMBER(G55)),ABS(G55-F55),"") -> 0 | O55: =IF(AND(ISNUMBER(N55),ISNUMBER(J55)),IF(N55<=J55,"PASS","FAIL"),"n/a") -> PASS
A56: L31.prior_year_usd | B56: Data lineage & record reconciliation | C56: prior_year_usd_adj == independently parsed raw x scale factor | E56: rows with a scale decision; undetermined/non-posting rows must be blank | F56: 0 | G56: 0 | H56: 0 | J56: 0 | K56: PASS | N56: =IF(AND(ISNUMBER(F56),ISNUMBER(G56)),ABS(G56-F56),"") -> 0 | O56: =IF(AND(ISNUMBER(N56),ISNUMBER(J56)),IF(N56<=J56,"PASS","FAIL"),"n/a") -> PASS
A57: L31.amount_local | B57: Data lineage & record reconciliation | C57: amount_local_adj == independently parsed raw x scale factor | E57: rows with a scale decision; undetermined/non-posting rows must be blank | F57: 0 | G57: 0 | H57: 0 | J57: 0 | K57: PASS | N57: =IF(AND(ISNUMBER(F57),ISNUMBER(G57)),ABS(G57-F57),"") -> 0 | O57: =IF(AND(ISNUMBER(N57),ISNUMBER(J57)),IF(N57<=J57,"PASS","FAIL"),"n/a") -> PASS
A58: L32 | B58: Data lineage & record reconciliation | C58: Scale-restored rows (all 152,682 rows) | F58: 6265 | G58: 6265 | H58: 0 | I58: 0 | J58: 0 | K58: PASS | L58: previously reported 6,265 | N58: =IF(AND(ISNUMBER(F58),ISNUMBER(G58)),ABS(G58-F58),"") -> 0 | O58: =IF(AND(ISNUMBER(N58),ISNUMBER(J58)),IF(N58<=J58,"PASS","FAIL"),"n/a") -> PASS
A59: L33 | B59: Data lineage & record reconciliation | C59: Restored rows with HIGH confidence | F59: 1814 | G59: 1814 | H59: 0 | I59: 0 | J59: 0 | K59: PASS | N59: =IF(AND(ISNUMBER(F59),ISNUMBER(G59)),ABS(G59-F59),"") -> 0 | O59: =IF(AND(ISNUMBER(N59),ISNUMBER(J59)),IF(N59<=J59,"PASS","FAIL"),"n/a") -> PASS
A60: L34 | B60: Data lineage & record reconciliation | C60: Restored rows with MEDIUM confidence | F60: 4451 | G60: 4451 | H60: 0 | I60: 0 | J60: 0 | K60: PASS | N60: =IF(AND(ISNUMBER(F60),ISNUMBER(G60)),ABS(G60-F60),"") -> 0 | O60: =IF(AND(ISNUMBER(N60),ISNUMBER(J60)),IF(N60<=J60,"PASS","FAIL"),"n/a") -> PASS
A61: L35 | B61: Data lineage & record reconciliation | C61: Undetermined-scale rows | F61: 73 | G61: 73 | H61: 0 | I61: 0 | J61: 0 | K61: PASS | N61: =IF(AND(ISNUMBER(F61),ISNUMBER(G61)),ABS(G61-F61),"") -> 0 | O61: =IF(AND(ISNUMBER(N61),ISNUMBER(J61)),IF(N61<=J61,"PASS","FAIL"),"n/a") -> PASS
A62: L36 | B62: Data lineage & record reconciliation | C62: Restorations by raw report_scale label | G62: 6265 | K62: INFO | L62: {"DIVIDED_1E3": {"Lakhs": 0, "Thousands": 5326}, "DIVIDED_1E5": {"Lakhs": 939, "Thousands": 0}} | N62: =IF(AND(ISNUMBER(F62),ISNUMBER(G62)),ABS(G62-F62),"") | O62: =IF(AND(ISNUMBER(N62),ISNUMBER(J62)),IF(N62<=J62,"PASS","FAIL"),"n/a") -> n/a
A63: L40 | B63: Data lineage & record reconciliation | C63: Every raw statement label maps to P&L or BS by the explicit list | F63: 0 | G63: 0 | H63: 0 | J63: 0 | K63: PASS | N63: =IF(AND(ISNUMBER(F63),ISNUMBER(G63)),ABS(G63-F63),"") -> 0 | O63: =IF(AND(ISNUMBER(N63),ISNUMBER(J63)),IF(N63<=J63,"PASS","FAIL"),"n/a") -> PASS
A64: L41 | B64: Data lineage & record reconciliation | C64: Cleaned statement agrees with independent mapping | F64: 0 | G64: 0 | H64: 0 | J64: 0 | K64: PASS | N64: =IF(AND(ISNUMBER(F64),ISNUMBER(G64)),ABS(G64-F64),"") -> 0 | O64: =IF(AND(ISNUMBER(N64),ISNUMBER(J64)),IF(N64<=J64,"PASS","FAIL"),"n/a") -> PASS
A65: L42 | B65: Data lineage & record reconciliation | C65: Non-posting rows (notes = 'subtotal row') | F65: 350 | G65: 350 | H65: 0 | I65: 0 | J65: 0 | K65: PASS | N65: =IF(AND(ISNUMBER(F65),ISNUMBER(G65)),ABS(G65-F65),"") -> 0 | O65: =IF(AND(ISNUMBER(N65),ISNUMBER(J65)),IF(N65<=J65,"PASS","FAIL"),"n/a") -> PASS
A66: L43 | B66: Data lineage & record reconciliation | C66: Cleaned is_posting_row agrees with notes rule | F66: 0 | G66: 0 | H66: 0 | J66: 0 | K66: PASS | N66: =IF(AND(ISNUMBER(F66),ISNUMBER(G66)),ABS(G66-F66),"") -> 0 | O66: =IF(AND(ISNUMBER(N66),ISNUMBER(J66)),IF(N66<=J66,"PASS","FAIL"),"n/a") -> PASS
A67: L44 | B67: Data lineage & record reconciliation | C67: Raw legal_entity values of blank-code rows (independent view) | G67: 76 | K67: INFO | L67: {"do not use": 23, "xxx": 21, "test entity": 16, "": 16} | N67: =IF(AND(ISNUMBER(F67),ISNUMBER(G67)),ABS(G67-F67),"") | O67: =IF(AND(ISNUMBER(N67),ISNUMBER(J67)),IF(N67<=J67,"PASS","FAIL"),"n/a") -> n/a
A68: L45 | B68: Data lineage & record reconciliation | C68: Junk-entity rows (code T999/99 or name TEST ENTITY/Do not use/xxx) | F68: 204 | G68: 204 | H68: 0 | I68: 0 | J68: 0 | K68: PASS | N68: =IF(AND(ISNUMBER(F68),ISNUMBER(G68)),ABS(G68-F68),"") -> 0 | O68: =IF(AND(ISNUMBER(N68),ISNUMBER(J68)),IF(N68<=J68,"PASS","FAIL"),"n/a") -> PASS
A69: L46 | B69: Data lineage & record reconciliation | C69: Cleaned entity_code agrees with independent resolution on resolvable rows | F69: 0 | G69: 0 | H69: 0 | J69: 0 | K69: PASS | N69: =IF(AND(ISNUMBER(F69),ISNUMBER(G69)),ABS(G69-F69),"") -> 0 | O69: =IF(AND(ISNUMBER(N69),ISNUMBER(J69)),IF(N69<=J69,"PASS","FAIL"),"n/a") -> PASS
A70: L47.pl_actual | B70: Data lineage & record reconciliation | C70: Independent primary exclusion reason == excl_PL_actual (row by row) | E70: precedence 1 non-posting, 2 junk, 3 entity, 4 statement, 5 status, 6 period, 7 amount, 8 scale | F70: 0 | G70: 0 | H70: 0 | J70: 0 | K70: PASS | N70: =IF(AND(ISNUMBER(F70),ISNUMBER(G70)),ABS(G70-F70),"") -> 0 | O70: =IF(AND(ISNUMBER(N70),ISNUMBER(J70)),IF(N70<=J70,"PASS","FAIL"),"n/a") -> PASS
A71: L48.pl_actual | B71: Data lineage & record reconciliation | C71: pl_actual: eligible + all exclusions = 152,682 | F71: 152682 | G71: 152682 | H71: 0 | I71: 0 | J71: 0 | K71: PASS | N71: =IF(AND(ISNUMBER(F71),ISNUMBER(G71)),ABS(G71-F71),"") -> 0 | O71: =IF(AND(ISNUMBER(N71),ISNUMBER(J71)),IF(N71<=J71,"PASS","FAIL"),"n/a") -> PASS
A72: L49.pl_actual | B72: Data lineage & record reconciliation | C72: eligible_PL_actual flag == (reason == ELIGIBLE) | F72: 0 | G72: 0 | H72: 0 | J72: 0 | K72: PASS | N72: =IF(AND(ISNUMBER(F72),ISNUMBER(G72)),ABS(G72-F72),"") -> 0 | O72: =IF(AND(ISNUMBER(N72),ISNUMBER(J72)),IF(N72<=J72,"PASS","FAIL"),"n/a") -> PASS
A73: L47.pl_variance | B73: Data lineage & record reconciliation | C73: Independent primary exclusion reason == excl_PL_variance (row by row) | E73: precedence 1 non-posting, 2 junk, 3 entity, 4 statement, 5 status, 6 period, 7 amount, 8 scale | F73: 0 | G73: 0 | H73: 0 | J73: 0 | K73: PASS | N73: =IF(AND(ISNUMBER(F73),ISNUMBER(G73)),ABS(G73-F73),"") -> 0 | O73: =IF(AND(ISNUMBER(N73),ISNUMBER(J73)),IF(N73<=J73,"PASS","FAIL"),"n/a") -> PASS
A74: L48.pl_variance | B74: Data lineage & record reconciliation | C74: pl_variance: eligible + all exclusions = 152,682 | F74: 152682 | G74: 152682 | H74: 0 | I74: 0 | J74: 0 | K74: PASS | N74: =IF(AND(ISNUMBER(F74),ISNUMBER(G74)),ABS(G74-F74),"") -> 0 | O74: =IF(AND(ISNUMBER(N74),ISNUMBER(J74)),IF(N74<=J74,"PASS","FAIL"),"n/a") -> PASS
A75: L49.pl_variance | B75: Data lineage & record reconciliation | C75: eligible_PL_variance flag == (reason == ELIGIBLE) | F75: 0 | G75: 0 | H75: 0 | J75: 0 | K75: PASS | N75: =IF(AND(ISNUMBER(F75),ISNUMBER(G75)),ABS(G75-F75),"") -> 0 | O75: =IF(AND(ISNUMBER(N75),ISNUMBER(J75)),IF(N75<=J75,"PASS","FAIL"),"n/a") -> PASS
A76: L47.bs_actual | B76: Data lineage & record reconciliation | C76: Independent primary exclusion reason == excl_BS_actual (row by row) | E76: precedence 1 non-posting, 2 junk, 3 entity, 4 statement, 5 status, 6 period, 7 amount, 8 scale | F76: 0 | G76: 0 | H76: 0 | J76: 0 | K76: PASS | N76: =IF(AND(ISNUMBER(F76),ISNUMBER(G76)),ABS(G76-F76),"") -> 0 | O76: =IF(AND(ISNUMBER(N76),ISNUMBER(J76)),IF(N76<=J76,"PASS","FAIL"),"n/a") -> PASS
A77: L48.bs_actual | B77: Data lineage & record reconciliation | C77: bs_actual: eligible + all exclusions = 152,682 | F77: 152682 | G77: 152682 | H77: 0 | I77: 0 | J77: 0 | K77: PASS | N77: =IF(AND(ISNUMBER(F77),ISNUMBER(G77)),ABS(G77-F77),"") -> 0 | O77: =IF(AND(ISNUMBER(N77),ISNUMBER(J77)),IF(N77<=J77,"PASS","FAIL"),"n/a") -> PASS
A78: L49.bs_actual | B78: Data lineage & record reconciliation | C78: eligible_BS_actual flag == (reason == ELIGIBLE) | F78: 0 | G78: 0 | H78: 0 | J78: 0 | K78: PASS | N78: =IF(AND(ISNUMBER(F78),ISNUMBER(G78)),ABS(G78-F78),"") -> 0 | O78: =IF(AND(ISNUMBER(N78),ISNUMBER(J78)),IF(N78<=J78,"PASS","FAIL"),"n/a") -> PASS
A79: P01 | B79: Data lineage & record reconciliation | C79: Posted eligible P&L lines (dashboard main population) | F79: 58340 | G79: 58340 | H79: 0 | I79: 0 | J79: 0 | K79: PASS | N79: =IF(AND(ISNUMBER(F79),ISNUMBER(G79)),ABS(G79-F79),"") -> 0 | O79: =IF(AND(ISNUMBER(N79),ISNUMBER(J79)),IF(N79<=J79,"PASS","FAIL"),"n/a") -> PASS
A80: P02 | B80: Data lineage & record reconciliation | C80: Non-Posted lines passing steps 1-4 and 6-8 (dashboard diagnostic population, documented definition) | F80: 77990 | G80: 77990 | H80: 0 | I80: 0 | J80: 0 | K80: PASS | N80: =IF(AND(ISNUMBER(F80),ISNUMBER(G80)),ABS(G80-F80),"") -> 0 | O80: =IF(AND(ISNUMBER(N80),ISNUMBER(J80)),IF(N80<=J80,"PASS","FAIL"),"n/a") -> PASS
A81: P03 | B81: Data lineage & record reconciliation | C81: Posted eligible + non-Posted diagnostic | F81: 136330 | G81: 136330 | H81: 0 | I81: 0 | J81: 0 | K81: PASS | N81: =IF(AND(ISNUMBER(F81),ISNUMBER(G81)),ABS(G81-F81),"") -> 0 | O81: =IF(AND(ISNUMBER(N81),ISNUMBER(J81)),IF(N81<=J81,"PASS","FAIL"),"n/a") -> PASS
A82: P04 | B82: Data lineage & record reconciliation | C82: Rows in cleaned file but in neither dashboard population | F82: 16352 | G82: 16352 | H82: 0 | I82: 0 | J82: 0 | K82: PASS | N82: =IF(AND(ISNUMBER(F82),ISNUMBER(G82)),ABS(G82-F82),"") -> 0 | O82: =IF(AND(ISNUMBER(N82),ISNUMBER(J82)),IF(N82<=J82,"PASS","FAIL"),"n/a") -> PASS
A83: P05 | B83: Data lineage & record reconciliation | C83: Gap rows with no explaining rule (UNEXPLAINED) | F83: 0 | G83: 0 | H83: 0 | J83: 0 | K83: PASS | M83: evidence/work/gap_16352_breakdown.csv | N83: =IF(AND(ISNUMBER(F83),ISNUMBER(G83)),ABS(G83-F83),"") -> 0 | O83: =IF(AND(ISNUMBER(N83),ISNUMBER(J83)),IF(N83<=J83,"PASS","FAIL"),"n/a") -> PASS
A84: P06 | B84: Data lineage & record reconciliation | C84: 16,352 gap decomposition (reason x status) | G84: 16352 | K84: INFO | L84: {"Posted":{"1_NON_POSTING_ROW":147,"2_JUNK_ENTITY":90,"3_ENTITY_UNRESOLVABLE":7,"4_OUT_OF_SCOPE_STATEMENT (Balance Sheet)":3136,"7_AMOUNT_MISSING (actual)":3637,"8_SCALE_UNDECIDABLE":24,"All":7041},"non-Posted":{"1_NON_POSTING_ROW":203,"2_JUNK_ENTITY":114,"3_ENTITY_UNRESOLVABLE":9,"4_OUT_OF_SCOPE_STATEMENT (Balance Sheet)":3989,"7_AMOUNT_MISSING (actual)":4958,"8_SCALE_UNDECIDABLE":38,"All":9311},"All":{"1_NON_POSTING_ROW":350,"2_JUNK_ENTITY":204,"3_ENTITY_UNRESOLVABLE":16,"4_OUT_OF_SCOPE_STATEMENT (Balance Sheet)":7125,"7_AMOUNT_MISSING (actual)":8595,"8_SCALE_UNDECIDABLE":62,"All":16352}} | N84: =IF(AND(ISNUMBER(F84),ISNUMBER(G84)),ABS(G84-F84),"") | O84: =IF(AND(ISNUMBER(N84),ISNUMBER(J84)),IF(N84<=J84,"PASS","FAIL"),"n/a") -> n/a
A85: P07 | B85: Data lineage & record reconciliation | C85: Restored rows in Posted eligible population | F85: 2374 | G85: 2374 | H85: 0 | I85: 0 | J85: 0 | K85: PASS | N85: =IF(AND(ISNUMBER(F85),ISNUMBER(G85)),ABS(G85-F85),"") -> 0 | O85: =IF(AND(ISNUMBER(N85),ISNUMBER(J85)),IF(N85<=J85,"PASS","FAIL"),"n/a") -> PASS
A86: P08 | B86: Data lineage & record reconciliation | C86: Restored rows in non-Posted diagnostic population | F86: 3220 | G86: 3220 | H86: 0 | I86: 0 | J86: 0 | K86: PASS | N86: =IF(AND(ISNUMBER(F86),ISNUMBER(G86)),ABS(G86-F86),"") -> 0 | O86: =IF(AND(ISNUMBER(N86),ISNUMBER(J86)),IF(N86<=J86,"PASS","FAIL"),"n/a") -> PASS
A87: P09 | B87: Data lineage & record reconciliation | C87: Non-Posted diagnostic by status | G87: 77990 | K87: INFO | L87: {"Pending": 19777, "Rejected": 19467, "(blank)": 19444, "Parked": 19302} | N87: =IF(AND(ISNUMBER(F87),ISNUMBER(G87)),ABS(G87-F87),"") | O87: =IF(AND(ISNUMBER(N87),ISNUMBER(J87)),IF(N87<=J87,"PASS","FAIL"),"n/a") -> n/a
A88: P10 | B88: Data lineage & record reconciliation | C88: Dashboard Posted payload row set == independent Posted eligible set | E88: symmetric difference of source_row_number sets | F88: 0 | G88: 0 | H88: 0 | J88: 0 | K88: PASS | N88: =IF(AND(ISNUMBER(F88),ISNUMBER(G88)),ABS(G88-F88),"") -> 0 | O88: =IF(AND(ISNUMBER(N88),ISNUMBER(J88)),IF(N88<=J88,"PASS","FAIL"),"n/a") -> PASS
A89: P11 | B89: Data lineage & record reconciliation | C89: Dashboard non-Posted payload row set == independent non-Posted diagnostic set | F89: 0 | G89: 0 | H89: 0 | J89: 0 | K89: PASS | N89: =IF(AND(ISNUMBER(F89),ISNUMBER(G89)),ABS(G89-F89),"") -> 0 | O89: =IF(AND(ISNUMBER(N89),ISNUMBER(J89)),IF(N89<=J89,"PASS","FAIL"),"n/a") -> PASS
A90: P12 | B90: Data lineage & record reconciliation | C90: Posted and non-Posted payload sets do not overlap | F90: 0 | G90: 0 | H90: 0 | J90: 0 | K90: PASS | N90: =IF(AND(ISNUMBER(F90),ISNUMBER(G90)),ABS(G90-F90),"") -> 0 | O90: =IF(AND(ISNUMBER(N90),ISNUMBER(J90)),IF(N90<=J90,"PASS","FAIL"),"n/a") -> PASS
A91: P13 | B91: Data lineage & record reconciliation | C91: Payload Posted actual (scale-adjusted) == independent parse x factor, max |diff| | F91: 0 | G91: 1.4551915e-11 | H91: 1.4551915e-11 | J91: 1e-06 | K91: PASS | N91: =IF(AND(ISNUMBER(F91),ISNUMBER(G91)),ABS(G91-F91),"") -> 1.4551915e-11 | O91: =IF(AND(ISNUMBER(N91),ISNUMBER(J91)),IF(N91<=J91,"PASS","FAIL"),"n/a") -> PASS
A92: P14 | B92: Data lineage & record reconciliation | C92: Payload non-Posted actual == independent, max |diff| | F92: 0 | G92: 1.4551915e-11 | H92: 1.4551915e-11 | J92: 1e-06 | K92: PASS | N92: =IF(AND(ISNUMBER(F92),ISNUMBER(G92)),ABS(G92-F92),"") -> 1.4551915e-11 | O92: =IF(AND(ISNUMBER(N92),ISNUMBER(J92)),IF(N92<=J92,"PASS","FAIL"),"n/a") -> PASS
A93: P15.b | B93: Data lineage & record reconciliation | C93: Payload budget_usd presence and value == independent (missing mismatches) | F93: 0 | G93: 0 | H93: 0 | J93: 0 | K93: PASS | L93: max |diff| 7.275957614183426e-12 | N93: =IF(AND(ISNUMBER(F93),ISNUMBER(G93)),ABS(G93-F93),"") -> 0 | O93: =IF(AND(ISNUMBER(N93),ISNUMBER(J93)),IF(N93<=J93,"PASS","FAIL"),"n/a") -> PASS
A94: P15.f | B94: Data lineage & record reconciliation | C94: Payload forecast_usd presence and value == independent (missing mismatches) | F94: 0 | G94: 0 | H94: 0 | J94: 0 | K94: PASS | L94: max |diff| 1.4551915228366852e-11 | N94: =IF(AND(ISNUMBER(F94),ISNUMBER(G94)),ABS(G94-F94),"") -> 0 | O94: =IF(AND(ISNUMBER(N94),ISNUMBER(J94)),IF(N94<=J94,"PASS","FAIL"),"n/a") -> PASS
A95: P15.p | B95: Data lineage & record reconciliation | C95: Payload prior_year_usd presence and value == independent (missing mismatches) | F95: 0 | G95: 0 | H95: 0 | J95: 0 | K95: PASS | L95: max |diff| 1.4551915228366852e-11 | N95: =IF(AND(ISNUMBER(F95),ISNUMBER(G95)),ABS(G95-F95),"") -> 0 | O95: =IF(AND(ISNUMBER(N95),ISNUMBER(J95)),IF(N95<=J95,"PASS","FAIL"),"n/a") -> PASS
A96: P16 | B96: Data lineage & record reconciliation | C96: Payload non-Posted status label == raw approval_status (row by row) | F96: 0 | G96: 0 | H96: 0 | J96: 0 | K96: PASS | N96: =IF(AND(ISNUMBER(F96),ISNUMBER(G96)),ABS(G96-F96),"") -> 0 | O96: =IF(AND(ISNUMBER(N96),ISNUMBER(J96)),IF(N96<=J96,"PASS","FAIL"),"n/a") -> PASS
A97: P17 | B97: Data lineage & record reconciliation | C97: Payload restored marker count (Posted) | F97: 2374 | G97: 2374 | H97: 0 | I97: 0 | J97: 0 | K97: PASS | N97: =IF(AND(ISNUMBER(F97),ISNUMBER(G97)),ABS(G97-F97),"") -> 0 | O97: =IF(AND(ISNUMBER(N97),ISNUMBER(J97)),IF(N97<=J97,"PASS","FAIL"),"n/a") -> PASS
A98: P18 | B98: Data lineage & record reconciliation | C98: Payload meta as embedded | K98: INFO | L98: {"csv_sha256": "c184b677bacc6f23086e3b5eedd71836643cb75064e428a1ebfee4c075fa9b47", "raw_sha256": "a0e6eddde25280aa27a60c5955743d3243b14138d876eedac0547e24a1cc6fff", "db_sha256": "00e7437697c8e11baab5d2cff7036d6dda3d251a139774adee0a2dfe92c413e6", "xlsx_sha256": "71e23dca9e0bbce3295223188c296cd3bd5ff51759825487bae049705375f561", "rows_total_source": 152682, "rows_pl_eligible": 58340, "rows_budget": 55043, "rows_any_status": 136330, "rows_nonposted": 77990, "p5_manifest_keys": ["formula_cells", "generated_at_utc", "generator", "generator_sha256", "generator_warnings", "inputs", "notes", "qa", "reconciliation", "sheets", "version", "workbook", "workbook_bytes", "workbook_sha256"]} | N98: =IF(AND(ISNUMBER(F98),ISNUMBER(G98)),ABS(G98-F98),"") | O98: =IF(AND(ISNUMBER(N98),ISNUMBER(J98)),IF(N98<=J98,"PASS","FAIL"),"n/a") -> n/a
A99: W99 | B99: Data lineage & record reconciliation | C99: Waterfall: 152,682 - exclusions = 58,340 | F99: 58340 | G99: 58340 | H99: 0 | I99: 0 | J99: 0 | K99: PASS | N99: =IF(AND(ISNUMBER(F99),ISNUMBER(G99)),ABS(G99-F99),"") -> 0 | O99: =IF(AND(ISNUMBER(N99),ISNUMBER(J99)),IF(N99<=J99,"PASS","FAIL"),"n/a") -> PASS
A100: L50.1_NON_POSTING_ROW | B100: Data lineage & record reconciliation | C100: SQL i9 waterfall rows for 1_NON_POSTING_ROW == independent | F100: 350 | G100: 350 | H100: 0 | I100: 0 | J100: 0 | K100: PASS | N100: =IF(AND(ISNUMBER(F100),ISNUMBER(G100)),ABS(G100-F100),"") -> 0 | O100: =IF(AND(ISNUMBER(N100),ISNUMBER(J100)),IF(N100<=J100,"PASS","FAIL"),"n/a") -> PASS
A101: L50.2_JUNK_ENTITY | B101: Data lineage & record reconciliation | C101: SQL i9 waterfall rows for 2_JUNK_ENTITY == independent | F101: 204 | G101: 204 | H101: 0 | I101: 0 | J101: 0 | K101: PASS | N101: =IF(AND(ISNUMBER(F101),ISNUMBER(G101)),ABS(G101-F101),"") -> 0 | O101: =IF(AND(ISNUMBER(N101),ISNUMBER(J101)),IF(N101<=J101,"PASS","FAIL"),"n/a") -> PASS
A102: L50.3_ENTITY_UNRESOLVABLE | B102: Data lineage & record reconciliation | C102: SQL i9 waterfall rows for 3_ENTITY_UNRESOLVABLE == independent | F102: 16 | G102: 16 | H102: 0 | I102: 0 | J102: 0 | K102: PASS | N102: =IF(AND(ISNUMBER(F102),ISNUMBER(G102)),ABS(G102-F102),"") -> 0 | O102: =IF(AND(ISNUMBER(N102),ISNUMBER(J102)),IF(N102<=J102,"PASS","FAIL"),"n/a") -> PASS
A103: L50.4_OUT_OF_SCOPE_STATEMENT | B103: Data lineage & record reconciliation | C103: SQL i9 waterfall rows for 4_OUT_OF_SCOPE_STATEMENT == independent | F103: 7125 | G103: 7125 | H103: 0 | I103: 0 | J103: 0 | K103: PASS | N103: =IF(AND(ISNUMBER(F103),ISNUMBER(G103)),ABS(G103-F103),"") -> 0 | O103: =IF(AND(ISNUMBER(N103),ISNUMBER(J103)),IF(N103<=J103,"PASS","FAIL"),"n/a") -> PASS
A104: L50.5_STATUS_NOT_ELIGIBLE | B104: Data lineage & record reconciliation | C104: SQL i9 waterfall rows for 5_STATUS_NOT_ELIGIBLE == independent | F104: 82986 | G104: 82986 | H104: 0 | I104: 0 | J104: 0 | K104: PASS | N104: =IF(AND(ISNUMBER(F104),ISNUMBER(G104)),ABS(G104-F104),"") -> 0 | O104: =IF(AND(ISNUMBER(N104),ISNUMBER(J104)),IF(N104<=J104,"PASS","FAIL"),"n/a") -> PASS
A105: L50.7_AMOUNT_MISSING | B105: Data lineage & record reconciliation | C105: SQL i9 waterfall rows for 7_AMOUNT_MISSING == independent | F105: 3637 | G105: 3637 | H105: 0 | I105: 0 | J105: 0 | K105: PASS | N105: =IF(AND(ISNUMBER(F105),ISNUMBER(G105)),ABS(G105-F105),"") -> 0 | O105: =IF(AND(ISNUMBER(N105),ISNUMBER(J105)),IF(N105<=J105,"PASS","FAIL"),"n/a") -> PASS
A106: L50.8_SCALE_UNDECIDABLE | B106: Data lineage & record reconciliation | C106: SQL i9 waterfall rows for 8_SCALE_UNDECIDABLE == independent | F106: 24 | G106: 24 | H106: 0 | I106: 0 | J106: 0 | K106: PASS | N106: =IF(AND(ISNUMBER(F106),ISNUMBER(G106)),ABS(G106-F106),"") -> 0 | O106: =IF(AND(ISNUMBER(N106),ISNUMBER(J106)),IF(N106<=J106,"PASS","FAIL"),"n/a") -> PASS
A107: L50.ELIGIBLE | B107: Data lineage & record reconciliation | C107: SQL i9 waterfall rows for ELIGIBLE == independent | F107: 58340 | G107: 58340 | H107: 0 | I107: 0 | J107: 0 | K107: PASS | N107: =IF(AND(ISNUMBER(F107),ISNUMBER(G107)),ABS(G107-F107),"") -> 0 | O107: =IF(AND(ISNUMBER(N107),ISNUMBER(J107)),IF(N107<=J107,"PASS","FAIL"),"n/a") -> PASS
...

Sheet Waterfall
A1: Record-count waterfall: raw -> cleaned -> eligibility -> Dashboard populations
A2: Each step is reproducible from the cleaned CSV with the expression in 'identification'; the reasons were re-derived independently from the raw values (check L47).
A3: step | B3: stage | C3: records | D3: note | E3: identification
A4: W00 | B4: Raw records | C4: 152682 | D4: raw CSV data rows | E4: len(raw)
A5: W01 | B5: Cleaned records (1:1 with raw, no row dropped) | C5: 152682 | D5: cleaned CSV rows | E5: L08/L09
A6: W11 | B6: less 1_NON_POSTING_ROW | C6: -350 | D6: remaining 152,332 | E6: excl_PL_actual == '1_NON_POSTING_ROW' (independently re-derived, L47)
A7: W12 | B7: less 2_JUNK_ENTITY | C7: -204 | D7: remaining 152,128 | E7: excl_PL_actual == '2_JUNK_ENTITY' (independently re-derived, L47)
A8: W13 | B8: less 3_ENTITY_UNRESOLVABLE | C8: -16 | D8: remaining 152,112 | E8: excl_PL_actual == '3_ENTITY_UNRESOLVABLE' (independently re-derived, L47)
A9: W14 | B9: less 4_OUT_OF_SCOPE_STATEMENT | C9: -7125 | D9: remaining 144,987 | E9: excl_PL_actual == '4_OUT_OF_SCOPE_STATEMENT' (independently re-derived, L47)
A10: W15 | B10: less 5_STATUS_NOT_ELIGIBLE | C10: -82986 | D10: remaining 62,001 | E10: excl_PL_actual == '5_STATUS_NOT_ELIGIBLE' (independently re-derived, L47)
A11: W16 | B11: less 6_PERIOD_UNRESOLVABLE | C11: 0 | D11: remaining 62,001 | E11: excl_PL_actual == '6_PERIOD_UNRESOLVABLE' (independently re-derived, L47)
A12: W17 | B12: less 7_AMOUNT_MISSING | C12: -3637 | D12: remaining 58,364 | E12: excl_PL_actual == '7_AMOUNT_MISSING' (independently re-derived, L47)
A13: W18 | B13: less 8_SCALE_UNDECIDABLE | C13: -24 | D13: remaining 58,340 | E13: excl_PL_actual == '8_SCALE_UNDECIDABLE' (independently re-derived, L47)
A14: W20 | B14: = Posted eligible P&L lines (dashboard main payload, SQL v_pl_actual) | C14: 58340 | E14: eligible_PL_actual = 1
A15: W30 | B15: Step-5 (status) exclusions | C15: 82986 | E15: excl_PL_actual == 5
A16: W31 | B16: of which also pass steps 6-8 -> non-Posted diagnostic payload | C16: 77990 | E16: v_pl_actual_any_status, status <> Posted
A17: W32 | B17: of which fail step 7 (actual missing) as well -> in NO payload | C17: 4958 | E17: status excl. AND actual missing
A18: W33 | B18: of which fail step 8 (scale undetermined) only -> in NO payload | C18: 38
A19: W40 | B19: Combined dashboard payload | C19: 136330 | E19: P03
A20: W41 | B20: Not in any dashboard payload | C20: 16352 | E20: P04 / gap_16352_breakdown.csv
A21: W50 | B21: P&L variance population (actual AND budget present) | C21: 55043 | E21: eligible_PL_variance = 1
A22: W60 | B22: Balance Sheet actual population (separate, never added to P&L) | C22: 2953 | E22: eligible_BS_actual = 1
A23: W70 | B23: P&L vs forecast population (eligible AND forecast present) | C23: 54851 | E23: v_pl_forecast
A24: W71 | B24: P&L vs prior-year population (eligible AND PY present) | C24: 54923 | E24: v_pl_prior

Sheet Gap_16352
A1: Why 16,352 cleaned rows are in no dashboard population
A2: Posted+non-Posted rows that fail a non-status gate. 0 unexplained rows (check P05).
A3: reason (first failing gate, status gate ignored) | B3: Posted | C3: non-Posted | D3: All
A4: 1_NON_POSTING_ROW | B4: 147 | C4: 203 | D4: 350
A5: 2_JUNK_ENTITY | B5: 90 | C5: 114 | D5: 204
A6: 3_ENTITY_UNRESOLVABLE | B6: 7 | C6: 9 | D6: 16
A7: 4_OUT_OF_SCOPE_STATEMENT (Balance Sheet) | B7: 3136 | C7: 3989 | D7: 7125
A8: 7_AMOUNT_MISSING (actual) | B8: 3637 | C8: 4958 | D8: 8595
A9: 8_SCALE_UNDECIDABLE | B9: 24 | C9: 38 | D9: 62
A10: All | B10: 7041 | C10: 9311 | D10: 16352

Sheet Excl_pl_actual
A1: Primary exclusion reasons - P&L actual (sum must be 152,682)
A3: primary reason | B3: rows
A4: 1_NON_POSTING_ROW | B4: 350
A5: 2_JUNK_ENTITY | B5: 204
A6: 3_ENTITY_UNRESOLVABLE | B6: 16
A7: 4_OUT_OF_SCOPE_STATEMENT | B7: 7125
A8: 5_STATUS_NOT_ELIGIBLE | B8: 82986
A9: 7_AMOUNT_MISSING | B9: 3637
A10: 8_SCALE_UNDECIDABLE | B10: 24
A11: ELIGIBLE | B11: 58340
A12: Total (formula) | B12: =SUM(B4:B11) -> 152682

Sheet Excl_pl_variance
A1: Primary exclusion reasons - P&L variance (actual and budget) (sum must be 152,682)
A3: primary reason | B3: rows
A4: 1_NON_POSTING_ROW | B4: 350
A5: 2_JUNK_ENTITY | B5: 204
A6: 3_ENTITY_UNRESOLVABLE | B6: 16
A7: 4_OUT_OF_SCOPE_STATEMENT | B7: 7125
A8: 5_STATUS_NOT_ELIGIBLE | B8: 82986
A9: 7_AMOUNT_MISSING | B9: 6937
A10: 8_SCALE_UNDECIDABLE | B10: 21
A11: ELIGIBLE | B11: 55043
A12: Total (formula) | B12: =SUM(B4:B11) -> 152682

Sheet Excl_bs_actual
A1: Primary exclusion reasons - Balance Sheet actual (sum must be 152,682)
A3: primary reason | B3: rows
A4: 1_NON_POSTING_ROW | B4: 350
A5: 2_JUNK_ENTITY | B5: 204
A6: 3_ENTITY_UNRESOLVABLE | B6: 16
A7: 4_OUT_OF_SCOPE_STATEMENT | B7: 144987
A8: 5_STATUS_NOT_ELIGIBLE | B8: 3989
A9: 7_AMOUNT_MISSING | B9: 182
A10: 8_SCALE_UNDECIDABLE | B10: 1
A11: ELIGIBLE | B11: 2953
A12: Total (formula) | B12: =SUM(B4:B11) -> 152682

Sheet Raw_preservation
A1: Raw column -> cleaned column: rows whose value differs (raw-value columns must be 0)
A3: raw_column | B3: cleaned_column | C3: rows_differing | D3: note
A4: row_id | B4: row_id | C4: 0
A5: source_system | B5: source_system | C5: 2038
A6: extract_batch | B6: extract_batch_raw | C6: 0
A7: fiscal_year | B7: fiscal_year_raw | C7: 0
A8: fiscal_period | B8: fiscal_period_raw | C8: 0
A9: legal_entity | B9: legal_entity_raw | C9: 0
A10: entity_code | B10: entity_code_raw | C10: 0
A11: division | B11: division | C11: 49554
A12: country | B12: country | C12: 0
A13: region | B13: region | C13: 6180
A14: cost_center_code | B14: cost_center_code | C14: 7405
A15: cost_center_name | B15: cost_center_name | C15: 7307
... A46: notes | B46: notes | C46: 0

Sheet Amount_formats
A1: Raw amount formats found by the independent parser (rows)
A3: format class (independent parser) | B3: amount_local | C3: actual_usd | D3: budget_usd | E3: forecast_usd | F3: prior_year_usd
A4: missing | B4: 9172 | C4: 9259 | D4: 8915 | E4: 9200 | F4: 9069
A5: us | B5: 19436 | C5: 18451 | D5: 18704 | E5: 18611 | F5: 18262
A6: plain | B6: 105724 | C6: 106776 | D6: 107134 | E6: 106963 | F6: 107474
A7: dec_comma | B7: 1389 | C7: 1919 | D7: 1832 | E7: 1817 | F7: 1974
A8: comma_thousands_ambiguous | B8: 9128 | C8: 9317 | D8: 9123 | E8: 9260 | F8: 9058
A9: eu | B9: 7238 | C9: 6936 | D9: 6948 | E9: 6801 | F9: 6826
A10: comma_thousands | B10: 595 | C10: 24 | D10: 26 | E10: 30 | F10: 19
