Workbook

Sheet Start Here
A1: Month-End Close Reliability & Financial Performance Analytics
A2: Phase 5 - FP&A Excel workbook and reconciliation | NovaBridge Industries (synthetic data) | local use only, not published
A4: STATUS: PROVISIONAL. The data is a synthetic extract with unverified provenance and licence. Posted-only eligibility, scale restoration, FX direction and the variance-% convention are working conventions; the account sign convention, duplicate rule and consolidation are unresolved. Read 'Definitions' before quoting any number.
A6: Sheet | B6: What it answers
A7: 1. Start Here | B7: This page: scope, status, navigation, colour legend, source identity.
A8: 2. Executive Summary | B8: Headline numbers, annual view, ranked insights and what the workbook does not claim. All numbers are links.
A9: 3. Monthly P&L | B9: 36-month P&L by section, gross profit, operating result proxy, calendar-year totals, MoM %. Source of the totals every other sheet reconciles to.
A10: 4. Budget vs Actual | B10: Variance by section on same-sign and all-lines bases, bridge, top entity x GL contributors, materiality sensitivity, monthly variance with % check.
A11: 5. Forecast & Prior Year | B11: Forecast error (WAPE, bias), forecast vs budget on matched lines, where the error sits, prior-year column vs true year-on-year.
A12: 6. Entity & Division | B12: Six entities and five divisions: size, margin, variance, growth; entity x GL variance detail.
A13: 7. GL & Cost Drivers | B13: 24 GL accounts, cost Pareto, mix, cost-to-revenue, concentration, persistent deviations, salary-rate scenario (conditional).
A14: 8. Gross Profit | B14: Three explicit discount/sign treatments x two row sets; margin range, versus budget, by entity.
A15: 9. Insights & Actions | B15: Seven ranked insights, 16 fields each: observed vs hypothesis, evidence required, owner, KPI. No savings claims.
A16: 10. Data Quality | B16: Exclusion waterfall (152,682 rows), flag exposure, field reliability, scenario swings, scale/duplicate exposure, balance-sheet limits.
A17: 11. Reconciliation & QA | B17: Live PASS/FAIL formulas: workbook vs independent recompute from the Phase 4 database views, plus source identity.
A18: 12. Definitions | B18: Rules register R1-R14, metric definitions, owner decisions, assumptions, lineage.
A21: Colour and format legend
A22: Blue text | B22: Input value taken from Phase 4 (or an adjustable assumption on an amber cell).
A23: Black text | B23: Formula calculated on the same sheet.
A24: Green text | B24: Formula that links to another sheet in this workbook.
A25: Red text | B25: Link to an external workbook - none exist in this file (checked by the test suite).
A26: Negative numbers | B26: Red in parentheses; zeros show as a dash.
A27: Amber fill | B27: Adjustable threshold, or highlighted result (legend printed on each sheet).
A30: How to read
A31: 1. Amounts: USD, scale-adjusted (provisional), signs as recorded; costs are positive magnitudes.
A32: 2. Variance = Actual - Budget; Variance % = Variance / |net budget|, hidden when |net budget| < 50% of gross budget. Direction columns state arithmetic only.
A33: 3. Primary basis: same-sign lines. The all-lines view is always shown beside it. Opposite-sign and zero-involved lines are bridged, never removed or flipped.
A34: 4. Tables have filters; use the sheet's Basis / Section columns to slice. Every sheet has a link back to this page.
A35: 5. Reconciliation & QA must read ALL CHECKS PASS; if you change an input, re-check it.
A38: Source identity
A39: Reconciliation status | B39: ='Reconciliation & QA'!$B$5 -> ALL 137 CHECKS PASS
A40: Phase 4 database SHA-256 | B40: 00e7437697c8e11baab5d2cff7036d6dda3d251a139774adee0a2dfe92c413e6
A41: Approved cleaned CSV SHA-256 | B41: c184b677bacc6f23086e3b5eedd71836643cb75064e428a1ebfee4c075fa9b47
A42: Generator SHA-256 | B42: 02b45089fc71e6b10d16c738e9796755409290014e85945c80aad932ac564d0a
A43: Generated at (UTC) | B43: 2026-10-29T12:55:33Z
A44: Version | B44: Phase 5 workbook v1.0

Sheet Executive Summary
A1: Executive summary - FP&A month-end close analysis | G1: Back to Start Here
A2: NovaBridge Industries (synthetic extract), Jan 2023 - Dec 2025, six legal entities, USD. Every number on this page is a green link to the sheet that calculates it.
A3: READ FIRST: all figures are provisional. The population is Posted-only journal lines with scale restoration (conventions R6/R7), signs are as recorded (R9 unresolved) and there are no favourable/adverse labels. The operating result proxy is NOT EBITDA. Nothing here is a forecast-skill claim, a saving or a finding about cause - see 'Insights & Actions' for what is observed vs hypothesised.
A5: Headline numbers (3 years, eligible Posted-only lines)
A6: Measure | B6: Value | D6: Where calculated
A7: Revenue (USD) | B7: ='Monthly P&L'!$C$45 -> 2.02649e+08 | D7: Monthly P&L
A8: Gross profit, treatment S1 signed as recorded (USD) | B8: ='Monthly P&L'!$E$45 -> 1.0984098e+08 | D8: Monthly P&L / Gross Profit
A9: Gross margin % (S1) | B9: ='Monthly P&L'!$F$45 -> 0.54202578 | D9: Monthly P&L
A10: Operating result proxy (USD) - not EBITDA | B10: ='Monthly P&L'!$I$45 -> 26319246 | D10: Monthly P&L
A11: Proxy margin % | B11: ='Monthly P&L'!$J$45 -> 0.12987602 | D11: Monthly P&L
A12: Eligible P&L lines (count) | B12: ='Monthly P&L'!$N$45 -> 58340 | D12: Monthly P&L
A13: Revenue growth 2024 vs 2023 | B13: ='Monthly P&L'!$O$52 -> 0.14792168 | D13: Monthly P&L (calendar-year block)
A14: Revenue growth 2025 vs 2024 | B14: ='Monthly P&L'!$O$53 -> 0.0089280979 | D14: Monthly P&L (calendar-year block)
A15: Revenue variance vs budget, same-sign lines (USD) | B15: ='Budget vs Actual'!$E$10 -> -7023037.3 | D15: Budget vs Actual A1
A16: Revenue variance %, same-sign lines | B16: ='Budget vs Actual'!$G$10 -> -0.035574137 | D16: Budget vs Actual A1
A17: COGS variance %, same-sign lines | B17: ='Budget vs Actual'!$G$11 -> 0.064186465 | D17: Budget vs Actual A1
A18: People variance %, same-sign lines | B18: ='Budget vs Actual'!$G$12 -> 0.063740232 | D18: Budget vs Actual A1
A19: Opex variance %, same-sign lines | B19: ='Budget vs Actual'!$G$13 -> 0.064129827 | D19: Budget vs Actual A1
A20: Gross profit variance vs budget, S1 same-sign (USD) | B20: ='Gross Profit'!$H$54 -> -12318779 | D20: Gross Profit GP3
A21: Opposite-sign share of revenue forecast error | B21: ='Forecast & Prior Year'!$F$58 -> 0.91180792 | D21: Forecast & Prior Year F4
A23: Revenue forecast accuracy: three populations, never to be mixed
A24: WAPE = sum |forecast - actual| / sum |actual| (budget analogous). Forecast error = forecast - actual.
A25: Population (revenue lines) | B25: Lines (count) | C25: Forecast WAPE | D25: Budget WAPE | E25: Where calculated
A26: A. Matched same-sign subset: actual, budget and forecast all non-zero with the same sign (selected by outcome) | B26: ='Forecast & Prior Year'!$B$32 -> 24372 | C26: ='Forecast & Prior Year'!$C$32 -> 0.02587993 | D26: ='Forecast & Prior Year'!$D$32 -> 0.03666117 | E26: Forecast & Prior Year F3
A27: B. Comparable lines: actual, budget and forecast all present, any sign (same lines for both measures) | B27: ='Forecast & Prior Year'!$B$49 -> 29131 | C27: ='Forecast & Prior Year'!$C$49 -> 0.268111 | D27: ='Forecast & Prior Year'!$D$49 -> 0.29263818 | E27: Forecast & Prior Year F3b
A28: C. All lines with a forecast value (no budget required; budget WAPE not computed on this population) | B28: ='Forecast & Prior Year'!$B$20 -> 30879 | C28: ='Forecast & Prior Year'!$I$20 -> 0.2659202 | D28: n/a | E28: Forecast & Prior Year F2
A30: Why the populations differ: A keeps only lines where all three amounts agree in sign, which mechanically removes the lines carrying most of the error (opposite-sign lines hold the share of absolute revenue forecast error shown above). B keeps every line that has all three values. C also keeps lines with no budget value.
A31: Reading: the matched-subset WAPE (A) is small because of how the subset is chosen; it is not general forecasting skill. On B both errors are large and the forecast is only modestly closer than the budget for revenue, COGS and opex, and not closer for people costs (see Forecast & Prior Year F3b). The extract has no forecast version or as-of date, so forecast skill cannot be established from either figure.
A34: Reconciliation status (workbook vs independent database recompute) | B34: ='Reconciliation & QA'!$B$5 -> ALL 137 CHECKS PASS
A37: Annual view (links to Monthly P&L)
A38: Year | B38: Revenue (USD) | C38: Gross profit S1 (USD) | D38: Operating result proxy (USD)
A39: 2023 | B39: ='Monthly P&L'!$C$51 -> 61295631 | C39: ='Monthly P&L'!$E$51 -> 32475369 | D39: ='Monthly P&L'!$I$51 -> 5637402.1
A40: 2024 | B40: ='Monthly P&L'!$C$52 -> 70362584 | C40: ='Monthly P&L'!$E$52 -> 40119070 | D40: ='Monthly P&L'!$I$52 -> 11898679
A41: 2025 | B41: ='Monthly P&L'!$C$53 -> 70990788 | C41: ='Monthly P&L'!$E$53 -> 37246545 | D41: ='Monthly P&L'!$I$53 -> 8783165.5
A44: Ranked insights (observed fact first; see 'Insights & Actions' for hypothesis, evidence required, owner and KPI)
A45: Insight | B45: Score (of 12) | C45: Confidence (1-3)
A46: #1 INS-01: The journal-status rule is the largest swing factor in the revenue and result headlines among the four assumptions tested (status, scale, sign, duplicates) | B46: 11 | C46: 2
A47: #2 INS-02: Lines whose forecast and actual have opposite signs (10% to 13% of lines) carry 89% to 91% of the absolute forecast error; whether they are data defects or legitimate entries is unresolved | B47: 11 | C47: 2
A48: #3 INS-03: Actuals sit a near-constant 3.6% below budget on revenue and 6.4% above budget on costs on same-sign lines in all 36 months, all 6 entities, all 5 divisions and every one of the 20 operating accounts (the all-lines view differs) | B48: 10 | C48: 2
A49: #4 INS-04: Gross profit is $12.3M below budget on same-sign lines: 57% of the gap is revenue below budget and 43% is COGS above budget; the margin gap holds under all three discount treatments | B49: 10 | C49: 2
A50: #5 INS-05: On a matched same-sign subset the forecast is closer to actuals than the budget; on all comparable lines the margin is 26.8% vs 29.3% revenue WAPE (forecast vs budget) and reverses for people costs, and neither view establishes forecast skill | B50: 10 | C50: 2
A51: #6 INS-06: Salary lines carry a near-constant rate per FTE within each entity; without a budgeted FTE plan and the budget's rate method, the people-cost variance cannot be split into rate and volume | B51: 10 | C51: 2
A52: #7 INS-07: Scale restoration moves the result proxy by $3.1M, and the larger (MEDIUM-confidence) tier cannot be verified against price | B52: 9 | C52: 2
A55: What this workbook does NOT say
A56: - Costs are not 'favourable' or 'adverse': the sign convention (R9) is unresolved.
A57: - A variance is not a saving; no recoverable-savings amount is claimed anywhere (financial exposure, cause hypothesis and savings are kept separate).
A58: - The matched-subset forecast WAPE is not general forecasting skill: on all comparable lines both errors are large and the forecast's edge over the budget is small (and absent for people costs). Without dated forecast snapshots neither is evidence of skill or of a correctable bias.
A59: - Headline revenue moves by more than 100% depending on which journal statuses count (INS-01): confirm the status rule before using any total externally.
A60: - Balance-sheet lines are records, not period-end balances; close duration and on-time-close rates cannot be calculated from this extract.

Sheet Monthly P&L
A1: Monthly P&L - actuals, Posted-only eligible lines | O1: Back to Start Here
A2: USD, scale-adjusted (provisional), signs as recorded. Source: out_a1_pl_period_section (Phase 4). Costs are positive magnitudes: result = revenue - costs.
A3: Provisional population: Posted-only journal status (rule R6) and the scale-restoration rule are conventions, not confirmed accounting. No favourable/adverse labels: the account sign convention (R9) is unresolved. 'Operating result proxy' = Revenue - COGS - People - Opex; it is NOT EBITDA or operating profit. D&A, below-EBITDA items and tax are shown as memo lines and are not subtotalled because their sign treatment is unverified. Balance-sheet records are excluded (see Data Quality).
A5: MoM highlight threshold (assumption): | D5: 0.1 | E5: <- amber = |month-on-month revenue change| >= threshold (also read the sign in the cell). Blue = input, black = formula.
A7: Month | B7: Year | C7: Revenue (USD) | D7: COGS (USD) | E7: Gross profit, S1 signed as recorded (USD) | F7: Gross margin % (S1) | G7: People costs (USD) | H7: Operating expenses (USD) | I7: Operating result proxy (USD) - not EBITDA | J7: Proxy margin % | K7: Memo: D&A (USD) | L7: Memo: Below-EBITDA (USD) | M7: Memo: Tax (USD) | N7: Eligible lines (count) | O7: Revenue MoM %
A8: 44927 | B8: 2023 | C8: 4261970.3 | D8: 2086530.6 | E8: =C8-D8 -> 2175439.7 | F8: =IF(C8>0,E8/C8,"n/a") -> 0.51043053 | G8: 1300449.4 | H8: 907347.88 | I8: =C8-D8-G8-H8 -> -32357.58 | J8: =IF(C8>0,I8/C8,"n/a") -> -0.0075921645 | K8: 27578.96 | L8: 286.8082 | M8: 102547.78 | N8: 1670 | O8: n/a
A9: 44958 | B9: 2023 | C9: 4952634.8 | D9: 2254535 | E9: =C9-D9 -> 2698099.9 | F9: =IF(C9>0,E9/C9,"n/a") -> 0.5447807 | G9: 989695.09 | H9: 1278087.1 | I9: =C9-D9-G9-H9 -> 430317.64 | J9: =IF(C9>0,I9/C9,"n/a") -> 0.086886608 | K9: 64012.01 | L9: 17800.824 | M9: 76795.04 | N9: 1637 | O9: =IF(C8>0,C9/C8-1,"n/a") -> 0.16205287
A10: 44986 | B10: 2023 | C10: 4520527.3 | D10: 2246171.8 | E10: =C10-D10 -> 2274355.5 | F10: =IF(C10>0,E10/C10,"n/a") -> 0.5031173 | G10: 1227630.7 | H10: 1404752 | I10: =C10-D10-G10-H10 -> -358027.25 | J10: =IF(C10>0,I10/C10,"n/a") -> -0.07920033 | K10: 19335.112 | L10: 20273.621 | M10: 87042.44 | N10: 1598 | O10: =IF(C9>0,C10/C9-1,"n/a") -> -0.087248015
A11: 45017 | B11: 2023 | C11: 5762118.3 | D11: 2506781 | E11: =C11-D11 -> 3255337.2 | F11: =IF(C11>0,E11/C11,"n/a") -> 0.56495495 | G11: 663677.31 | H11: 1182995 | I11: =C11-D11-G11-H11 -> 1408664.9 | J11: =IF(C11>0,I11/C11,"n/a") -> 0.24446998 | K11: 56383.16 | L11: 7004.82 | M11: 75446.31 | N11: 1646 | O11: =IF(C10>0,C11/C10-1,"n/a") -> 0.27465623
A12: 45047 | B12: 2023 | C12: 5278866.6 | D12: 2759484 | E12: =C12-D12 -> 2519382.7 | F12: =IF(C12>0,E12/C12,"n/a") -> 0.47725825 | G12: 920661.37 | H12: 969810.34 | I12: =C12-D12-G12-H12 -> 628910.94 | J12: =IF(C12>0,I12/C12,"n/a") -> 0.11913749 | K12: 89978.81 | L12: 7703.1698 | M12: 76859.84 | N12: 1651 | O12: =IF(C11>0,C12/C11-1,"n/a") -> -0.083867013
A13: 45078 | B13: 2023 | C13: 5344108.5 | D13: 2509076.2 | E13: =C13-D13 -> 2835032.3 | F13: =IF(C13>0,E13/C13,"n/a") -> 0.53049677 | G13: 953553.84 | H13: 908585.81 | I13: =C13-D13-G13-H13 -> 972892.61 | J13: =IF(C13>0,I13/C13,"n/a") -> 0.18204956 | K13: 45497.7 | L13: 12238.169 | M13: 98367.221 | N13: 1605 | O13: =IF(C12>0,C13/C12-1,"n/a") -> 0.012359065
A14: 45108 | B14: 2023 | C14: 6347255 | D14: 2487990.5 | E14: =C14-D14 -> 3859264.4 | F14: =IF(C14>0,E14/C14,"n/a") -> 0.60802102 | G14: 1420978.3 | H14: 1331740.5 | I14: =C14-D14-G14-H14 -> 1106545.6 | J14: =IF(C14>0,I14/C14,"n/a") -> 0.17433452 | K14: 56450.696 | L14: 36953.56 | M14: 114487.94 | N14: 1652 | O14: =IF(C13>0,C14/C13-1,"n/a") -> 0.18771073
A15: 45139 | B15: 2023 | C15: 4916757.8 | D15: 2729906.7 | E15: =C15-D15 -> 2186851 | F15: =IF(C15>0,E15/C15,"n/a") -> 0.44477502 | G15: 1478533.4 | H15: 1252506.4 | I15: =C15-D15-G15-H15 -> -544188.75 | J15: =IF(C15>0,I15/C15,"n/a") -> -0.11068041 | K15: 23719.3 | L15: 20994.469 | M15: 110922.63 | N15: 1644 | O15: =IF(C14>0,C15/C14-1,"n/a") -> -0.22537257
A16: 45170 | B16: 2023 | C16: 5542771.8 | D16: 2149206.5 | E16: =C16-D16 -> 3393565.3 | F16: =IF(C16>0,E16/C16,"n/a") -> 0.61225059 | G16: 1056920.6 | H16: 891852.92 | I16: =C16-D16-G16-H16 -> 1444791.8 | J16: =IF(C16>0,I16/C16,"n/a") -> 0.26066232 | K16: 86655.633 | L16: 28024.181 | M16: 24332.717 | N16: 1580 | O16: =IF(C15>0,C16/C15-1,"n/a") -> 0.12732253
A17: 45200 | B17: 2023 | C17: 4803300.9 | D17: 2128271.6 | E17: =C17-D17 -> 2675029.2 | F17: =IF(C17>0,E17/C17,"n/a") -> 0.55691477 | G17: 1362384.4 | H17: 1200679.9 | I17: =C17-D17-G17-H17 -> 111964.89 | J17: =IF(C17>0,I17/C17,"n/a") -> 0.023309989 | K17: 34374.195 | L17: 12680.771 | M17: 69099.762 | N17: 1630 | O17: =IF(C16>0,C17/C16-1,"n/a") -> -0.13341176
A18: 45231 | B18: 2023 | C18: 4905385.9 | D18: 2495876 | E18: =C18-D18 -> 2409510 | F18: =IF(C18>0,E18/C18,"n/a") -> 0.49119682 | G18: 875813.55 | H18: 1097601.9 | I18: =C18-D18-G18-H18 -> 436094.48 | J18: =IF(C18>0,I18/C18,"n/a") -> 0.088901156 | K18: 21737.31 | L18: 20908.09 | M18: 38621.827 | N18: 1609 | O18: =IF(C17>0,C18/C17-1,"n/a") -> 0.021253106
A19: 45261 | B19: 2023 | C19: 4659933.8 | D19: 2466431.7 | E19: =C19-D19 -> 2193502.2 | F19: =IF(C19>0,E19/C19,"n/a") -> 0.4707153 | G19: 1134455.5 | H19: 1027253.9 | I19: =C19-D19-G19-H19 -> 31792.737 | J19: =IF(C19>0,I19/C19,"n/a") -> 0.0068225726 | K19: 31833.16 | L19: 19408.2 | M19: 110341.38 | N19: 1596 | O19: =IF(C18>0,C19/C18-1,"n/a") -> -0.050037263
A20: 45292 | B20: 2024 | C20: 4879215.5 | D20: 1782755.4 | E20: =C20-D20 -> 3096460 | F20: =IF(C20>0,E20/C20,"n/a") -> 0.63462252 | G20: 1023893.5 | H20: 1132483.4 | I20: =C20-D20-G20-H20 -> 940083.16 | J20: =IF(C20>0,I20/C20,"n/a") -> 0.19267097 | K20: 24064.38 | L20: 23968.43 | M20: 49330.704 | N20: 1603 | O20: =IF(C19>0,C20/C19-1,"n/a") -> 0.047056813
... A43: 45992 | B43: 2025 | C43: 5156931.1 | D43: 2363015.1 | E43: =C43-D43 -> 2793916.1 | F43: =IF(C43>0,E43/C43,"n/a") -> 0.54177882 | G43: 1012075.8 | H43: 1118639.8 | I43: =C43-D43-G43-H43 -> 663200.47 | J43: =IF(C43>0,I43/C43,"n/a") -> 0.12860371 | K43: 42120.64 | L43: 14611.78 | M43: 52438.099 | N43: 1605 | O43: =IF(C42>0,C43/C42-1,"n/a") -> 0.0084184763
A45: Total Jan 2023 - Dec 2025 | C45: =SUM(C8:C43) -> 2.02649e+08 | D45: =SUM(D8:D43) -> 92808018 | E45: =C45-D45 -> 1.0984098e+08 | F45: =IF(C45>0,E45/C45,"n/a") -> 0.54202578 | G45: =SUM(G8:G43) -> 39708939 | H45: =SUM(H8:H43) -> 43812799 | I45: =C45-D45-G45-H45 -> 26319246 | J45: =IF(C45>0,I45/C45,"n/a") -> 0.12987602 | K45: =SUM(K8:K43) -> 1841552.1 | L45: =SUM(L8:L43) -> 595918.87 | M45: =SUM(M8:M43) -> 2751000.7 | N45: =SUM(N8:N43) -> 58340
A48: Calendar-year totals (formulas over the monthly table)
A49: Calendar year of the posting period. Growth = year / prior year - 1.
A50: Year | C50: Revenue (USD) | D50: COGS (USD) | E50: Gross profit S1 (USD) | F50: Gross margin % | G50: People (USD) | H50: Opex (USD) | I50: Operating result proxy (USD) | J50: Proxy margin % | K50: D&A memo (USD) | L50: Below-EBITDA memo (USD) | M50: Tax memo (USD) | N50: Eligible lines | O50: Revenue growth %
A51: 2023 | C51: =SUMIFS($C$8:$C$43,$B$8:$B$43,$A51) -> 61295631 | D51: =SUMIFS($D$8:$D$43,$B$8:$B$43,$A51) -> 28820262 | E51: =C51-D51 -> 32475369 | F51: =IF(C51>0,E51/C51,"n/a") -> 0.5298154 | G51: =SUMIFS($G$8:$G$43,$B$8:$B$43,$A51) -> 13384754 | H51: =SUMIFS($H$8:$H$43,$B$8:$B$43,$A51) -> 13453214 | I51: =C51-D51-G51-H51 -> 5637402.1 | J51: =IF(C51>0,I51/C51,"n/a") -> 0.0919707 | K51: =SUMIFS($K$8:$K$43,$B$8:$B$43,$A51) -> 557556.05 | L51: =SUMIFS($L$8:$L$43,$B$8:$B$43,$A51) -> 204276.68 | M51: =SUMIFS($M$8:$M$43,$B$8:$B$43,$A51) -> 984864.88 | N51: =SUMIFS($N$8:$N$43,$B$8:$B$43,$A51) -> 19518 | O51: n/a
A52: 2024 | C52: =SUMIFS($C$8:$C$43,$B$8:$B$43,$A52) -> 70362584 | D52: =SUMIFS($D$8:$D$43,$B$8:$B$43,$A52) -> 30243513 | E52: =C52-D52 -> 40119070 | F52: =IF(C52>0,E52/C52,"n/a") -> 0.5701762 | G52: =SUMIFS($G$8:$G$43,$B$8:$B$43,$A52) -> 13324774 | H52: =SUMIFS($H$8:$H$43,$B$8:$B$43,$A52) -> 14895617 | I52: =C52-D52-G52-H52 -> 11898679 | J52: =IF(C52>0,I52/C52,"n/a") -> 0.1691052 | K52: =SUMIFS($K$8:$K$43,$B$8:$B$43,$A52) -> 584497.19 | L52: =SUMIFS($L$8:$L$43,$B$8:$B$43,$A52) -> 193094.74 | M52: =SUMIFS($M$8:$M$43,$B$8:$B$43,$A52) -> 765343.56 | N52: =SUMIFS($N$8:$N$43,$B$8:$B$43,$A52) -> 19446 | O52: =C52/C51-1 -> 0.14792168
A53: 2025 | C53: =SUMIFS($C$8:$C$43,$B$8:$B$43,$A53) -> 70990788 | D53: =SUMIFS($D$8:$D$43,$B$8:$B$43,$A53) -> 33744243 | E53: =C53-D53 -> 37246545 | F53: =IF(C53>0,E53/C53,"n/a") -> 0.5246673 | G53: =SUMIFS($G$8:$G$43,$B$8:$B$43,$A53) -> 12999411 | H53: =SUMIFS($H$8:$H$43,$B$8:$B$43,$A53) -> 15463968 | I53: =C53-D53-G53-H53 -> 8783165.5 | J53: =IF(C53>0,I53/C53,"n/a") -> 0.12372261 | K53: =SUMIFS($K$8:$K$43,$B$8:$B$43,$A53) -> 699498.83 | L53: =SUMIFS($L$8:$L$43,$B$8:$B$43,$A53) -> 198547.45 | M53: =SUMIFS($M$8:$M$43,$B$8:$B$43,$A53) -> 1000792.2 | N53: =SUMIFS($N$8:$N$43,$B$8:$B$43,$A53) -> 19376 | O53: =C53/C52-1 -> 0.0089280979

Sheet Budget vs Actual
A1: Budget vs actual | M1: Back to Start Here
A2: USD, scale-adjusted (provisional), signs as recorded. Population: eligible P&L lines that also have a budget (55,043 lines). Sources: out_b1, out_b2, out_b3, out_b4, out_b7-b11.
A3: Definitions follow Phase 4 exactly: Variance = Actual - Budget. Variance % = Variance / |net budget|, published only when |net budget| >= 50% of the gross (absolute) budget (project convention, not an accounting standard). Primary basis = SAME-SIGN lines (actual and budget non-zero with the same sign). 'All lines' includes opposite-sign and zero-involved lines and is shown beside it. Nothing is labelled favourable or unfavourable: the sign convention (R9) is unresolved. Cost-centre variance is not published by Phase 4, so it is not shown.
A5: Net-budget guard (Phase 4 convention): | D5: 0.5 | E5: <- % is shown only when |net budget| / gross budget >= this value. Highlight threshold for |variance %|: | J5: 0.05
A7: A1. By section - SAME-SIGN lines (primary basis)
A8: Gross cell variance = sum of absolute entity x GL x month variances; it shows movements that offset inside the net figure.
A9: Section | B9: Lines (count) | C9: Actual (USD) | D9: Budget (USD) | E9: Net variance = actual - budget (USD) | F9: |Net budget| / gross budget | G9: Variance % of |budget| (guarded) | H9: Gross cell variance (USD) | I9: Gross variance % of gross budget | J9: Direction (arithmetic only)
A10: Revenue | B10: 27537 | C10: 1.9039672e+08 | D10: 1.9741975e+08 | E10: =C10-D10 -> -7023037.3 | F10: 0.97320187 | G10: =IF(AND(F10>=$D$5,D10<>0),E10/ABS(D10),"n/a (guard)") -> -0.035574137 | H10: 7090405 | I10: 0.034952913 | J10: =IF(E10>0,"Actual above budget",IF(E10<0,"Actual below budget","On budget")) -> Actual below budget
A11: COGS | B11: 10142 | C11: 87801326 | D11: 82505584 | E11: =C11-D11 -> 5295741.8 | F11: 0.96416508 | G11: =IF(AND(F11>=$D$5,D11<>0),E11/ABS(D11),"n/a (guard)") -> 0.064186465 | H11: 5490272.1 | I11: 0.064159642 | J11: =IF(E11>0,"Actual above budget",IF(E11<0,"Actual below budget","On budget")) -> Actual above budget
A12: People costs | B12: 2721 | C12: 38264640 | D12: 35971790 | E12: =C12-D12 -> 2292850.2 | F12: 0.98867738 | G12: =IF(AND(F12>=$D$5,D12<>0),E12/ABS(D12),"n/a (guard)") -> 0.063740232 | H12: 2333898 | I12: 0.064146716 | J12: =IF(E12>0,"Actual above budget",IF(E12<0,"Actual below budget","On budget")) -> Actual above budget
A13: Operating expenses | B13: 7125 | C13: 41457348 | D13: 38958919 | E13: =C13-D13 -> 2498428.7 | F13: 0.98175602 | G13: =IF(AND(F13>=$D$5,D13<>0),E13/ABS(D13),"n/a (guard)") -> 0.064129827 | H13: 2564626.6 | I13: 0.064628015 | J13: =IF(E13>0,"Actual above budget",IF(E13<0,"Actual below budget","On budget")) -> Actual above budget
A14: D&A (depreciation, GL 6300) | B14: 292 | C14: 1742110.1 | D14: 1638237.8 | E14: =C14-D14 -> 103872.29 | F14: 0.9287694 | G14: =IF(AND(F14>=$D$5,D14<>0),E14/ABS(D14),"n/a (guard)") -> 0.063404891 | H14: 114022.19 | I14: 0.064642826 | J14: =IF(E14>0,"Actual above budget",IF(E14<0,"Actual below budget","On budget")) -> Actual above budget
A15: Below-EBITDA items | B15: 589 | C15: 525074.46 | D15: 493909.02 | E15: =C15-D15 -> 31165.442 | F15: 0.68097347 | G15: =IF(AND(F15>=$D$5,D15<>0),E15/ABS(D15),"n/a (guard)") -> 0.063099561 | H15: 47619.12 | I15: 0.065654516 | J15: =IF(E15>0,"Actual above budget",IF(E15<0,"Actual below budget","On budget")) -> Actual above budget
A16: Tax | B16: 294 | C16: 2812303.9 | D16: 2645687.7 | E16: =C16-D16 -> 166616.19 | F16: 0.93056576 | G16: =IF(AND(F16>=$D$5,D16<>0),E16/ABS(D16),"n/a (guard)") -> 0.062976513 | H16: 178286.19 | I16: 0.062708467 | J16: =IF(E16>0,"Actual above budget",IF(E16<0,"Actual below budget","On budget")) -> Actual above budget
A19: A2. By section - ALL lines (sensitivity)
A20: Gross cell variance = sum of absolute entity x GL x month variances; it shows movements that offset inside the net figure.
A21: Section | B21: Lines (count) | C21: Actual (USD) | D21: Budget (USD) | E21: Net variance = actual - budget (USD) | F21: |Net budget| / gross budget | G21: Variance % of |budget| (guarded) | H21: Gross cell variance (USD) | I21: Gross variance % of gross budget | J21: Direction (arithmetic only)
A22: Revenue | B22: 30953 | C22: 1.9162786e+08 | D22: 1.9629377e+08 | E22: =C22-D22 -> -4665907.5 | F22: 0.9703321 | G22: =IF(AND(F22>=$D$5,D22<>0),E22/ABS(D22),"n/a (guard)") -> -0.023770023 | H22: 29639085 | I22: 0.14651384 | J22: =IF(E22>0,"Actual above budget",IF(E22<0,"Actual below budget","On budget")) -> Actual below budget
A23: COGS | B23: 11517 | C23: 87563589 | D23: 82756590 | E23: =C23-D23 -> 4806999.4 | F23: 0.94122874 | G23: =IF(AND(F23>=$D$5,D23<>0),E23/ABS(D23),"n/a (guard)") -> 0.058086002 | H23: 18631524 | I23: 0.21190489 | J23: =IF(E23>0,"Actual above budget",IF(E23<0,"Actual below budget","On budget")) -> Actual above budget
A24: People costs | B24: 3101 | C24: 37123068 | D24: 37083624 | E24: =C24-D24 -> 39443.735 | F24: 0.98347432 | G24: =IF(AND(F24>=$D$5,D24<>0),E24/ABS(D24),"n/a (guard)") -> 0.001063643 | H24: 11007528 | I24: 0.29192457 | J24: =IF(E24>0,"Actual above budget",IF(E24<0,"Actual below budget","On budget")) -> Actual above budget
A25: Operating expenses | B25: 8153 | C25: 41160730 | D25: 39236310 | E25: =C25-D25 -> 1924419.9 | F25: 0.96402203 | G25: =IF(AND(F25>=$D$5,D25<>0),E25/ABS(D25),"n/a (guard)") -> 0.049046913 | H25: 13214431 | I25: 0.32467383 | J25: =IF(E25>0,"Actual above budget",IF(E25<0,"Actual below budget","On budget")) -> Actual above budget
A26: D&A (depreciation, GL 6300) | B26: 325 | C26: 1762454.8 | D26: 1621481.1 | E26: =C26-D26 -> 140973.73 | F26: 0.88251888 | G26: =IF(AND(F26>=$D$5,D26<>0),E26/ABS(D26),"n/a (guard)") -> 0.086941336 | H26: 622029.65 | I26: 0.33855031 | J26: =IF(E26>0,"Actual above budget",IF(E26<0,"Actual below budget","On budget")) -> Actual above budget
A27: Below-EBITDA items | B27: 655 | C27: 539704.35 | D27: 481316.27 | E27: =C27-D27 -> 58388.08 | F27: 0.61113906 | G27: =IF(AND(F27>=$D$5,D27<>0),E27/ABS(D27),"n/a (guard)") -> 0.12130917 | H27: 288305.13 | I27: 0.36606809 | J27: =IF(E27>0,"Actual above budget",IF(E27<0,"Actual below budget","On budget")) -> Actual above budget
A28: Tax | B28: 339 | C28: 2715839.9 | D28: 2750950 | E28: =C28-D28 -> -35110.036 | F28: 0.90110569 | G28: =IF(AND(F28>=$D$5,D28<>0),E28/ABS(D28),"n/a (guard)") -> -0.012762877 | H28: 955020.04 | I28: 0.31282793 | J28: =IF(E28>0,"Actual above budget",IF(E28<0,"Actual below budget","On budget")) -> Actual below budget
A31: A3. Bridge: all-lines net variance = same-sign + opposite-sign + zero-involved (out_b8)
A32: Opposite-sign and zero-involved lines are an observation, not a proven error: credit notes, reversals and contra accounts can legitimately differ in sign. They are kept, never flipped or removed.
A33: Section | B33: All lines net variance (USD) | C33: Same-sign (USD) | D33: Opposite-sign (USD) | E33: Zero-involved (USD) | F33: Bridge difference (USD) = all - (same + opposite + zero)
A34: Revenue | B34: -4665907.5 | C34: -7023037.3 | D34: 2361269.7 | E34: -4140 | F34: =B34-(C34+D34+E34) -> -7.4505806e-09
A35: COGS | B35: 4806999.4 | C35: 5295741.8 | D35: -453472.72 | E35: -35269.65 | F35: =B35-(C35+D35+E35) -> -9.3132257e-10
A36: People costs | B36: 39443.735 | C36: 2292850.2 | D36: -2264166.5 | E36: 10760 | F36: =B36-(C36+D36+E36) -> -4.9039954e-09
A37: Operating expenses | B37: 1924419.9 | C37: 2498428.7 | D37: -610688.8 | E37: 36679.92 | F37: =B37-(C37+D37+E37) -> 9.5460564e-09
A38: D&A (depreciation, GL 6300) | B38: 140973.73 | C38: 103872.29 | D38: 37101.44 | E38: 0 | F38: =B38-(C38+D38+E38) -> -2.910383e-11
A39: Below-EBITDA items | B39: 58388.08 | C39: 31165.442 | D39: 27222.637 | E39: 0 | F39: =B39-(C39+D39+E39) -> 0
A40: Tax | B40: -35110.036 | C40: 166616.19 | D40: -217726.22 | E40: 16000 | F40: =B40-(C40+D40+E40) -> -1.0913936e-10
A43: B. Largest entity x GL contributors to the variance - same-sign basis (top 20 by |variance|)
A44: Net variance can hide offsetting cells; 'Share of section gross cell variance' shows each cell's weight against the section's gross movement (Phase 4 out_b2).
A45: Rank by |variance| | B45: Section | C45: Entity | D45: GL | E45: Account | F45: Actual (USD) | G45: Budget (USD) | H45: Variance (USD) | I45: Variance % (Phase 4) | J45: Share of section gross cell variance | K45: Direction (arithmetic only)
A46: 1 | B46: Revenue | C46: US01 | D46: 4100 | E46: Product sales | F46: 45163684 | G46: 46799586 | H46: =F46-G46 -> -1635901.6 | I46: -0.034955471 | J46: 0.23293363 | K46: =IF(H46>0,"Actual above budget",IF(H46<0,"Actual below budget","On budget")) -> Actual below budget
A47: 2 | B47: Revenue | C47: IN01 | D47: 4100 | E47: Product sales | F47: 39062316 | G47: 40431207 | H47: =F47-G47 -> -1368891.5 | I47: -0.0338573 | J47: 0.19491446 | K47: =IF(H47>0,"Actual above budget",IF(H47<0,"Actual below budget","On budget")) -> Actual below budget
A48: 3 | B48: COGS | C48: US01 | D48: 5100 | E48: Materials | F48: 16784899 | G48: 15775213 | H48: =F48-G48 -> 1009686.6 | I48: 0.064004623 | J48: 0.19061869 | K48: =IF(H48>0,"Actual above budget",IF(H48<0,"Actual below budget","On budget")) -> Actual above budget
A49: 4 | B49: COGS | C49: IN01 | D49: 5100 | E49: Materials | F49: 14552123 | G49: 13687720 | H49: =F49-G49 -> 864403.33 | I49: 0.063151742 | J49: 0.16319068 | K49: =IF(H49>0,"Actual above budget",IF(H49<0,"Actual below budget","On budget")) -> Actual above budget
A50: 5 | B50: Revenue | C50: SG01 | D50: 4100 | E50: Product sales | F50: 22882185 | G50: 23743615 | H50: =F50-G50 -> -861430.45 | I50: -0.036280509 | J50: 0.12265782 | K50: =IF(H50>0,"Actual above budget",IF(H50<0,"Actual below budget","On budget")) -> Actual below budget
A51: 6 | B51: Revenue | C51: DE01 | D51: 4100 | E51: Product sales | F51: 23532211 | G51: 24390096 | H51: =F51-G51 -> -857884.85 | I51: -0.035173493 | J51: 0.12215297 | K51: =IF(H51>0,"Actual above budget",IF(H51<0,"Actual below budget","On budget")) -> Actual below budget
A52: 7 | B52: COGS | C52: DE01 | D52: 5100 | E52: Materials | F52: 9983483 | G52: 9378766.2 | H52: =F52-G52 -> 604716.73 | I52: 0.064477216 | J52: 0.11416445 | K52: =IF(H52>0,"Actual above budget",IF(H52<0,"Actual below budget","On budget")) -> Actual above budget
A53: 8 | B53: Revenue | C53: AE01 | D53: 4100 | E53: Product sales | F53: 16515293 | G53: 17116953 | H53: =F53-G53 -> -601660.13 | I53: -0.035149956 | J53: 0.085669505 | K53: =IF(H53>0,"Actual above budget",IF(H53<0,"Actual below budget","On budget")) -> Actual below budget
A54: 9 | B54: Revenue | C54: GB01 | D54: 4100 | E54: Product sales | F54: 16378412 | G54: 16964616 | H54: =F54-G54 -> -586204.91 | I54: -0.034554563 | J54: 0.083468859 | K54: =IF(H54>0,"Actual above budget",IF(H54<0,"Actual below budget","On budget")) -> Actual below budget
A55: 10 | B55: COGS | C55: SG01 | D55: 5100 | E55: Materials | F55: 9110414.1 | G55: 8550728.7 | H55: =F55-G55 -> 559685.42 | I55: 0.065454704 | J55: 0.10566299 | K55: =IF(H55>0,"Actual above budget",IF(H55<0,"Actual below budget","On budget")) -> Actual above budget
A56: 11 | B56: COGS | C56: GB01 | D56: 5100 | E56: Materials | F56: 6386101.4 | G56: 5993368.1 | H56: =F56-G56 -> 392733.31 | I56: 0.065527982 | J56: 0.074144109 | K56: =IF(H56>0,"Actual above budget",IF(H56<0,"Actual below budget","On budget")) -> Actual above budget
A57: 12 | B57: People costs | C57: US01 | D57: 6100 | E57: Salaries | F57: 6326715.9 | G57: 5944851.8 | H57: =F57-G57 -> 381864.12 | I57: 0.064234423 | J57: 0.1665456 | K57: =IF(H57>0,"Actual above budget",IF(H57<0,"Actual below budget","On budget")) -> Actual above budget
... A65: 20 | B65: People costs | C65: GB01 | D65: 6100 | E65: Salaries | F65: 2999600 | G65: 2831926.5 | H65: =F65-G65 -> 167673.52 | I65: 0.059208289 | J65: 0.073128859 | K65: =IF(H65>0,"Actual above budget",IF(H65<0,"Actual below budget","On budget")) -> Actual above budget
A68: C. How sensitive is 'what counts as material'? (out_b9, out_b10, out_b11)
A69: Phase 4 materiality thresholds are project conventions, not standards. The tables show how many entity x GL cells fall above each threshold, and how much of the total absolute variance they cover.
A70: Basis | B70: Cell share of total |variance| >= | C70: Cells at/above (count) | D70: Share of total |variance| covered | G70: Basis | H70: |Variance| >= % of cell gross budget | I70: Cells at/above (count) | J70: Cells not scored (count) | K70: Cells total (count) | L70: Share of total |variance| in flagged cells
A71: Same-sign | B71: 0.0025 | C71: 69 | D71: 0.91251175 | G71: Same-sign | H71: 0.005 | I71: 138 | J71: 0 | K71: 144 | L71: 0.99837304
A72: Same-sign | B72: 0.005 | C72: 38 | D72: 0.79860953 | G72: Same-sign | H72: 0.01 | I72: 133 | J72: 0 | K72: 144 | L72: 0.99635892
A73: Same-sign | B73: 0.01 | C73: 19 | D73: 0.6706273 | G73: Same-sign | H73: 0.02 | I73: 130 | J73: 0 | K73: 144 | L73: 0.99613802
A74: Same-sign | B74: 0.02 | C74: 14 | D74: 0.60108179 | G74: Same-sign | H74: 0.05 | I74: 86 | J74: 0 | K74: 144 | L74: 0.53867366
A75: Same-sign | B75: 0.05 | C75: 3 | D75: 0.23049617 | G75: Same-sign | H75: 0.1 | I75: 0 | J75: 0 | K75: 144
A76: All lines | B76: 0.0025 | C76: 78 | D76: 0.9396246 | G76: All lines | H76: 0.005 | I76: 138 | J76: 0 | K76: 144 | L76: 0.99344027
A77: All lines | B77: 0.005 | C77: 54 | D77: 0.85348106 | G77: All lines | H77: 0.01 | I77: 128 | J77: 0 | K77: 144 | L77: 0.99059126
A78: All lines | B78: 0.01 | C78: 26 | D78: 0.65579258 | G78: All lines | H78: 0.02 | I78: 105 | J78: 0 | K78: 144 | L78: 0.90340767
A79: All lines | B79: 0.02 | C79: 11 | D79: 0.44432099 | G79: All lines | H79: 0.05 | I79: 67 | J79: 0 | K79: 144 | L79: 0.51597109
A80: All lines | B80: 0.05 | C80: 2 | D80: 0.16375111 | G80: All lines | H80: 0.1 | I80: 31 | J80: 0 | K80: 144 | L80: 0.24327616
A82: Top-10 cell overlap between the all-lines and same-sign views: 8 of 10 cells are in both lists (out_b10). The ranking is stable enough to read the concentration, not stable enough to rely on a single cell.
A85: D. Monthly variance by section (out_b4; filter by Basis and Section)
A86: Variance recomputed in Excel; 'Phase 4 %' is the guarded published figure (blank = suppressed by the guard); 'Recomputed %' is variance/|budget| with no guard, shown so the two can be compared. Check = OK when they agree.
A87: Basis | B87: Section | C87: Month | D87: Lines (count) | E87: Actual (USD) | F87: Budget (USD) | G87: Variance (USD) | H87: Phase 4 variance % (guarded) | I87: Recomputed % (no guard) | J87: Check
A88: Same-sign | B88: REVENUE | C88: 44927 | D88: 770 | E88: 4006977.1 | F88: 4145927.6 | G88: =E88-F88 -> -138950.52 | H88: -0.033514942 | I88: =IF(F88<>0,G88/ABS(F88),"n/a") -> -0.033514942 | J88: =IF(H88="","guard",IF(ABS(H88-I88)<0.000001,"OK","DIFF")) -> OK
A89: Same-sign | B89: REVENUE | C89: 44958 | D89: 785 | E89: 4750459.7 | F89: 4932440.7 | G89: =E89-F89 -> -181981.02 | H89: -0.03689472 | I89: =IF(F89<>0,G89/ABS(F89),"n/a") -> -0.03689472 | J89: =IF(H89="","guard",IF(ABS(H89-I89)<0.000001,"OK","DIFF")) -> OK
A90: Same-sign | B90: REVENUE | C90: 44986 | D90: 754 | E90: 4184101.1 | F90: 4347648.6 | G90: =E90-F90 -> -163547.45 | H90: -0.037617449 | I90: =IF(F90<>0,G90/ABS(F90),"n/a") -> -0.037617449 | J90: =IF(H90="","guard",IF(ABS(H90-I90)<0.000001,"OK","DIFF")) -> OK
A91: Same-sign | B91: REVENUE | C91: 45017 | D91: 765 | E91: 5151502.1 | F91: 5337285 | G91: =E91-F91 -> -185782.83 | H91: -0.03480849 | I91: =IF(F91<>0,G91/ABS(F91),"n/a") -> -0.03480849 | J91: =IF(H91="","guard",IF(ABS(H91-I91)<0.000001,"OK","DIFF")) -> OK
A92: Same-sign | B92: REVENUE | C92: 45047 | D92: 756 | E92: 5138693.2 | F92: 5335455.4 | G92: =E92-F92 -> -196762.26 | H92: -0.03687825 | I92: =IF(F92<>0,G92/ABS(F92),"n/a") -> -0.03687825 | J92: =IF(H92="","guard",IF(ABS(H92-I92)<0.000001,"OK","DIFF")) -> OK
A93: Same-sign | B93: REVENUE | C93: 45078 | D93: 768 | E93: 5317946.4 | F93: 5513478.1 | G93: =E93-F93 -> -195531.71 | H93: -0.035464311 | I93: =IF(F93<>0,G93/ABS(F93),"n/a") -> -0.035464311 | J93: =IF(H93="","guard",IF(ABS(H93-I93)<0.000001,"OK","DIFF")) -> OK
A94: Same-sign | B94: REVENUE | C94: 45108 | D94: 791 | E94: 6012950.1 | F94: 6248757.8 | G94: =E94-F94 -> -235807.65 | H94: -0.037736724 | I94: =IF(F94<>0,G94/ABS(F94),"n/a") -> -0.037736724 | J94: =IF(H94="","guard",IF(ABS(H94-I94)<0.000001,"OK","DIFF")) -> OK
A95: Same-sign | B95: REVENUE | C95: 45139 | D95: 756 | E95: 4877792.4 | F95: 5048531 | G95: =E95-F95 -> -170738.65 | H95: -0.033819472 | I95: =IF(F95<>0,G95/ABS(F95),"n/a") -> -0.033819472 | J95: =IF(H95="","guard",IF(ABS(H95-I95)<0.000001,"OK","DIFF")) -> OK
A96: Same-sign | B96: REVENUE | C96: 45170 | D96: 739 | E96: 4745365.6 | F96: 4925483.8 | G96: =E96-F96 -> -180118.2 | H96: -0.036568631 | I96: =IF(F96<>0,G96/ABS(F96),"n/a") -> -0.036568631 | J96: =IF(H96="","guard",IF(ABS(H96-I96)<0.000001,"OK","DIFF")) -> OK
A97: Same-sign | B97: REVENUE | C97: 45200 | D97: 754 | E97: 4591634 | F97: 4759171.7 | G97: =E97-F97 -> -167537.66 | H97: -0.035203113 | I97: =IF(F97<>0,G97/ABS(F97),"n/a") -> -0.035203113 | J97: =IF(H97="","guard",IF(ABS(H97-I97)<0.000001,"OK","DIFF")) -> OK
A98: Same-sign | B98: REVENUE | C98: 45231 | D98: 747 | E98: 4639979 | F98: 4804950.4 | G98: =E98-F98 -> -164971.42 | H98: -0.034333636 | I98: =IF(F98<>0,G98/ABS(F98),"n/a") -> -0.034333636 | J98: =IF(H98="","guard",IF(ABS(H98-I98)<0.000001,"OK","DIFF")) -> OK
A99: Same-sign | B99: REVENUE | C99: 45261 | D99: 763 | E99: 4305996.1 | F99: 4468705.3 | G99: =E99-F99 -> -162709.21 | H99: -0.036410816 | I99: =IF(F99<>0,G99/ABS(F99),"n/a") -> -0.036410816 | J99: =IF(H99="","guard",IF(ABS(H99-I99)<0.000001,"OK","DIFF")) -> OK
... A246: Same-sign | B246: D&A | C246: 45352 | D246: 7 | E246: 40640.24 | F246: 37378.279 | G246: =E246-F246 -> 3261.9605 | H246: 0.087268878 | I246: =IF(F246<>0,G246/ABS(F246),"n/a") -> 0.087268878 | J246: =IF(H246="","guard",IF(ABS(H246-I246)<0.000001,"OK","DIFF")) -> OK
A247: Same-sign | B247: D&A | C247: 45383 | D247: 6 | E247: 9432.5 | F247: 8838.8 | G247: =E247-F247 -> 593.7 | I247: =IF(F247<>0,G247/ABS(F247),"n/a") -> 0.067169752 | J247: =IF(H247="","guard",IF(ABS(H247-I247)<0.000001,"OK","DIFF")) -> guard
A248: Same-sign | B248: D&A | C248: 45413 | D248: 7 | E248: 23890.47 | F248: 22379.19 | G248: =E248-F248 -> 1511.28 | I248: =IF(F248<>0,G248/ABS(F248),"n/a") -> 0.067530594 | J248: =IF(H248="","guard",IF(ABS(H248-I248)<0.000001,"OK","DIFF")) -> guard
A249: Same-sign | B249: D&A | C249: 45444 | D249: 9 | E249: 66853.411 | F249: 61666.85 | G249: =E249-F249 -> 5186.5612 | H249: 0.084106148 | I249: =IF(F249<>0,G249/ABS(F249),"n/a") -> 0.084106148 | J249: =IF(H249="","guard",IF(ABS(H249-I249)<0.000001,"OK","DIFF")) -> OK
A250: Same-sign | B250: D&A | C250: 45474 | D250: 8 | E250: 51567.684 | F250: 49223.65 | G250: =E250-F250 -> 2344.0343 | H250: 0.047620083 | I250: =IF(F250<>0,G250/ABS(F250),"n/a") -> 0.047620083 | J250: =IF(H250="","guard",IF(ABS(H250-I250)<0.000001,"OK","DIFF")) -> OK
A251: Same-sign | B251: D&A | C251: 45505 | D251: 7 | E251: 50942.81 | F251: 47425.2 | G251: =E251-F251 -> 3517.61 | H251: 0.074171748 | I251: =IF(F251<>0,G251/ABS(F251),"n/a") -> 0.074171748 | J251: =IF(H251="","guard",IF(ABS(H251-I251)<0.000001,"OK","DIFF")) -> OK
A252: Same-sign | B252: D&A | C252: 45536 | D252: 11 | E252: 89536.937 | F252: 85413.82 | G252: =E252-F252 -> 4123.1172 | H252: 0.048272249 | I252: =IF(F252<>0,G252/ABS(F252),"n/a") -> 0.048272249 | J252: =IF(H252="","guard",IF(ABS(H252-I252)<0.000001,"OK","DIFF")) -> OK
A253: Same-sign | B253: D&A | C253: 45566 | D253: 8 | E253: 8438.17 | F253: 7880.75 | G253: =E253-F253 -> 557.42 | I253: =IF(F253<>0,G253/ABS(F253),"n/a") -> 0.070731847 | J253: =IF(H253="","guard",IF(ABS(H253-I253)<0.000001,"OK","DIFF")) -> guard
A254: Same-sign | B254: D&A | C254: 45597 | D254: 6 | E254: 50088.115 | F254: 46551.04 | G254: =E254-F254 -> 3537.0745 | H254: 0.075982717 | I254: =IF(F254<>0,G254/ABS(F254),"n/a") -> 0.075982717 | J254: =IF(H254="","guard",IF(ABS(H254-I254)<0.000001,"OK","DIFF")) -> OK
A255: Same-sign | B255: D&A | C255: 45627 | D255: 7 | E255: 38973.461 | F255: 37166.79 | G255: =E255-F255 -> 1806.6713 | H255: 0.048609829 | I255: =IF(F255<>0,G255/ABS(F255),"n/a") -> 0.048609829 | J255: =IF(H255="","guard",IF(ABS(H255-I255)<0.000001,"OK","DIFF")) -> OK
A256: Same-sign | B256: D&A | C256: 45658 | D256: 4 | E256: 20080.55 | F256: 18829.73 | G256: =E256-F256 -> 1250.82 | H256: 0.066427931 | I256: =IF(F256<>0,G256/ABS(F256),"n/a") -> 0.066427931 | J256: =IF(H256="","guard",IF(ABS(H256-I256)<0.000001,"OK","DIFF")) -> OK
A257: Same-sign | B257: D&A | C257: 45689 | D257: 12 | E257: 71541.23 | F257: 67437.63 | G257: =E257-F257 -> 4103.6 | H257: 0.0608503 | I257: =IF(F257<>0,G257/ABS(F257),"n/a") -> 0.0608503 | J257: =IF(H257="","guard",IF(ABS(H257-I257)<0.000001,"OK","DIFF")) -> OK
A258: Same-sign | B258: D&A | C258: 45717 | D258: 10 | E258: 88499.99 | F258: 83286.917 | G258: =E258-F258 -> 5213.0735 | H258: 0.062591746 | I258: =IF(F258<>0,G258/ABS(F258),"n/a") -> 0.062591746 | J258: =IF(H258="","guard",IF(ABS(H258-I258)<0.000001,"OK","DIFF")) -> OK
A259: Same-sign | B259: D&A | C259: 45748 | D259: 6 | E259: 69630.1 | F259: 65483.325 | G259: =E259-F259 -> 4146.7745 | H259: 0.063325655 | I259: =IF(F259<>0,G259/ABS(F259),"n/a") -> 0.063325655 | J259: =IF(H259="","guard",IF(ABS(H259-I259)<0.000001,"OK","DIFF")) -> OK
A260: Same-sign | B260: D&A | C260: 45778 | D260: 7 | E260: 49919.97 | F260: 46503.21 | G260: =E260-F260 -> 3416.76 | H260: 0.073473638 | I260: =IF(F260<>0,G260/ABS(F260),"n/a") -> 0.073473638 | J260: =IF(H260="","guard",IF(ABS(H260-I260)<0.000001,"OK","DIFF")) -> OK
A261: Same-sign | B261: D&A | C261: 45809 | D261: 9 | E261: 85958.049 | F261: 81575.11 | G261: =E261-F261 -> 4382.9395 | H261: 0.053728883 | I261: =IF(F261<>0,G261/ABS(F261),"n/a") -> 0.053728883 | J261: =IF(H261="","guard",IF(ABS(H261-I261)<0.000001,"OK","DIFF")) -> OK
A262: Same-sign | B262: D&A | C262: 45839 | D262: 9 | E262: 56797.332 | F262: 54101.236 | G262: =E262-F262 -> 2696.0966 | H262: 0.049834289 | I262: =IF(F262<>0,G262/ABS(F262),"n/a") -> 0.049834289 | J262: =IF(H262="","guard",IF(ABS(H262-I262)<0.000001,"OK","DIFF")) -> OK
A263: Same-sign | B263: D&A | C263: 45870 | D263: 7 | E263: 40114.359 | F263: 38468.553 | G263: =E263-F263 -> 1645.8062 | H263: 0.042783159 | I263: =IF(F263<>0,G263/ABS(F263),"n/a") -> 0.042783159 | J263: =IF(H263="","guard",IF(ABS(H263-I263)<0.000001,"OK","DIFF")) -> OK
A264: Same-sign | B264: D&A | C264: 45901 | D264: 10 | E264: 69403.94 | F264: 65693.98 | G264: =E264-F264 -> 3709.96 | H264: 0.056473363 | I264: =IF(F264<>0,G264/ABS(F264),"n/a") -> 0.056473363 | J264: =IF(H264="","guard",IF(ABS(H264-I264)<0.000001,"OK","DIFF")) -> OK
A265: Same-sign | B265: D&A | C265: 45931 | D265: 8 | E265: 57942.321 | F265: 54097.19 | G265: =E265-F265 -> 3845.1308 | H265: 0.071078198 | I265: =IF(F265<>0,G265/ABS(F265),"n/a") -> 0.071078198 | J265: =IF(H265="","guard",IF(ABS(H265-I265)<0.000001,"OK","DIFF")) -> OK
... A267: Same-sign | B267: D&A | C267: 45992 | D267: 7 | E267: 34635.77 | F267: 32586.08 | G267: =E267-F267 -> 2049.69 | H267: 0.062900785 | I267: =IF(F267<>0,G267/ABS(F267),"n/a") -> 0.062900785 | J267: =IF(H267="","guard",IF(ABS(H267-I267)<0.000001,"OK","DIFF")) -> OK
...

Sheet Forecast & Prior Year
A1: Forecast and prior-year analysis | L1: Back to Start Here
A2: USD, scale-adjusted (provisional), signs as recorded. Forecast error = Forecast - Actual. WAPE = sum|F-A| / sum|A|. Bias = sum(F-A) / sum|A|. Sources: out_c1-c8, out_d1-d5.
A3: THREE DIFFERENT THINGS - do not blur them. (1) Observed: the forecast column differs from actuals by the amounts shown. (2) A historical forecasting-performance measure would need dated forecast snapshots: the extract has NO forecast version or as-of date, so forecast skill, forecast accuracy as a KPI and any bias correction are NOT established here. (3) Business explanations (a late re-forecast, a mechanically derived forecast, planning optimism) are hypotheses. Population: eligible P&L lines with a forecast value; the prior-year COLUMN is not the prior calendar year's actuals (see F6).
A5: F1. Forecast vs actual - SAME-SIGN lines (actual and forecast non-zero, same sign)
A6: Net error = forecast - actual (positive = forecast above actual). Bias and WAPE recomputed from Phase 4 inputs (net error, absolute error and absolute actual).
A7: Section | B7: Lines (count) | C7: Actual (USD) | D7: Forecast (USD) | E7: Net error = forecast - actual (USD) | F7: Absolute error sum (USD) | G7: Absolute actual sum (USD) | H7: Bias = net error / abs actual | I7: WAPE = abs error / abs actual | J7: Observed direction
A8: Revenue | B8: 27593 | C8: 1.9173109e+08 | D8: 1.952144e+08 | E8: =D8-C8 -> 3483312.7 | F8: 5505538.3 | G8: 2.1144577e+08 | H8: =IF(G8>0,E8/G8,"n/a") -> 0.016473787 | I8: =IF(G8>0,F8/G8,"n/a") -> 0.02603759 | J8: =IF(E8>0,"Forecast above actual",IF(E8<0,"Forecast below actual","Equal")) -> Forecast above actual
A9: COGS | B9: 10051 | C9: 87006529 | D9: 84342693 | E9: =D9-C9 -> -2663835.2 | F9: 3600247.2 | G9: 1.0507826e+08 | H9: =IF(G9>0,E9/G9,"n/a") -> -0.025350965 | I9: =IF(G9>0,F9/G9,"n/a") -> 0.034262532 | J9: =IF(E9>0,"Forecast above actual",IF(E9<0,"Forecast below actual","Equal")) -> Forecast below actual
A10: People costs | B10: 2690 | C10: 37742906 | D10: 36607976 | E10: =D10-C10 -> -1134929.4 | F10: 1513623.1 | G10: 44889275 | H10: =IF(G10>0,E10/G10,"n/a") -> -0.025282864 | I10: =IF(G10>0,F10/G10,"n/a") -> 0.033719035 | J10: =IF(E10>0,"Forecast above actual",IF(E10<0,"Forecast below actual","Equal")) -> Forecast below actual
A11: Operating expenses | B11: 7048 | C11: 41408223 | D11: 40141629 | E11: =D11-C11 -> -1266594 | F11: 1703776.8 | G11: 49859051 | H11: =IF(G11>0,E11/G11,"n/a") -> -0.025403491 | I11: =IF(G11>0,F11/G11,"n/a") -> 0.034171866 | J11: =IF(E11>0,"Forecast above actual",IF(E11<0,"Forecast below actual","Equal")) -> Forecast below actual
A12: D&A (depreciation, GL 6300) | B12: 291 | C12: 1706887.7 | D12: 1653528 | E12: =D12-C12 -> -53359.791 | F12: 72067.823 | G12: 2018086.5 | H12: =IF(G12>0,E12/G12,"n/a") -> -0.026440785 | I12: =IF(G12>0,F12/G12,"n/a") -> 0.035710969 | J12: =IF(E12>0,"Forecast above actual",IF(E12<0,"Forecast below actual","Equal")) -> Forecast below actual
A13: Below-EBITDA items | B13: 588 | C13: 573571.01 | D13: 556448.34 | E13: =D13-C13 -> -17122.67 | F13: 31016.526 | G13: 898734.53 | H13: =IF(G13>0,E13/G13,"n/a") -> -0.019051978 | I13: =IF(G13>0,F13/G13,"n/a") -> 0.034511332 | J13: =IF(E13>0,"Forecast above actual",IF(E13<0,"Forecast below actual","Equal")) -> Forecast below actual
A14: Tax | B14: 273 | C14: 2404993 | D14: 2336093.7 | E14: =D14-C14 -> -68899.301 | F14: 95908.071 | G14: 2867875.1 | H14: =IF(G14>0,E14/G14,"n/a") -> -0.024024513 | I14: =IF(G14>0,F14/G14,"n/a") -> 0.033442207 | J14: =IF(E14>0,"Forecast above actual",IF(E14<0,"Forecast below actual","Equal")) -> Forecast below actual
A17: F2. Forecast vs actual - ALL lines
A18: Net error = forecast - actual (positive = forecast above actual). Bias and WAPE recomputed from Phase 4 inputs (net error, absolute error and absolute actual).
A19: Section | B19: Lines (count) | C19: Actual (USD) | D19: Forecast (USD) | E19: Net error = forecast - actual (USD) | F19: Absolute error sum (USD) | G19: Absolute actual sum (USD) | H19: Bias = net error / abs actual | I19: WAPE = abs error / abs actual | J19: Observed direction
A20: Revenue | B20: 30879 | C20: 1.9171908e+08 | D20: 1.952756e+08 | E20: =D20-C20 -> 3556516.2 | F20: 63934715 | G20: 2.4042821e+08 | H20: =IF(G20>0,E20/G20,"n/a") -> 0.014792425 | I20: =IF(G20>0,F20/G20,"n/a") -> 0.2659202 | J20: =IF(E20>0,"Forecast above actual",IF(E20<0,"Forecast below actual","Equal")) -> Forecast above actual
A21: COGS | B21: 11443 | C21: 86904916 | D21: 84491282 | E21: =D21-C21 -> -2413633.4 | F21: 32296581 | G21: 1.1963614e+08 | H21: =IF(G21>0,E21/G21,"n/a") -> -0.020174785 | I21: =IF(G21>0,F21/G21,"n/a") -> 0.26995672 | J21: =IF(E21>0,"Forecast above actual",IF(E21<0,"Forecast below actual","Equal")) -> Forecast below actual
A22: People costs | B22: 3102 | C22: 37478988 | D22: 36857250 | E22: =D22-C22 -> -621737.97 | F22: 15204991 | G22: 51844399 | H22: =IF(G22>0,E22/G22,"n/a") -> -0.011992385 | I22: =IF(G22>0,F22/G22,"n/a") -> 0.29328126 | J22: =IF(E22>0,"Forecast above actual",IF(E22<0,"Forecast below actual","Equal")) -> Forecast below actual
A23: Operating expenses | B23: 8119 | C23: 40927995 | D23: 40599946 | E23: =D23-C23 -> -328049.77 | F23: 15905906 | G23: 57064671 | H23: =IF(G23>0,E23/G23,"n/a") -> -0.0057487368 | I23: =IF(G23>0,F23/G23,"n/a") -> 0.27873473 | J23: =IF(E23>0,"Forecast above actual",IF(E23<0,"Forecast below actual","Equal")) -> Forecast below actual
A24: D&A (depreciation, GL 6300) | B24: 335 | C24: 1739141.3 | D24: 1640330.7 | E24: =D24-C24 -> -98810.641 | F24: 672444.79 | G24: 2329898.3 | H24: =IF(G24>0,E24/G24,"n/a") -> -0.042409852 | I24: =IF(G24>0,F24/G24,"n/a") -> 0.28861551 | J24: =IF(E24>0,"Forecast above actual",IF(E24<0,"Forecast below actual","Equal")) -> Forecast below actual
A25: Below-EBITDA items | B25: 648 | C25: 574242.67 | D25: 554901.34 | E25: =D25-C25 -> -19341.327 | F25: 253860.43 | G25: 1011565.5 | H25: =IF(G25>0,E25/G25,"n/a") -> -0.019120194 | I25: =IF(G25>0,F25/G25,"n/a") -> 0.25095799 | J25: =IF(E25>0,"Forecast above actual",IF(E25<0,"Forecast below actual","Equal")) -> Forecast below actual
A26: Tax | B26: 325 | C26: 2536774.7 | D26: 2204434 | E26: =D26-C26 -> -332340.75 | F26: 1285776.2 | G26: 3471849.7 | H26: =IF(G26>0,E26/G26,"n/a") -> -0.095724407 | I26: =IF(G26>0,F26/G26,"n/a") -> 0.37034327 | J26: =IF(E26>0,"Forecast above actual",IF(E26<0,"Forecast below actual","Equal")) -> Forecast below actual
A29: F3. Is the forecast closer to actuals than the budget? Matched lines only (out_c6)
A30: Same lines for both measures: actual, budget and forecast all non-zero with the same sign. This population is selected by outcome (it drops the opposite-sign lines that carry most of the error - see F4), so the improvement is a statement about these lines only.
A31: Section | B31: Matched lines (count) | C31: WAPE forecast | D31: WAPE budget | E31: Budget WAPE - forecast WAPE (points) | F31: Bias forecast | G31: Bias budget
A32: Revenue | B32: 24372 | C32: 0.02587993 | D32: 0.03666117 | E32: =D32-C32 -> 0.01078124 | F32: 0.016463783 | G32: 0.033897031
A33: COGS | B33: 8837 | C33: 0.034384802 | D33: 0.060005975 | E33: =D33-C33 -> 0.025621173 | F33: -0.025256104 | G33: -0.04970263
A34: People costs | B34: 2370 | C34: 0.033486976 | D34: 0.061206509 | E34: =D34-C34 -> 0.027719533 | F34: -0.024590215 | G34: -0.050526803
A35: Operating expenses | B35: 6186 | C35: 0.034507893 | D35: 0.060635221 | E35: =D35-C35 -> 0.026127328 | F35: -0.025696813 | G35: -0.049884244
A36: D&A (depreciation, GL 6300) | B36: 255 | C36: 0.034698504 | D36: 0.0602104 | E36: =D36-C36 -> 0.025511897 | F36: -0.025123198 | G36: -0.049943047
A37: Below-EBITDA items | B37: 522 | C37: 0.035094038 | D37: 0.061903289 | E37: =D37-C37 -> 0.026809251 | F37: -0.018681925 | G37: -0.035809157
A38: Tax | B38: 245 | C38: 0.033467871 | D38: 0.06064024 | E38: =D38-C38 -> 0.027172369 | F38: -0.025550909 | G38: -0.053044288
A46: F3b. Forecast vs budget on ALL comparable lines (actual, budget and forecast present; any sign)
A47: Same lines for both measures, NOT selected by outcome. Compare with F3: the matched subset drops opposite-sign and zero-involved lines, so its WAPE is much smaller. Neither population establishes forecast skill (no forecast version/as-of date). F2 (all forecast lines) is larger still because it does not require a budget value, so its lines are not the same lines as F3b.
A48: Section | B48: Comparable lines (count) | C48: WAPE forecast | D48: WAPE budget | E48: Forecast WAPE - budget WAPE (points; negative = forecast closer) | F48: Bias forecast | G48: Bias budget
A49: Revenue | B49: 29131 | C49: 0.268111 | D49: 0.29263818 | E49: =C49-D49 -> -0.024527185 | F49: 0.014478934 | G49: 0.019954565
A50: COGS | B50: 10799 | C50: 0.26953264 | D50: 0.29171141 | E50: =C50-D50 -> -0.022178772 | F50: -0.019944454 | G50: -0.040801841
A51: People costs | B51: 2927 | C51: 0.29872398 | D51: 0.29049378 | E51: =C51-D51 -> 0.008230205 | F51: -0.0079038469 | G51: -0.0028601946
A52: Operating expenses | B52: 7647 | C52: 0.27982292 | D52: 0.30221215 | E52: =C52-D52 -> -0.022389233 | F52: -0.0035625417 | G52: -0.029991271
A55: F4. Where the forecast error sits: by sign category of the (actual, forecast) pair (out_c2)
A56: Counts of lines and dollars are separate columns. Opposite-sign lines carry most of the absolute error; whether they are data defects or legitimate entries (credit notes, reversals) is unresolved. Zero-involved lines carry very little.
A57: Section | B57: Sign category | C57: Lines (count) | D57: Absolute error (USD) | E57: Share of the section's lines | F57: Share of the section's absolute error
A58: Revenue | B58: OPPOSITE_SIGN_NONZERO | C58: 3236 | D58: 58296180 | E58: =C58/SUMIFS($C$58:$C$76,$A$58:$A$76,$A58) -> 0.10479614 | F58: =D58/SUMIFS($D$58:$D$76,$A$58:$A$76,$A58) -> 0.91180792
A59: Revenue | B59: SAME_SIGN_NONZERO | C59: 27593 | D59: 5505538.3 | E59: =C59/SUMIFS($C$58:$C$76,$A$58:$A$76,$A59) -> 0.89358464 | F59: =D59/SUMIFS($D$58:$D$76,$A$58:$A$76,$A59) -> 0.086111876
A60: Revenue | B60: ZERO_INVOLVED | C60: 50 | D60: 132997.04 | E60: =C60/SUMIFS($C$58:$C$76,$A$58:$A$76,$A60) -> 0.0016192234 | F60: =D60/SUMIFS($D$58:$D$76,$A$58:$A$76,$A60) -> 0.0020802007
A61: COGS | B61: OPPOSITE_SIGN_NONZERO | C61: 1384 | D61: 28619064 | E61: =C61/SUMIFS($C$58:$C$76,$A$58:$A$76,$A61) -> 0.1209473 | F61: =D61/SUMIFS($D$58:$D$76,$A$58:$A$76,$A61) -> 0.88613292
A62: COGS | B62: SAME_SIGN_NONZERO | C62: 10051 | D62: 3600247.2 | E62: =C62/SUMIFS($C$58:$C$76,$A$58:$A$76,$A62) -> 0.87835358 | F62: =D62/SUMIFS($D$58:$D$76,$A$58:$A$76,$A62) -> 0.11147456
A63: COGS | B63: ZERO_INVOLVED | C63: 8 | D63: 77270.36 | E63: =C63/SUMIFS($C$58:$C$76,$A$58:$A$76,$A63) -> 0.00069911736 | F63: =D63/SUMIFS($D$58:$D$76,$A$58:$A$76,$A63) -> 0.0023925244
A64: People costs | B64: OPPOSITE_SIGN_NONZERO | C64: 408 | D64: 13675108 | E64: =C64/SUMIFS($C$58:$C$76,$A$58:$A$76,$A64) -> 0.13152805 | F64: =D64/SUMIFS($D$58:$D$76,$A$58:$A$76,$A64) -> 0.89938283
A65: People costs | B65: SAME_SIGN_NONZERO | C65: 2690 | D65: 1513623.1 | E65: =C65/SUMIFS($C$58:$C$76,$A$58:$A$76,$A65) -> 0.86718246 | F65: =D65/SUMIFS($D$58:$D$76,$A$58:$A$76,$A65) -> 0.09954778
A66: People costs | B66: ZERO_INVOLVED | C66: 4 | D66: 16260 | E66: =C66/SUMIFS($C$58:$C$76,$A$58:$A$76,$A66) -> 0.0012894907 | F66: =D66/SUMIFS($D$58:$D$76,$A$58:$A$76,$A66) -> 0.0010693857
A67: Operating expenses | B67: OPPOSITE_SIGN_NONZERO | C67: 1063 | D67: 14164899 | E67: =C67/SUMIFS($C$58:$C$76,$A$58:$A$76,$A67) -> 0.13092745 | F67: =D67/SUMIFS($D$58:$D$76,$A$58:$A$76,$A67) -> 0.89054337
A68: Operating expenses | B68: SAME_SIGN_NONZERO | C68: 7048 | D68: 1703776.8 | E68: =C68/SUMIFS($C$58:$C$76,$A$58:$A$76,$A68) -> 0.8680872 | F68: =D68/SUMIFS($D$58:$D$76,$A$58:$A$76,$A68) -> 0.10711599
A69: Operating expenses | B69: ZERO_INVOLVED | C69: 8 | D69: 37230 | E69: =C69/SUMIFS($C$58:$C$76,$A$58:$A$76,$A69) -> 0.00098534302 | F69: =D69/SUMIFS($D$58:$D$76,$A$58:$A$76,$A69) -> 0.0023406401
... A76: Tax | B76: SAME_SIGN_NONZERO | C76: 273 | D76: 95908.071 | E76: =C76/SUMIFS($C$58:$C$76,$A$58:$A$76,$A76) -> 0.84 | F76: =D76/SUMIFS($D$58:$D$76,$A$58:$A$76,$A76) -> 0.074591574
A79: F5. Direction by quarter (out_c5, 12 quarters)
A80: On same-sign lines the forecast sits on one side of actual in every quarter. That is an observation about this sample; without dated snapshots it cannot be called a forecasting bias that a correction would remove.
A81: Basis | B81: Section | C81: Quarters (count) | D81: Quarters forecast above actual | E81: Quarters forecast below actual | F81: Mean quarterly bias | G81: SD of quarterly bias
A82: Same-sign | B82: Revenue | C82: 12 | D82: 12 | E82: 0 | F82: 0.016460457 | G82: 0.0011433969
A83: Same-sign | B83: COGS | C83: 12 | D83: 0 | E83: 12 | F83: -0.025236033 | G83: 0.0020341872
A84: Same-sign | B84: People costs | C84: 12 | D84: 0 | E84: 12 | F84: -0.025358502 | G84: 0.0042569316
A85: Same-sign | B85: Operating expenses | C85: 12 | D85: 0 | E85: 12 | F85: -0.025422305 | G85: 0.0017891036
A86: All lines | B86: Revenue | C86: 12 | D86: 6 | E86: 6 | F86: 0.014029857 | G86: 0.027459394
A87: All lines | B87: COGS | C87: 12 | D87: 4 | E87: 8 | F87: -0.020331979 | G87: 0.038465274
A88: All lines | B88: People costs | C88: 12 | D88: 4 | E88: 8 | F88: -0.012778766 | G88: 0.064313585
A89: All lines | B89: Operating expenses | C89: 12 | D89: 7 | E89: 5 | F89: -0.0064712252 | G89: 0.053455314
A92: F6. Result proxy on lines where actual, budget and forecast are all non-zero and same-sign (out_c8)
A93: Result proxy = revenue - COGS - People - Opex on the selected lines. Illustrates the gap in dollars; the selection is outcome-based, so these are NOT company results and not a forecast-skill measure.
A94: Year | B94: Actual revenue (USD) | C94: Actual result proxy (USD) | D94: Forecast result proxy (USD) | E94: Budget result proxy (USD) | F94: Forecast - actual (USD) | G94: Budget - actual (USD)
A95: 2023 | B95: 50558721 | C95: 4877602.9 | D95: 7192256.9 | E95: 9487123.6 | F95: =D95-C95 -> 2314654 | G95: =E95-C95 -> 4609520.7
A96: 2024 | B96: 59344836 | C96: 10726566 | D96: 13271429 | E96: 15891894 | F96: =D96-C96 -> 2544862.6 | G96: =E96-C96 -> 5165328
A97: 2025 | B97: 58649800 | C97: 7733528.5 | D97: 10333710 | E97: 12968999 | F97: =D97-C97 -> 2600181.4 | G97: =E97-C97 -> 5235470.8
A98: 3 years | B98: 1.6855336e+08 | C98: 23337698 | D98: 30797396 | E98: 38348017 | F98: =D98-C98 -> 7459697.9 | G98: =E98-C98 -> 15010319
A101: F7. Forecast error by entity (out_c3)
A102: Same measures by legal entity and section; 'Basis' filters same-sign vs all lines.
A103: Basis | B103: Entity | C103: Section | D103: Lines (count) | E103: Net error (USD) | F103: Bias | G103: WAPE
A104: Same-sign | B104: AE01 | C104: Revenue | D104: 4650 | E104: 328027.74 | F104: 0.014970444 | G104: 0.025748253
A105: Same-sign | B105: AE01 | C105: COGS | D105: 1642 | E105: -238687.58 | F105: -0.022054473 | G105: 0.033508741
A106: Same-sign | B106: AE01 | C106: People costs | D106: 432 | E106: -121713.86 | F106: -0.025825941 | G106: 0.034685848
A107: Same-sign | B107: AE01 | C107: Operating expenses | D107: 1145 | E107: -126769.86 | F107: -0.025333267 | G107: 0.034302627
A108: Same-sign | B108: AE01 | C108: D&A (depreciation, GL 6300) | D108: 55 | E108: -5870.6985 | F108: -0.023048158 | G108: 0.036616874
A109: Same-sign | B109: AE01 | C109: Below-EBITDA items | D109: 120 | E109: -2558.8979 | F109: -0.023100469 | G109: 0.032374825
A110: Same-sign | B110: AE01 | C110: Tax | D110: 52 | E110: -9035.4465 | F110: -0.026100072 | G110: 0.032700832
A111: Same-sign | B111: DE01 | C111: Revenue | D111: 4531 | E111: 509334.29 | F111: 0.016539809 | G111: 0.024990058
A112: Same-sign | B112: DE01 | C112: COGS | D112: 1734 | E112: -473462.68 | F112: -0.028112673 | G112: 0.036828818
A113: Same-sign | B113: DE01 | C113: People costs | D113: 458 | E113: -176789.73 | F113: -0.023852447 | G113: 0.03111163
A114: Same-sign | B114: DE01 | C114: Operating expenses | D114: 1186 | E114: -190493.54 | F114: -0.025510623 | G114: 0.034741697
A115: Same-sign | B115: DE01 | C115: D&A (depreciation, GL 6300) | D115: 55 | E115: -12570.573 | F115: -0.03424541 | G115: 0.037223205
... A187: All lines | B187: US01 | C187: Tax | D187: 61 | E187: -338644.26 | F187: -0.33464114 | G187: 0.37933311
A190: F8. Actual vs the prior-year COLUMN (out_d1) - USD
A191: The prior-year column is a field on each line. F9 shows it is NOT equal to the previous calendar year's actuals, so 'change vs prior-year column' must not be read as year-on-year growth.
A192: Basis | B192: Section | C192: Year | D192: Lines (count) | E192: Actual (USD) | F192: Prior-year column (USD) | G192: Change = actual - prior-year column (USD) | H192: Change % of |prior-year column|
A193: Same-sign | B193: Revenue | C193: 2023 | D193: 9137 | E193: 57584695 | F193: 53312659 | G193: =E193-F193 -> 4272036 | H193: =IF(F193<>0,G193/ABS(F193),"n/a") -> 0.080131737
A194: Same-sign | B194: Revenue | C194: 2024 | D194: 9179 | E194: 65342414 | F194: 60544217 | G194: =E194-F194 -> 4798197.2 | H194: =IF(F194<>0,G194/ABS(F194),"n/a") -> 0.079251124
A195: Same-sign | B195: Revenue | C195: 2025 | D195: 9143 | E195: 66283603 | F195: 61396016 | G195: =E195-F195 -> 4887586.8 | H195: =IF(F195<>0,G195/ABS(F195),"n/a") -> 0.079607557
A196: Same-sign | B196: COGS | C196: 2023 | D196: 3452 | E196: 26797879 | F196: 24827383 | G196: =E196-F196 -> 1970496.5 | H196: =IF(F196<>0,G196/ABS(F196),"n/a") -> 0.079367872
A197: Same-sign | B197: COGS | C197: 2024 | D197: 3317 | E197: 28601618 | F197: 26515839 | G197: =E197-F197 -> 2085779.1 | H197: =IF(F197<>0,G197/ABS(F197),"n/a") -> 0.07866163
A198: Same-sign | B198: COGS | C198: 2025 | D198: 3343 | E198: 31536950 | F198: 29261694 | G198: =E198-F198 -> 2275256.1 | H198: =IF(F198<>0,G198/ABS(F198),"n/a") -> 0.077755447
A199: Same-sign | B199: People costs | C199: 2023 | D199: 949 | E199: 13213763 | F199: 12280986 | G199: =E199-F199 -> 932776.31 | H199: =IF(F199<>0,G199/ABS(F199),"n/a") -> 0.075952883
...

Sheet Entity & Division
A1: Entity and division analysis | N1: Back to Start Here
A2: USD, scale-adjusted (provisional), signs as recorded. 3-year totals unless stated. Sources: out_a2, out_a3, out_b2, out_b3, out_g5.
A3: Comparability: all six entities report in USD in this extract after conversion, cover the same 36 months (0 entity-month gaps, out_a6) and use the same Posted-only population. Entity size differs widely, so compare shares and percentages, not raw amounts. Consolidation and intercompany elimination (R12) are unresolved: group totals here are sums of entity lines, not consolidated results.
A5: E1. Actual performance by legal entity (3 years, Posted-only eligible lines)
A6: Gross profit = Revenue - COGS (treatment S1, signed as recorded). Share of group revenue = entity revenue / sum of entity revenues.
A7: Entity | B7: Legal entity | C7: Revenue (USD) | D7: COGS (USD) | E7: Gross profit S1 (USD) | F7: Gross margin % (S1) | G7: People (USD) | H7: Opex (USD) | I7: Operating result proxy (USD) | J7: Proxy margin % | K7: Share of group revenue | L7: Eligible lines (count)
A8: AE01 | B8: NovaBridge MENA FZE | C8: 21148202 | D8: 8731913.5 | E8: =C8-D8 -> 12416288 | F8: =IF(C8>0,E8/C8,"n/a") -> 0.58710847 | G8: 3802070.7 | H8: 4371835 | I8: =C8-D8-G8-H8 -> 4242382.6 | J8: =IF(C8>0,I8/C8,"n/a") -> 0.20060252 | K8: =C8/SUM($C$8:$C$13) -> 0.10435878 | L8: 9634
A9: DE01 | B9: NovaBridge Europe GmbH | C9: 29549094 | D9: 15097025 | E9: =C9-D9 -> 14452069 | F9: =IF(C9>0,E9/C9,"n/a") -> 0.4890867 | G9: 6720387.8 | H9: 6783449 | I9: =C9-D9-G9-H9 -> 948232.08 | J9: =IF(C9>0,I9/C9,"n/a") -> 0.032090056 | K9: =C9/SUM($C$8:$C$13) -> 0.14581416 | L9: 9772
A10: GB01 | B10: NovaBridge UK Ltd | C10: 20503977 | D10: 9747172.4 | E10: =C10-D10 -> 10756805 | F10: =IF(C10>0,E10/C10,"n/a") -> 0.5246204 | G10: 4210720.3 | H10: 4330207.8 | I10: =C10-D10-G10-H10 -> 2215876.5 | J10: =IF(C10>0,I10/C10,"n/a") -> 0.10807057 | K10: =C10/SUM($C$8:$C$13) -> 0.10117976 | L10: 9882
A11: IN01 | B11: NovaBridge India Pvt Ltd | C11: 48348042 | D11: 21648388 | E11: =C11-D11 -> 26699654 | F11: =IF(C11>0,E11/C11,"n/a") -> 0.55223857 | G11: 9134124.4 | H11: 9997788.9 | I11: =C11-D11-G11-H11 -> 7567740.3 | J11: =IF(C11>0,I11/C11,"n/a") -> 0.1565263 | K11: =C11/SUM($C$8:$C$13) -> 0.23858021 | L11: 9692
A12: SG01 | B12: NovaBridge APAC Pte Ltd | C12: 27763849 | D12: 13579996 | E12: =C12-D12 -> 14183853 | F12: =IF(C12>0,E12/C12,"n/a") -> 0.51087487 | G12: 6127320.5 | H12: 6524566.1 | I12: =C12-D12-G12-H12 -> 1531966.2 | J12: =IF(C12>0,I12/C12,"n/a") -> 0.05517845 | K12: =C12/SUM($C$8:$C$13) -> 0.13700462 | L12: 9706
A13: US01 | B13: NovaBridge Americas Inc | C13: 55335838 | D13: 24003522 | E13: =C13-D13 -> 31332316 | F13: =IF(C13>0,E13/C13,"n/a") -> 0.56622105 | G13: 9714315.6 | H13: 11804952 | I13: =C13-D13-G13-H13 -> 9813048.4 | J13: =IF(C13>0,I13/C13,"n/a") -> 0.17733622 | K13: =C13/SUM($C$8:$C$13) -> 0.27306247 | L13: 9654
A14: Group | B14: Sum of entities | C14: =SUM($C$8:$C$13) -> 2.02649e+08 | D14: =SUM($D$8:$D$13) -> 92808018 | G14: =SUM($G$8:$G$13) -> 39708939 | H14: =SUM($H$8:$H$13) -> 43812799 | L14: =SUM($L$8:$L$13) -> 58340
A17: E2. Actual performance by division (3 years)
A18: Division is populated on 100% of eligible lines (out_a5). Shares are of the sum of divisions.
A19: Division | C19: Revenue (USD) | D19: COGS (USD) | E19: Gross profit S1 (USD) | F19: Gross margin % (S1) | G19: People (USD) | H19: Opex (USD) | I19: Operating result proxy (USD) | J19: Proxy margin % | K19: Share of group revenue | L19: Eligible lines (count)
A20: Consumer Durables | C20: 73952684 | D20: 32947623 | E20: =C20-D20 -> 41005061 | F20: =IF(C20>0,E20/C20,"n/a") -> 0.55447699 | G20: 14098554 | H20: 16312049 | I20: =C20-D20-G20-H20 -> 10594458 | J20: =IF(C20>0,I20/C20,"n/a") -> 0.14325996 | K20: =C20/SUM($C$20:$C$24) -> 0.36492992 | L20: 14441
A21: Industrial Components | C21: 51566935 | D21: 23949621 | E21: =C21-D21 -> 27617313 | F21: =IF(C21>0,E21/C21,"n/a") -> 0.53556244 | G21: 11264016 | H21: 11510470 | I21: =C21-D21-G21-H21 -> 4842827.2 | J21: =IF(C21>0,I21/C21,"n/a") -> 0.093913421 | K21: =C21/SUM($C$20:$C$24) -> 0.25446429 | L21: 14598
A22: Medical Devices | C22: 48335023 | D22: 21989480 | E22: =C22-D22 -> 26345542 | F22: =IF(C22>0,E22/C22,"n/a") -> 0.54506114 | G22: 9232766.3 | H22: 9837609.9 | I22: =C22-D22-G22-H22 -> 7275166.2 | J22: =IF(C22>0,I22/C22,"n/a") -> 0.15051542 | K22: =C22/SUM($C$20:$C$24) -> 0.23851597 | L22: 14628
A23: Packaging | C23: 21446251 | D23: 10491725 | E23: =C23-D23 -> 10954526 | F23: =IF(C23>0,E23/C23,"n/a") -> 0.51078981 | G23: 3549153.7 | H23: 4601302 | I23: =C23-D23-G23-H23 -> 2804070.6 | J23: =IF(C23>0,I23/C23,"n/a") -> 0.13074876 | K23: =C23/SUM($C$20:$C$24) -> 0.10582954 | L23: 9713
A24: Services & Spares | C24: 7348110.3 | D24: 3429569.2 | E24: =C24-D24 -> 3918541.1 | F24: =IF(C24>0,E24/C24,"n/a") -> 0.53327195 | G24: 1564449.9 | H24: 1551367.6 | I24: =C24-D24-G24-H24 -> 802723.65 | J24: =IF(C24>0,I24/C24,"n/a") -> 0.10924219 | K24: =C24/SUM($C$20:$C$24) -> 0.036260284 | L24: 4960
A25: Group | C25: =SUM($C$20:$C$24) -> 2.02649e+08
A28: E3. Actual vs budget by legal entity - same-sign basis (SUMIFS over the E6 detail table)
A29: Variance = actual - budget. Variance % = variance / |budget| at entity level; no favourable/adverse label. Cost = COGS + People + Opex.
A30: Entity | B30: Revenue actual (USD) | C30: Revenue budget (USD) | D30: Revenue variance (USD) | E30: Revenue variance % | F30: Cost actual (USD) | G30: Cost budget (USD) | H30: Cost variance (USD) | I30: Cost variance % | J30: Net effect on result proxy (USD) = revenue var - cost var
A31: AE01 | B31: =SUMIFS('Entity & Division'!$G$150:$G$437,'Entity & Division'!$C$150:$C$437,$A31,'Entity & Division'!$A$150:$A$437,"Same-sign",'Entity & Division'!$B$150:$B$437,"REVENUE") -> 19447445 | C31: =SUMIFS('Entity & Division'!$H$150:$H$437,'Entity & Division'!$C$150:$C$437,$A31,'Entity & Division'!$A$150:$A$437,"Same-sign",'Entity & Division'!$B$150:$B$437,"REVENUE") -> 20163398 | D31: =B31-C31 -> -715953 | E31: =IF(C31<>0,D31/ABS(C31),"n/a") -> -0.035507556 | F31: =SUMIFS('Entity & Division'!$G$150:$G$437,'Entity & Division'!$C$150:$C$437,$A31,'Entity & Division'!$A$150:$A$437,"Same-sign",'Entity & Division'!$B$150:$B$437,"COGS")+SUMIFS('Entity & Division'!$G$150:$G$437,'Entity & Division'!$C$150:$C$437,$A31,'Entity & Division'!$A$150:$A$437,"Same-sign",'Entity & Division'!$B$150:$B$437,"PEOPLE")+SUMIFS('Entity & Division'!$G$150:$G$437,'Entity & Division'!$C$150:$C$437,$A31,'Entity & Division'!$A$150:$A$437,"Same-sign",'Entity & Division'!$B$150:$B$437,"OPEX") -> 16521382 | G31: =SUMIFS('Entity & Division'!$H$150:$H$437,'Entity & Division'!$C$150:$C$437,$A31,'Entity & Division'!$A$150:$A$437,"Same-sign",'Entity & Division'!$B$150:$B$437,"COGS")+SUMIFS('Entity & Division'!$H$150:$H$437,'Entity & Division'!$C$150:$C$437,$A31,'Entity & Division'!$A$150:$A$437,"Same-sign",'Entity & Division'!$B$150:$B$437,"PEOPLE")+SUMIFS('Entity & Division'!$H$150:$H$437,'Entity & Division'!$C$150:$C$437,$A31,'Entity & Division'!$A$150:$A$437,"Same-sign",'Entity & Division'!$B$150:$B$437,"OPEX") -> 15523464 | H31: =F31-G31 -> 997918.06 | I31: =IF(G31<>0,H31/ABS(G31),"n/a") -> 0.064284496 | J31: =D31-H31 -> -1713871.1
A32: DE01 | B32: =SUMIFS('Entity & Division'!$G$150:$G$437,'Entity & Division'!$C$150:$C$437,$A32,'Entity & Division'!$A$150:$A$437,"Same-sign",'Entity & Division'!$B$150:$B$437,"REVENUE") -> 27740192 | C32: =SUMIFS('Entity & Division'!$H$150:$H$437,'Entity & Division'!$C$150:$C$437,$A32,'Entity & Division'!$A$150:$A$437,"Same-sign",'Entity & Division'!$B$150:$B$437,"REVENUE") -> 28768945 | D32: =B32-C32 -> -1028752.3 | E32: =IF(C32<>0,D32/ABS(C32),"n/a") -> -0.035759125 | F32: =SUMIFS('Entity & Division'!$G$150:$G$437,'Entity & Division'!$C$150:$C$437,$A32,'Entity & Division'!$A$150:$A$437,"Same-sign",'Entity & Division'!$B$150:$B$437,"COGS")+SUMIFS('Entity & Division'!$G$150:$G$437,'Entity & Division'!$C$150:$C$437,$A32,'Entity & Division'!$A$150:$A$437,"Same-sign",'Entity & Division'!$B$150:$B$437,"PEOPLE")+SUMIFS('Entity & Division'!$G$150:$G$437,'Entity & Division'!$C$150:$C$437,$A32,'Entity & Division'!$A$150:$A$437,"Same-sign",'Entity & Division'!$B$150:$B$437,"OPEX") -> 27067905 | G32: =SUMIFS('Entity & Division'!$H$150:$H$437,'Entity & Division'!$C$150:$C$437,$A32,'Entity & Division'!$A$150:$A$437,"Same-sign",'Entity & Division'!$B$150:$B$437,"COGS")+SUMIFS('Entity & Division'!$H$150:$H$437,'Entity & Division'!$C$150:$C$437,$A32,'Entity & Division'!$A$150:$A$437,"Same-sign",'Entity & Division'!$B$150:$B$437,"PEOPLE")+SUMIFS('Entity & Division'!$H$150:$H$437,'Entity & Division'!$C$150:$C$437,$A32,'Entity & Division'!$A$150:$A$437,"Same-sign",'Entity & Division'!$B$150:$B$437,"OPEX") -> 25427725 | H32: =F32-G32 -> 1640180.1 | I32: =IF(G32<>0,H32/ABS(G32),"n/a") -> 0.064503613 | J32: =D32-H32 -> -2668932.5
A33: GB01 | B33: =SUMIFS('Entity & Division'!$G$150:$G$437,'Entity & Division'!$C$150:$C$437,$A33,'Entity & Division'!$A$150:$A$437,"Same-sign",'Entity & Division'!$B$150:$B$437,"REVENUE") -> 19030287 | C33: =SUMIFS('Entity & Division'!$H$150:$H$437,'Entity & Division'!$C$150:$C$437,$A33,'Entity & Division'!$A$150:$A$437,"Same-sign",'Entity & Division'!$B$150:$B$437,"REVENUE") -> 19723180 | D33: =B33-C33 -> -692893.92 | E33: =IF(C33<>0,D33/ABS(C33),"n/a") -> -0.035130942 | F33: =SUMIFS('Entity & Division'!$G$150:$G$437,'Entity & Division'!$C$150:$C$437,$A33,'Entity & Division'!$A$150:$A$437,"Same-sign",'Entity & Division'!$B$150:$B$437,"COGS")+SUMIFS('Entity & Division'!$G$150:$G$437,'Entity & Division'!$C$150:$C$437,$A33,'Entity & Division'!$A$150:$A$437,"Same-sign",'Entity & Division'!$B$150:$B$437,"PEOPLE")+SUMIFS('Entity & Division'!$G$150:$G$437,'Entity & Division'!$C$150:$C$437,$A33,'Entity & Division'!$A$150:$A$437,"Same-sign",'Entity & Division'!$B$150:$B$437,"OPEX") -> 17487058 | G33: =SUMIFS('Entity & Division'!$H$150:$H$437,'Entity & Division'!$C$150:$C$437,$A33,'Entity & Division'!$A$150:$A$437,"Same-sign",'Entity & Division'!$B$150:$B$437,"COGS")+SUMIFS('Entity & Division'!$H$150:$H$437,'Entity & Division'!$C$150:$C$437,$A33,'Entity & Division'!$A$150:$A$437,"Same-sign",'Entity & Division'!$B$150:$B$437,"PEOPLE")+SUMIFS('Entity & Division'!$H$150:$H$437,'Entity & Division'!$C$150:$C$437,$A33,'Entity & Division'!$A$150:$A$437,"Same-sign",'Entity & Division'!$B$150:$B$437,"OPEX") -> 16444064 | H33: =F33-G33 -> 1042994.6 | I33: =IF(G33<>0,H33/ABS(G33),"n/a") -> 0.063426816 | J33: =D33-H33 -> -1735888.5
A34: IN01 | B34: =SUMIFS('Entity & Division'!$G$150:$G$437,'Entity & Division'!$C$150:$C$437,$A34,'Entity & Division'!$A$150:$A$437,"Same-sign",'Entity & Division'!$B$150:$B$437,"REVENUE") -> 45356329 | C34: =SUMIFS('Entity & Division'!$H$150:$H$437,'Entity & Division'!$C$150:$C$437,$A34,'Entity & Division'!$A$150:$A$437,"Same-sign",'Entity & Division'!$B$150:$B$437,"REVENUE") -> 46995352 | D34: =B34-C34 -> -1639023.1 | E34: =IF(C34<>0,D34/ABS(C34),"n/a") -> -0.034876282 | F34: =SUMIFS('Entity & Division'!$G$150:$G$437,'Entity & Division'!$C$150:$C$437,$A34,'Entity & Division'!$A$150:$A$437,"Same-sign",'Entity & Division'!$B$150:$B$437,"COGS")+SUMIFS('Entity & Division'!$G$150:$G$437,'Entity & Division'!$C$150:$C$437,$A34,'Entity & Division'!$A$150:$A$437,"Same-sign",'Entity & Division'!$B$150:$B$437,"PEOPLE")+SUMIFS('Entity & Division'!$G$150:$G$437,'Entity & Division'!$C$150:$C$437,$A34,'Entity & Division'!$A$150:$A$437,"Same-sign",'Entity & Division'!$B$150:$B$437,"OPEX") -> 38279037 | G34: =SUMIFS('Entity & Division'!$H$150:$H$437,'Entity & Division'!$C$150:$C$437,$A34,'Entity & Division'!$A$150:$A$437,"Same-sign",'Entity & Division'!$B$150:$B$437,"COGS")+SUMIFS('Entity & Division'!$H$150:$H$437,'Entity & Division'!$C$150:$C$437,$A34,'Entity & Division'!$A$150:$A$437,"Same-sign",'Entity & Division'!$B$150:$B$437,"PEOPLE")+SUMIFS('Entity & Division'!$H$150:$H$437,'Entity & Division'!$C$150:$C$437,$A34,'Entity & Division'!$A$150:$A$437,"Same-sign",'Entity & Division'!$B$150:$B$437,"OPEX") -> 35988057 | H34: =F34-G34 -> 2290979.8 | I34: =IF(G34<>0,H34/ABS(G34),"n/a") -> 0.063659446 | J34: =D34-H34 -> -3930002.9
A35: SG01 | B35: =SUMIFS('Entity & Division'!$G$150:$G$437,'Entity & Division'!$C$150:$C$437,$A35,'Entity & Division'!$A$150:$A$437,"Same-sign",'Entity & Division'!$B$150:$B$437,"REVENUE") -> 26567250 | C35: =SUMIFS('Entity & Division'!$H$150:$H$437,'Entity & Division'!$C$150:$C$437,$A35,'Entity & Division'!$A$150:$A$437,"Same-sign",'Entity & Division'!$B$150:$B$437,"REVENUE") -> 27585399 | D35: =B35-C35 -> -1018149.1 | E35: =IF(C35<>0,D35/ABS(C35),"n/a") -> -0.036908984 | F35: =SUMIFS('Entity & Division'!$G$150:$G$437,'Entity & Division'!$C$150:$C$437,$A35,'Entity & Division'!$A$150:$A$437,"Same-sign",'Entity & Division'!$B$150:$B$437,"COGS")+SUMIFS('Entity & Division'!$G$150:$G$437,'Entity & Division'!$C$150:$C$437,$A35,'Entity & Division'!$A$150:$A$437,"Same-sign",'Entity & Division'!$B$150:$B$437,"PEOPLE")+SUMIFS('Entity & Division'!$G$150:$G$437,'Entity & Division'!$C$150:$C$437,$A35,'Entity & Division'!$A$150:$A$437,"Same-sign",'Entity & Division'!$B$150:$B$437,"OPEX") -> 24910282 | G35: =SUMIFS('Entity & Division'!$H$150:$H$437,'Entity & Division'!$C$150:$C$437,$A35,'Entity & Division'!$A$150:$A$437,"Same-sign",'Entity & Division'!$B$150:$B$437,"COGS")+SUMIFS('Entity & Division'!$H$150:$H$437,'Entity & Division'!$C$150:$C$437,$A35,'Entity & Division'!$A$150:$A$437,"Same-sign",'Entity & Division'!$B$150:$B$437,"PEOPLE")+SUMIFS('Entity & Division'!$H$150:$H$437,'Entity & Division'!$C$150:$C$437,$A35,'Entity & Division'!$A$150:$A$437,"Same-sign",'Entity & Division'!$B$150:$B$437,"OPEX") -> 23426054 | H35: =F35-G35 -> 1484227.7 | I35: =IF(G35<>0,H35/ABS(G35),"n/a") -> 0.063357988 | J35: =D35-H35 -> -2502376.7
A36: US01 | B36: =SUMIFS('Entity & Division'!$G$150:$G$437,'Entity & Division'!$C$150:$C$437,$A36,'Entity & Division'!$A$150:$A$437,"Same-sign",'Entity & Division'!$B$150:$B$437,"REVENUE") -> 52255212 | C36: =SUMIFS('Entity & Division'!$H$150:$H$437,'Entity & Division'!$C$150:$C$437,$A36,'Entity & Division'!$A$150:$A$437,"Same-sign",'Entity & Division'!$B$150:$B$437,"REVENUE") -> 54183478 | D36: =B36-C36 -> -1928265.8 | E36: =IF(C36<>0,D36/ABS(C36),"n/a") -> -0.035587708 | F36: =SUMIFS('Entity & Division'!$G$150:$G$437,'Entity & Division'!$C$150:$C$437,$A36,'Entity & Division'!$A$150:$A$437,"Same-sign",'Entity & Division'!$B$150:$B$437,"COGS")+SUMIFS('Entity & Division'!$G$150:$G$437,'Entity & Division'!$C$150:$C$437,$A36,'Entity & Division'!$A$150:$A$437,"Same-sign",'Entity & Division'!$B$150:$B$437,"PEOPLE")+SUMIFS('Entity & Division'!$G$150:$G$437,'Entity & Division'!$C$150:$C$437,$A36,'Entity & Division'!$A$150:$A$437,"Same-sign",'Entity & Division'!$B$150:$B$437,"OPEX") -> 43257650 | G36: =SUMIFS('Entity & Division'!$H$150:$H$437,'Entity & Division'!$C$150:$C$437,$A36,'Entity & Division'!$A$150:$A$437,"Same-sign",'Entity & Division'!$B$150:$B$437,"COGS")+SUMIFS('Entity & Division'!$H$150:$H$437,'Entity & Division'!$C$150:$C$437,$A36,'Entity & Division'!$A$150:$A$437,"Same-sign",'Entity & Division'!$B$150:$B$437,"PEOPLE")+SUMIFS('Entity & Division'!$H$150:$H$437,'Entity & Division'!$C$150:$C$437,$A36,'Entity & Division'!$A$150:$A$437,"Same-sign",'Entity & Division'!$B$150:$B$437,"OPEX") -> 40626930 | H36: =F36-G36 -> 2630720.5 | I36: =IF(G36<>0,H36/ABS(G36),"n/a") -> 0.064753123 | J36: =D36-H36 -> -4558986.4
A41: E4. Actual vs budget by division (out_b3, both bases)
A42: Variance recomputed in Excel (actual - budget); % is the Phase 4 guarded figure.
A43: Basis | B43: Section | C43: Division | D43: Lines (count) | E43: Actual (USD) | F43: Budget (USD) | G43: Variance (USD) | H43: Variance % (Phase 4, guarded)
A44: Same-sign | B44: REVENUE | C44: Consumer Durables | D44: 6824 | E44: 70102762 | F44: 72689502 | G44: =E44-F44 -> -2586740.8 | H44: -0.035586168
A45: Same-sign | B45: REVENUE | C45: Industrial Components | D45: 6832 | E45: 48191424 | F45: 49986088 | G45: =E45-F45 -> -1794664 | H45: -0.03590327
A46: Same-sign | B46: REVENUE | C46: Medical Devices | D46: 6947 | E46: 45390041 | F46: 47055147 | G46: =E46-F46 -> -1665106.1 | H46: -0.035386269
A47: Same-sign | B47: REVENUE | C47: Packaging | D47: 4637 | E47: 19818217 | F47: 20534925 | G47: =E47-F47 -> -716708.72 | H47: -0.03490194
A48: Same-sign | B48: REVENUE | C48: Services & Spares | D48: 2297 | E48: 6894272.6 | F48: 7154090.2 | G48: =E48-F48 -> -259817.59 | H48: -0.036317349
A49: Same-sign | B49: COGS | C49: Consumer Durables | D49: 2482 | E49: 31565327 | F49: 29614684 | G49: =E49-F49 -> 1950643.2 | H49: 0.065867431
A50: Same-sign | B50: COGS | C50: Industrial Components | D50: 2567 | E50: 22370460 | F50: 21051607 | G50: =E50-F50 -> 1318853.7 | H50: 0.062648598
A51: Same-sign | B51: COGS | C51: Medical Devices | D51: 2524 | E51: 20816740 | F51: 19563218 | G51: =E51-F51 -> 1253521.2 | H51: 0.064075406
A52: Same-sign | B52: COGS | C52: Packaging | D52: 1685 | E52: 9791164.1 | F52: 9215553.7 | G52: =E52-F52 -> 575610.4 | H52: 0.06246075
A53: Same-sign | B53: COGS | C53: Services & Spares | D53: 884 | E53: 3257634.5 | F53: 3060521.1 | G53: =E53-F53 -> 197113.41 | H53: 0.064405181
A54: Same-sign | B54: PEOPLE | C54: Consumer Durables | D54: 687 | E54: 13356059 | F54: 12575004 | G54: =E54-F54 -> 781054.22 | H54: 0.062111647
A55: Same-sign | B55: PEOPLE | C55: Industrial Components | D55: 690 | E55: 10742732 | F55: 10067267 | G55: =E55-F55 -> 675464.18 | H55: 0.067095087
... A103: All lines | B103: D&A | C103: Services & Spares | D103: 31 | E103: 73313.061 | F103: 54119.649 | G103: =E103-F103 -> 19193.412 | H103: 0.35464775
A104: All lines | B104: BELOW_EBITDA | C104: Consumer Durables | D104: 170 | E104: 197676.06 | F104: 139904.66 | G104: =E104-F104 -> 57771.404
A105: All lines | B105: BELOW_EBITDA | C105: Industrial Components | D105: 165 | E105: 131123.2 | F105: 128380.47 | G105: =E105-F105 -> 2742.7314 | H105: 0.021364087
A106: All lines | B106: BELOW_EBITDA | C106: Medical Devices | D106: 172 | E106: 120270.62 | F106: 119839.38 | G106: =E106-F106 -> 431.2439 | H106: 0.0035985158
A107: All lines | B107: BELOW_EBITDA | C107: Packaging | D107: 100 | E107: 68751.001 | F107: 65845.982 | G107: =E107-F107 -> 2905.019 | H107: 0.044118394
A108: All lines | B108: BELOW_EBITDA | C108: Services & Spares | D108: 48 | E108: 21883.462 | F108: 27345.78 | G108: =E108-F108 -> -5462.3182 | H108: -0.19974995
A109: All lines | B109: TAX | C109: Consumer Durables | D109: 76 | E109: 896674.19 | F109: 862501.62 | G109: =E109-F109 -> 34172.569 | H109: 0.039620295
A110: All lines | B110: TAX | C110: Industrial Components | D110: 84 | E110: 620536.54 | F110: 765619.27 | G110: =E110-F110 -> -145082.73 | H110: -0.18949723
A111: All lines | B111: TAX | C111: Medical Devices | D111: 86 | E111: 709209.76 | F111: 679669.38 | G111: =E111-F111 -> 29540.379 | H111: 0.043462865
A112: All lines | B112: TAX | C112: Packaging | D112: 62 | E112: 348091.63 | F112: 298635.57 | G112: =E112-F112 -> 49456.056 | H112: 0.16560671
A113: All lines | B113: TAX | C113: Services & Spares | D113: 31 | E113: 141327.82 | F113: 144524.13 | G113: =E113-F113 -> -3196.307 | H113: -0.022116078
A117: E5. Year-on-year growth by entity (out_g5; operating cost = COGS + People + Opex)
A118: Growth uses Posted-only signed amounts for consecutive calendar years; 2023 has no prior year.
A119: Group | B119: Entity | C119: Year | D119: Amount (USD) | E119: YoY growth %
A120: REVENUE | B120: AE01 | C120: 2024 | D120: 20889221 | E120: 0.073062313
A121: REVENUE | B121: AE01 | C121: 2025 | D121: 22397428 | E121: 0.072200206
A122: REVENUE | B122: DE01 | C122: 2024 | D122: 29894771 | E122: 0.060176017
A123: REVENUE | B123: DE01 | C123: 2025 | D123: 31643455 | E123: 0.05849464
A124: REVENUE | B124: GB01 | C124: 2024 | D124: 19884140 | E124: 0.059028099
A125: REVENUE | B125: GB01 | C125: 2025 | D125: 20992621 | E125: 0.055746991
A126: REVENUE | B126: IN01 | C126: 2024 | D126: 46315746 | E126: 0.064108327
A127: REVENUE | B127: IN01 | C127: 2025 | D127: 48590064 | E127: 0.049104645
A128: REVENUE | B128: SG01 | C128: 2024 | D128: 28321827 | E128: 0.040453663
A129: REVENUE | B129: SG01 | C129: 2025 | D129: 30421171 | E129: 0.074124583
A130: REVENUE | B130: US01 | C130: 2024 | D130: 53088266 | E130: 0.073824071
A131: REVENUE | B131: US01 | C131: 2025 | D131: 55653878 | E131: 0.048327295
... A143: OPERATING COST | B143: US01 | C143: 2025 | D143: 54768787 | E143: 0.062991215
A147: E6. Detail: variance by entity x GL (out_b2, 288 rows; filter by Basis)
A148: Source of the SUMIFS in E3 and in 'Budget vs Actual' / 'GL & Cost Drivers'. Same-sign = lines where actual and budget are non-zero with the same sign (Phase 4 primary basis). All lines = every eligible line with a budget. 'Variance %' is blank where the Phase 4 guard (|net budget| < 50% of gross) suppresses it.
A149: Basis | B149: Section | C149: Entity | D149: GL | E149: Account | F149: Lines (count) | G149: Actual (USD) | H149: Budget (USD) | I149: Variance = actual - budget (USD) | J149: Variance % (Phase 4, guarded) | K149: Share of section gross cell variance | L149: Direction (arithmetic only)
A150: Same-sign | B150: REVENUE | C150: AE01 | D150: 4100 | E150: Product sales | F150: 1465 | G150: 16515293 | H150: 17116953 | I150: =G150-H150 -> -601660.13 | J150: -0.035149956 | K150: 0.085669505 | L150: =IF(I150>0,"Actual above budget",IF(I150<0,"Actual below budget","On budget")) -> Actual below budget
A151: Same-sign | B151: REVENUE | C151: AE01 | D151: 4110 | E151: Service and spares revenue | F151: 1440 | G151: 2572902 | H151: 2665314.6 | I151: =G151-H151 -> -92412.588 | J151: -0.034672301 | K151: 0.013158493 | L151: =IF(I151>0,"Actual above budget",IF(I151<0,"Actual below budget","On budget")) -> Actual below budget
A152: Same-sign | B152: REVENUE | C152: AE01 | D152: 4120 | E152: Freight recovered | F152: 52 | G152: 576538.41 | H152: 595802.87 | I152: =G152-H152 -> -19264.461 | J152: -0.032333615 | K152: 0.0027430384 | L152: =IF(I152>0,"Actual above budget",IF(I152<0,"Actual below budget","On budget")) -> Actual below budget
A153: Same-sign | B153: REVENUE | C153: AE01 | D153: 4190 | E153: Sales discounts and rebates | F153: 1635 | G153: -217287.64 | H153: -214671.81 | I153: =G153-H153 -> -2615.8276 | K153: 0.00037246386 | L153: =IF(I153>0,"Actual above budget",IF(I153<0,"Actual below budget","On budget")) -> Actual below budget
A154: Same-sign | B154: REVENUE | C154: DE01 | D154: 4100 | E154: Product sales | F154: 1458 | G154: 23532211 | H154: 24390096 | I154: =G154-H154 -> -857884.85 | J154: -0.035173493 | K154: 0.12215297 | L154: =IF(I154>0,"Actual above budget",IF(I154<0,"Actual below budget","On budget")) -> Actual below budget
A155: Same-sign | B155: REVENUE | C155: DE01 | D155: 4110 | E155: Service and spares revenue | F155: 1472 | G155: 3640518.3 | H155: 3776003.1 | I155: =G155-H155 -> -135484.83 | J155: -0.035880486 | K155: 0.019291487 | L155: =IF(I155>0,"Actual above budget",IF(I155<0,"Actual below budget","On budget")) -> Actual below budget
A156: Same-sign | B156: REVENUE | C156: DE01 | D156: 4120 | E156: Freight recovered | F156: 64 | G156: 870596.74 | H156: 898774.01 | I156: =G156-H156 -> -28177.271 | J156: -0.031350785 | K156: 0.0040121203 | L156: =IF(I156>0,"Actual above budget",IF(I156<0,"Actual below budget","On budget")) -> Actual below budget
A157: Same-sign | B157: REVENUE | C157: DE01 | D157: 4190 | E157: Sales discounts and rebates | F157: 1592 | G157: -303133.32 | H157: -295927.97 | I157: =G157-H157 -> -7205.3545 | K157: 0.0010259599 | L157: =IF(I157>0,"Actual above budget",IF(I157<0,"Actual below budget","On budget")) -> Actual below budget
A158: Same-sign | B158: REVENUE | C158: GB01 | D158: 4100 | E158: Product sales | F158: 1482 | G158: 16378412 | H158: 16964616 | I158: =G158-H158 -> -586204.91 | J158: -0.034554563 | K158: 0.083468859 | L158: =IF(I158>0,"Actual above budget",IF(I158<0,"Actual below budget","On budget")) -> Actual below budget
A159: Same-sign | B159: REVENUE | C159: GB01 | D159: 4110 | E159: Service and spares revenue | F159: 1450 | G159: 2404293.5 | H159: 2487337.1 | I159: =G159-H159 -> -83043.62 | J159: -0.033386556 | K159: 0.01182446 | L159: =IF(I159>0,"Actual above budget",IF(I159<0,"Actual below budget","On budget")) -> Actual below budget
A160: Same-sign | B160: REVENUE | C160: GB01 | D160: 4120 | E160: Freight recovered | F160: 53 | G160: 497349.76 | H160: 517123.12 | I160: =G160-H160 -> -19773.365 | J160: -0.038237247 | K160: 0.0028155005 | L160: =IF(I160>0,"Actual above budget",IF(I160<0,"Actual below budget","On budget")) -> Actual below budget
A161: Same-sign | B161: REVENUE | C161: GB01 | D161: 4190 | E161: Sales discounts and rebates | F161: 1611 | G161: -249768.18 | H161: -245896.16 | I161: =G161-H161 -> -3872.0249 | K161: 0.00055133196 | L161: =IF(I161>0,"Actual above budget",IF(I161<0,"Actual below budget","On budget")) -> Actual below budget
A162: Same-sign | B162: REVENUE | C162: IN01 | D162: 4100 | E162: Product sales | F162: 1506 | G162: 39062316 | H162: 40431207 | I162: =G162-H162 -> -1368891.5 | J162: -0.0338573 | K162: 0.19491446 | L162: =IF(I162>0,"Actual above budget",IF(I162<0,"Actual below budget","On budget")) -> Actual below budget
A163: Same-sign | B163: REVENUE | C163: IN01 | D163: 4110 | E163: Service and spares revenue | F163: 1453 | G163: 5707360.3 | H163: 5912906 | I163: =G163-H163 -> -205545.69 | J163: -0.034762211 | K163: 0.02926735 | L163: =IF(I163>0,"Actual above budget",IF(I163<0,"Actual below budget","On budget")) -> Actual below budget
A164: Same-sign | B164: REVENUE | C164: IN01 | D164: 4120 | E164: Freight recovered | F164: 53 | G164: 1213649.3 | H164: 1256146.4 | I164: =G164-H164 -> -42497.159 | J164: -0.033831374 | K164: 0.0060511083 | L164: =IF(I164>0,"Actual above budget",IF(I164<0,"Actual below budget","On budget")) -> Actual below budget
A165: Same-sign | B165: REVENUE | C165: IN01 | D165: 4190 | E165: Sales discounts and rebates | F165: 1538 | G165: -626996.73 | H165: -604907.95 | I165: =G165-H165 -> -22088.777 | K165: 0.0031451887 | L165: =IF(I165>0,"Actual above budget",IF(I165<0,"Actual below budget","On budget")) -> Actual below budget
A166: Same-sign | B166: REVENUE | C166: SG01 | D166: 4100 | E166: Product sales | F166: 1497 | G166: 22882185 | H166: 23743615 | I166: =G166-H166 -> -861430.45 | J166: -0.036280509 | K166: 0.12265782 | L166: =IF(I166>0,"Actual above budget",IF(I166<0,"Actual below budget","On budget")) -> Actual below budget
A167: Same-sign | B167: REVENUE | C167: SG01 | D167: 4110 | E167: Service and spares revenue | F167: 1448 | G167: 3473963.8 | H167: 3598201.7 | I167: =G167-H167 -> -124237.92 | J167: -0.034527781 | K167: 0.017690056 | L167: =IF(I167>0,"Actual above budget",IF(I167<0,"Actual below budget","On budget")) -> Actual below budget
A168: Same-sign | B168: REVENUE | C168: SG01 | D168: 4120 | E168: Freight recovered | F168: 41 | G168: 623304.85 | H168: 645448.81 | I168: =G168-H168 -> -22143.952 | J168: -0.034307837 | K168: 0.0031530449 | L168: =IF(I168>0,"Actual above budget",IF(I168<0,"Actual below budget","On budget")) -> Actual below budget
A169: Same-sign | B169: REVENUE | C169: SG01 | D169: 4190 | E169: Sales discounts and rebates | F169: 1638 | G169: -412202.9 | H169: -401866.14 | I169: =G169-H169 -> -10336.755 | K169: 0.0014718354 | L169: =IF(I169>0,"Actual above budget",IF(I169<0,"Actual below budget","On budget")) -> Actual below budget
A170: Same-sign | B170: REVENUE | C170: US01 | D170: 4100 | E170: Product sales | F170: 1549 | G170: 45163684 | H170: 46799586 | I170: =G170-H170 -> -1635901.6 | J170: -0.034955471 | K170: 0.23293363 | L170: =IF(I170>0,"Actual above budget",IF(I170<0,"Actual below budget","On budget")) -> Actual below budget
A171: Same-sign | B171: REVENUE | C171: US01 | D171: 4110 | E171: Service and spares revenue | F171: 1457 | G171: 6581105.2 | H171: 6816998 | I171: =G171-H171 -> -235892.8 | J171: -0.034603619 | K171: 0.033588431 | L171: =IF(I171>0,"Actual above budget",IF(I171<0,"Actual below budget","On budget")) -> Actual below budget
A172: Same-sign | B172: REVENUE | C172: US01 | D172: 4120 | E172: Freight recovered | F172: 49 | G172: 1179962.2 | H172: 1222470.2 | I172: =G172-H172 -> -42507.969 | J172: -0.034772193 | K172: 0.0060526474 | L172: =IF(I172>0,"Actual above budget",IF(I172<0,"Actual below budget","On budget")) -> Actual below budget
A173: Same-sign | B173: REVENUE | C173: US01 | D173: 4190 | E173: Sales discounts and rebates | F173: 1534 | G173: -669539.12 | H173: -655575.63 | I173: =G173-H173 -> -13963.492 | K173: 0.0019882412 | L173: =IF(I173>0,"Actual above budget",IF(I173<0,"Actual below budget","On budget")) -> Actual below budget
...

Sheet GL & Cost Drivers
A1: GL accounts and cost drivers | L1: Back to Start Here
A2: USD, scale-adjusted (provisional), signs as recorded. Sources: out_a4, out_f1-f7, out_b2, out_b6. 3-year totals.
A3: High spending is not proof of inefficiency, and a variance is not a saving. Nothing here claims a causal cost driver. Unit economics (price, volume, mix) are NOT built: quantity is populated on only 33% of revenue lines (UNSUITABLE, out_a5) and the materials unit value equals the sales unit value for every product family (out_e5), so quantity and unit-of-measure fields are unresolved. 'NOS' and 'EA' are not treated as equivalent.
A5: G1. Activity by GL account - all 24 P&L accounts used (out_a4)
A6: Share of total = |actual| / sum of |actual| over all accounts (absolute activity, so offsetting signs do not net out). '% lines negative' flags accounts whose sign convention is mixed (4190 discounts and 5120 PPV are the visible cases).
A7: GL | B7: Account | C7: Section | D7: Eligible lines (count) | E7: Actual, signed (USD) | F7: Absolute actual (USD) | G7: Share of total absolute activity | H7: % of lines negative
A8: 4100 | B8: Product sales | C8: REVENUE | D8: 10989 | E8: 1.7380499e+08 | F8: 2.0290462e+08 | G8: =F8/SUM($F$8:$F$31) -> 0.4014381 | H8: 0.06988807
A9: 4110 | B9: Service and spares revenue | C9: REVENUE | D9: 10619 | E9: 25836278 | F9: 30043878 | G9: =F9/SUM($F$8:$F$31) -> 0.059440527 | H9: 0.070628119
A10: 4120 | B10: Freight recovered | C10: REVENUE | D10: 385 | E10: 5541213.9 | F10: 6200186 | G10: =F10/SUM($F$8:$F$31) -> 0.012266803 | H10: 0.05974026
A11: 4190 | B11: Sales discounts and rebates | C11: REVENUE | D11: 10820 | E11: -2533482.9 | F11: 15381853 | G11: =F11/SUM($F$8:$F$31) -> 0.030432337 | H11: 0.57661738
A12: 5100 | B12: Materials | C12: COGS | D12: 10805 | E12: 66640644 | F12: 90575711 | G12: =F12/SUM($F$8:$F$31) -> 0.17920017 | H12: 0.13216104
A13: 5110 | B13: Inbound freight | C13: COGS | D13: 346 | E13: 5889399.2 | F13: 7867824.6 | G13: =F13/SUM($F$8:$F$31) -> 0.015566154 | H13: 0.12716763
A14: 5120 | B14: Purchase price variance | C14: COGS | D14: 348 | E14: 987251.47 | F14: 2643666 | G14: =F14/SUM($F$8:$F$31) -> 0.0052303799 | H14: 0.33333333
A15: 5200 | B15: Direct labor | C15: COGS | D15: 340 | E15: 11830633 | F15: 15660732 | G15: =F15/SUM($F$8:$F$31) -> 0.030984087 | H15: 0.13529412
A16: 5300 | B16: Factory overhead | C16: COGS | D16: 359 | E16: 7460090.4 | F16: 11251449 | G16: =F16/SUM($F$8:$F$31) -> 0.02226051 | H16: 0.17548747
A17: 6100 | B17: Salaries | C17: PEOPLE | D17: 1071 | E17: 27879880 | F17: 38887948 | G17: =F17/SUM($F$8:$F$31) -> 0.076938139 | H17: 0.13538749
A18: 6110 | B18: Bonus and incentives | C18: PEOPLE | D18: 1133 | E18: 4907347.2 | F18: 6629433.8 | G18: =F18/SUM($F$8:$F$31) -> 0.013116051 | H18: 0.13062665
A19: 6120 | B19: Benefits | C19: PEOPLE | D19: 1081 | E19: 6921711.6 | F19: 9375058.7 | G19: =F19/SUM($F$8:$F$31) -> 0.018548152 | H19: 0.13135985
... A31: 8100 | B31: Income tax expense | C31: TAX | D31: 357 | E31: 2751000.7 | F31: 3786888.1 | G31: =F31/SUM($F$8:$F$31) -> 0.0074921961 | H31: 0.14565826
A32: Total | D32: =SUM($D$8:$D$31) -> 58340 | E32: =SUM($E$8:$E$31) -> 3.8416723e+08 | F32: =SUM($F$8:$F$31) -> 5.0544435e+08
A35: G2. Cost concentration - Pareto of the 17 cost accounts (out_f1)
A36: Cost = COGS + People + Opex + D&A accounts only (COGS 5, D&A 1, OPEX 8, PEOPLE 3), ranked by absolute activity. Below-EBITDA items and Tax are NOT in this population (they are not operating costs and the Phase 4 query excludes them). Cumulative share is a running sum of shares.
A37: Rank | B37: GL | C37: Account | D37: Section | E37: Eligible lines (count) | F37: Actual, signed (USD) | G37: Absolute actual (USD) | H37: Share of cost absolute activity | I37: Cumulative share
A38: 1 | B38: 5100 | C38: Materials | D38: COGS | E38: 10805 | F38: 66640644 | G38: 90575711 | H38: =G38/SUM($G$38:$G$54) -> 0.36812982 | I38: =SUM($H$38:H38) -> 0.36812982
A39: 2 | B39: 6100 | C39: Salaries | D39: PEOPLE | E39: 1071 | F39: 27879880 | G39: 38887948 | H39: =G39/SUM($G$38:$G$54) -> 0.15805356 | I39: =SUM($H$38:H39) -> 0.52618338
A40: 3 | B40: 5200 | C40: Direct labor | D40: COGS | E40: 340 | F40: 11830633 | G40: 15660732 | H40: =G40/SUM($G$38:$G$54) -> 0.063650423 | I40: =SUM($H$38:H40) -> 0.5898338
A41: 4 | B41: 6220 | C41: Warehouse and distribution | D41: OPEX | E41: 1031 | F41: 10084193 | G41: 14039197 | H41: =G41/SUM($G$38:$G$54) -> 0.057059968 | I41: =SUM($H$38:H41) -> 0.64689377
A42: 5 | B42: 6210 | C42: Marketing programs | D42: OPEX | E42: 1086 | F42: 9062846.6 | G42: 11948547 | H42: =G42/SUM($G$38:$G$54) -> 0.048562871 | I42: =SUM($H$38:H42) -> 0.69545664
A43: 6 | B43: 5300 | C43: Factory overhead | D43: COGS | E43: 359 | F43: 7460090.4 | G43: 11251449 | H43: =G43/SUM($G$38:$G$54) -> 0.045729632 | I43: =SUM($H$38:H43) -> 0.74118627
A44: 7 | B44: 6230 | C44: Rent and facilities | D44: OPEX | E44: 1092 | F44: 7324936.6 | G44: 10529962 | H44: =G44/SUM($G$38:$G$54) -> 0.04279727 | I44: =SUM($H$38:H44) -> 0.78398354
A45: 8 | B45: 6120 | C45: Benefits | D45: PEOPLE | E45: 1081 | F45: 6921711.6 | G45: 9375058.7 | H45: =G45/SUM($G$38:$G$54) -> 0.038103357 | I45: =SUM($H$38:H45) -> 0.8220869
A46: 9 | B46: 5110 | C46: Inbound freight | D46: COGS | E46: 346 | F46: 5889399.2 | G46: 7867824.6 | H46: =G46/SUM($G$38:$G$54) -> 0.031977457 | I46: =SUM($H$38:H46) -> 0.85406435
A47: 10 | B47: 6250 | C47: IT and software | D47: OPEX | E47: 1079 | F47: 4769489.4 | G47: 6779051.6 | H47: =G47/SUM($G$38:$G$54) -> 0.027552321 | I47: =SUM($H$38:H47) -> 0.88161668
A48: 11 | B48: 6110 | C48: Bonus and incentives | D48: PEOPLE | E48: 1133 | F48: 4907347.2 | G48: 6629433.8 | H48: =G48/SUM($G$38:$G$54) -> 0.026944225 | I48: =SUM($H$38:H48) -> 0.9085609
A49: 12 | B49: 6260 | C49: Warranty provision | D49: OPEX | E49: 1075 | F49: 3972998.6 | G49: 5536685.9 | H49: =G49/SUM($G$38:$G$54) -> 0.022502934 | I49: =SUM($H$38:H49) -> 0.93106383
... A54: 17 | B54: 6300 | C54: Depreciation | D54: D&A | E54: 345 | F54: 1841552.1 | G54: 2432309 | H54: =G54/SUM($G$38:$G$54) -> 0.009885713 | I54: =SUM($H$38:H54) -> 1
A57: G3. Variance by GL account - same-sign basis (SUMIFS over 'Entity & Division' E6)
A58: Rank = rank of |variance| across accounts (1 = largest). Variance % = variance / |budget|. No favourable/adverse label.
A59: GL | B59: Account | C59: Section | D59: Actual (USD) | E59: Budget (USD) | F59: Variance (USD) | G59: Variance % of |budget| | H59: Rank by |variance|
A60: 4100 | B60: Product sales | C60: REVENUE | D60: =SUMIFS('Entity & Division'!$G$150:$G$437,'Entity & Division'!$D$150:$D$437,$A60,'Entity & Division'!$A$150:$A$437,"Same-sign") -> 1.635341e+08 | E60: =SUMIFS('Entity & Division'!$H$150:$H$437,'Entity & Division'!$D$150:$D$437,$A60,'Entity & Division'!$A$150:$A$437,"Same-sign") -> 1.6944607e+08 | F60: =D60-E60 -> -5911973.4 | G60: =IF(E60<>0,F60/ABS(E60),"n/a") -> -0.03489 | H60: =SUMPRODUCT(--(ABS($F$60:$F$83)>ABS(F60)))+1 -> 1
A61: 4110 | B61: Service and spares revenue | C61: REVENUE | D61: =SUMIFS('Entity & Division'!$G$150:$G$437,'Entity & Division'!$D$150:$D$437,$A61,'Entity & Division'!$A$150:$A$437,"Same-sign") -> 24380143 | E61: =SUMIFS('Entity & Division'!$H$150:$H$437,'Entity & Division'!$D$150:$D$437,$A61,'Entity & Division'!$A$150:$A$437,"Same-sign") -> 25256761 | F61: =D61-E61 -> -876617.45 | G61: =IF(E61<>0,F61/ABS(E61),"n/a") -> -0.03470823 | H61: =SUMPRODUCT(--(ABS($F$60:$F$83)>ABS(F61)))+1 -> 4
A62: 4120 | B62: Freight recovered | C62: REVENUE | D62: =SUMIFS('Entity & Division'!$G$150:$G$437,'Entity & Division'!$D$150:$D$437,$A62,'Entity & Division'!$A$150:$A$437,"Same-sign") -> 4961401.2 | E62: =SUMIFS('Entity & Division'!$H$150:$H$437,'Entity & Division'!$D$150:$D$437,$A62,'Entity & Division'!$A$150:$A$437,"Same-sign") -> 5135765.4 | F62: =D62-E62 -> -174364.18 | G62: =IF(E62<>0,F62/ABS(E62),"n/a") -> -0.033950962 | H62: =SUMPRODUCT(--(ABS($F$60:$F$83)>ABS(F62)))+1 -> 16
A63: 4190 | B63: Sales discounts and rebates | C63: REVENUE | D63: =SUMIFS('Entity & Division'!$G$150:$G$437,'Entity & Division'!$D$150:$D$437,$A63,'Entity & Division'!$A$150:$A$437,"Same-sign") -> -2478927.9 | E63: =SUMIFS('Entity & Division'!$H$150:$H$437,'Entity & Division'!$D$150:$D$437,$A63,'Entity & Division'!$A$150:$A$437,"Same-sign") -> -2418845.7 | F63: =D63-E63 -> -60082.231 | G63: =IF(E63<>0,F63/ABS(E63),"n/a") -> -0.024839217 | H63: =SUMPRODUCT(--(ABS($F$60:$F$83)>ABS(F63)))+1 -> 21
A64: 5100 | B64: Materials | C64: COGS | D64: =SUMIFS('Entity & Division'!$G$150:$G$437,'Entity & Division'!$D$150:$D$437,$A64,'Entity & Division'!$A$150:$A$437,"Same-sign") -> 62938257 | E64: =SUMIFS('Entity & Division'!$H$150:$H$437,'Entity & Division'!$D$150:$D$437,$A64,'Entity & Division'!$A$150:$A$437,"Same-sign") -> 59137481 | F64: =D64-E64 -> 3800775.2 | G64: =IF(E64<>0,F64/ABS(E64),"n/a") -> 0.064270158 | H64: =SUMPRODUCT(--(ABS($F$60:$F$83)>ABS(F64)))+1 -> 2
A65: 5110 | B65: Inbound freight | C65: COGS | D65: =SUMIFS('Entity & Division'!$G$150:$G$437,'Entity & Division'!$D$150:$D$437,$A65,'Entity & Division'!$A$150:$A$437,"Same-sign") -> 5562764 | E65: =SUMIFS('Entity & Division'!$H$150:$H$437,'Entity & Division'!$D$150:$D$437,$A65,'Entity & Division'!$A$150:$A$437,"Same-sign") -> 5231665.2 | F65: =D65-E65 -> 331098.77 | G65: =IF(E65<>0,F65/ABS(E65),"n/a") -> 0.063287454 | H65: =SUMPRODUCT(--(ABS($F$60:$F$83)>ABS(F65)))+1 -> 11
A66: 5120 | B66: Purchase price variance | C66: COGS | D66: =SUMIFS('Entity & Division'!$G$150:$G$437,'Entity & Division'!$D$150:$D$437,$A66,'Entity & Division'!$A$150:$A$437,"Same-sign") -> 847357.13 | E66: =SUMIFS('Entity & Division'!$H$150:$H$437,'Entity & Division'!$D$150:$D$437,$A66,'Entity & Division'!$A$150:$A$437,"Same-sign") -> 801020.11 | F66: =D66-E66 -> 46337.018 | G66: =IF(E66<>0,F66/ABS(E66),"n/a") -> 0.057847508 | H66: =SUMPRODUCT(--(ABS($F$60:$F$83)>ABS(F66)))+1 -> 22
A67: 5200 | B67: Direct labor | C67: COGS | D67: =SUMIFS('Entity & Division'!$G$150:$G$437,'Entity & Division'!$D$150:$D$437,$A67,'Entity & Division'!$A$150:$A$437,"Same-sign") -> 11064146 | E67: =SUMIFS('Entity & Division'!$H$150:$H$437,'Entity & Division'!$D$150:$D$437,$A67,'Entity & Division'!$A$150:$A$437,"Same-sign") -> 10385747 | F67: =D67-E67 -> 678398.68 | G67: =IF(E67<>0,F67/ABS(E67),"n/a") -> 0.065320162 | H67: =SUMPRODUCT(--(ABS($F$60:$F$83)>ABS(F67)))+1 -> 5
A68: 5300 | B68: Factory overhead | C68: COGS | D68: =SUMIFS('Entity & Division'!$G$150:$G$437,'Entity & Division'!$D$150:$D$437,$A68,'Entity & Division'!$A$150:$A$437,"Same-sign") -> 7388802.2 | E68: =SUMIFS('Entity & Division'!$H$150:$H$437,'Entity & Division'!$D$150:$D$437,$A68,'Entity & Division'!$A$150:$A$437,"Same-sign") -> 6949670.1 | F68: =D68-E68 -> 439132.09 | G68: =IF(E68<>0,F68/ABS(E68),"n/a") -> 0.063187472 | H68: =SUMPRODUCT(--(ABS($F$60:$F$83)>ABS(F68)))+1 -> 8
A69: 6100 | B69: Salaries | C69: PEOPLE | D69: =SUMIFS('Entity & Division'!$G$150:$G$437,'Entity & Division'!$D$150:$D$437,$A69,'Entity & Division'!$A$150:$A$437,"Same-sign") -> 27116516 | E69: =SUMIFS('Entity & Division'!$H$150:$H$437,'Entity & Division'!$D$150:$D$437,$A69,'Entity & Division'!$A$150:$A$437,"Same-sign") -> 25492057 | F69: =D69-E69 -> 1624459.1 | G69: =IF(E69<>0,F69/ABS(E69),"n/a") -> 0.06372413 | H69: =SUMPRODUCT(--(ABS($F$60:$F$83)>ABS(F69)))+1 -> 3
A70: 6110 | B70: Bonus and incentives | C70: PEOPLE | D70: =SUMIFS('Entity & Division'!$G$150:$G$437,'Entity & Division'!$D$150:$D$437,$A70,'Entity & Division'!$A$150:$A$437,"Same-sign") -> 4586940.2 | E70: =SUMIFS('Entity & Division'!$H$150:$H$437,'Entity & Division'!$D$150:$D$437,$A70,'Entity & Division'!$A$150:$A$437,"Same-sign") -> 4311097.1 | F70: =D70-E70 -> 275843.13 | G70: =IF(E70<>0,F70/ABS(E70),"n/a") -> 0.063984439 | H70: =SUMPRODUCT(--(ABS($F$60:$F$83)>ABS(F70)))+1 -> 12
A71: 6120 | B71: Benefits | C71: PEOPLE | D71: =SUMIFS('Entity & Division'!$G$150:$G$437,'Entity & Division'!$D$150:$D$437,$A71,'Entity & Division'!$A$150:$A$437,"Same-sign") -> 6561184.2 | E71: =SUMIFS('Entity & Division'!$H$150:$H$437,'Entity & Division'!$D$150:$D$437,$A71,'Entity & Division'!$A$150:$A$437,"Same-sign") -> 6168636.2 | F71: =D71-E71 -> 392547.98 | G71: =IF(E71<>0,F71/ABS(E71),"n/a") -> 0.063636105 | H71: =SUMPRODUCT(--(ABS($F$60:$F$83)>ABS(F71)))+1 -> 10
... A83: 8100 | B83: Income tax expense | C83: TAX | D83: =SUMIFS('Entity & Division'!$G$150:$G$437,'Entity & Division'!$D$150:$D$437,$A83,'Entity & Division'!$A$150:$A$437,"Same-sign") -> 2812303.9 | E83: =SUMIFS('Entity & Division'!$H$150:$H$437,'Entity & Division'!$D$150:$D$437,$A83,'Entity & Division'!$A$150:$A$437,"Same-sign") -> 2645687.7 | F83: =D83-E83 -> 166616.19 | G83: =IF(E83<>0,F83/ABS(E83),"n/a") -> 0.062976513 | H83: =SUMPRODUCT(--(ABS($F$60:$F$83)>ABS(F83)))+1 -> 18
A84: Amber = five largest absolute variances.
A87: G4. Cost mix and cost-to-revenue ratios by year (out_f3, out_f4)
A88: Ratios are absolute-value ratios (|cost| / |revenue|) and signed ratios; the two differ because of negative lines. Not a margin.
A89: Year | B89: Section | C89: Absolute actual (USD) | D89: Share of cost (absolute) | E89: Signed actual (USD) | G89: Year | H89: COGS / revenue (abs) | I89: People / revenue (abs) | J89: Opex / revenue (abs) | K89: COGS / revenue (signed) | L89: People / revenue (signed) | M89: Opex / revenue (signed)
A90: 2023 | B90: COGS | C90: 39921143 | D90: 0.51725057 | E90: 28820262 | G90: 3 years | H90: 0.50288419 | I90: 0.21566151 | J90: 0.23855181 | K90: 0.45797422 | L90: 0.19594935 | M90: 0.21620042
A91: 2023 | B91: People costs | C91: 18057210 | D91: 0.2339638 | E91: 13384754 | G91: 2023 | H91: 0.51186707 | I91: 0.23152872 | J91: 0.23690777 | K91: 0.4701846 | L91: 0.21836391 | M91: 0.21948079
A92: 2023 | B92: Operating expenses | C92: 18476729 | D92: 0.23939942 | E92: 13453214 | G92: 2024 | H92: 0.49313267 | I92: 0.20636722 | J92: 0.24204613 | K92: 0.4298238 | L92: 0.18937301 | M92: 0.21169799
A93: 2023 | B93: D&A (depreciation, GL 6300) | C93: 724423.49 | D93: 0.0093862158 | E93: 557556.05 | G93: 2025 | H93: 0.5045114 | I93: 0.21086219 | J93: 0.2365998 | K93: 0.4753327 | L93: 0.18311406 | M93: 0.21783062
A94: 2024 | B94: COGS | C94: 42811703 | D94: 0.51861512 | E94: 30243513
A95: 2024 | B95: People costs | C95: 17915933 | D95: 0.21703117 | E95: 13324774
A96: 2024 | B96: Operating expenses | C96: 21013426 | D96: 0.25455377 | E96: 14895617
A97: 2024 | B97: D&A (depreciation, GL 6300) | C97: 808985.65 | D97: 0.0097999416 | E97: 584497.19
A98: 2025 | B98: COGS | C98: 45266536 | D98: 0.52444452 | E98: 33744243
A99: 2025 | B99: People costs | C99: 18919297 | D99: 0.2191933 | E99: 12999411
A100: 2025 | B100: Operating expenses | C100: 21228566 | D100: 0.2459478 | E100: 15463968
A101: 2025 | B101: D&A (depreciation, GL 6300) | C101: 898899.88 | D101: 0.010414384 | E101: 699498.83
A104: G5. Concentration (out_f2)
A105: HHI = sum of squared shares; the equal-share benchmark is 1 / members. Concentration is descriptive: it does not say spend is excessive.
A106: Dimension | B106: Members (count) | C106: Largest member | D106: Top-1 share | E106: Top-3 share | F106: HHI | G106: Equal-share benchmark (1/members)
A107: gl_account | B107: 17 | C107: 5100 | D107: 0.36812982 | E107: 0.5898338 | F107: 0.17959307 | G107: 0.058823529
A108: legal_entity | B108: 6 | C108: US01 | D108: 0.25785244 | E108: 0.64669717 | F108: 0.18781712 | G108: 0.16666667
A109: cost_center (opex+people) | B109: 8 | C109: CC410 | D109: 0.17548397 | E109: 0.5226522 | F109: 0.14498004 | G109: 0.125
A110: division | B110: 5 | C110: Consumer Durables | D110: 0.36052864 | E110: 0.8544491 | F110: 0.26538375 | G110: 0.2
A113: G6. Persistent deviations: entity x GL cells that are on the same side of budget in most months (out_f5; all 144 cells, filter/sort)
A114: Dominant-direction share = months on the more common side / months with data. A share near 100% means the deviation is systematic rather than month-to-month noise (INS-03).
A115: Entity | B115: GL | C115: Account | D115: Section | E115: Months with data (count) | F115: Months above budget (count) | G115: Months below budget (count) | H115: Dominant-direction share | I115: Variance (USD) | J115: Variance %
A116: AE01 | B116: 4100 | C116: Product sales | D116: REVENUE | E116: 36 | F116: 0 | G116: 36 | H116: 1 | I116: -601660.13 | J116: -0.035149956
A117: AE01 | B117: 4110 | C117: Service and spares revenue | D117: REVENUE | E117: 36 | F117: 0 | G117: 36 | H117: 1 | I117: -92412.588 | J117: -0.034672301
A118: AE01 | B118: 4120 | C118: Freight recovered | D118: REVENUE | E118: 30 | F118: 0 | G118: 30 | H118: 1 | I118: -19264.461 | J118: -0.032333615
A119: AE01 | B119: 4190 | C119: Sales discounts and rebates | D119: REVENUE | E119: 36 | F119: 16 | G119: 20 | H119: 0.55555556 | I119: -2615.8276 | J119: -0.01218524
A120: AE01 | B120: 5100 | C120: Materials | D120: COGS | E120: 36 | F120: 36 | G120: 0 | H120: 1 | I120: 369549.88 | J120: 0.064250708
A121: AE01 | B121: 5110 | C121: Inbound freight | D121: COGS | E121: 27 | F121: 26 | G121: 1 | H121: 0.96296296 | I121: 36436.64 | J121: 0.063289537
A122: AE01 | B122: 5120 | C122: Purchase price variance | D122: COGS | E122: 30 | F122: 17 | G122: 13 | H122: 0.56666667 | I122: -574.9397
A123: AE01 | B123: 5200 | C123: Direct labor | D123: COGS | E123: 30 | F123: 28 | G123: 2 | H123: 0.93333333 | I123: 68311.393 | J123: 0.065055375
A124: AE01 | B124: 5300 | C124: Factory overhead | D124: COGS | E124: 34 | F124: 27 | G124: 7 | H124: 0.79411765 | I124: 33217.134 | J124: 0.071606379
A125: AE01 | B125: 6100 | C125: Salaries | D125: PEOPLE | E125: 35 | F125: 33 | G125: 2 | H125: 0.94285714 | I125: 156509.05 | J125: 0.061725282
A126: AE01 | B126: 6110 | C126: Bonus and incentives | D126: PEOPLE | E126: 36 | F126: 34 | G126: 2 | H126: 0.94444444 | I126: 30753.988 | J126: 0.062372752
A127: AE01 | B127: 6120 | C127: Benefits | D127: PEOPLE | E127: 36 | F127: 35 | G127: 1 | H127: 0.97222222 | I127: 38562.519 | J127: 0.063175709
A128: AE01 | B128: 6200 | C128: Travel | D128: OPEX | E128: 36 | F128: 34 | G128: 2 | H128: 0.94444444 | I128: 17400.298 | J128: 0.070068701
A129: AE01 | B129: 6210 | C129: Marketing programs | D129: OPEX | E129: 35 | F129: 35 | G129: 0 | H129: 1 | I129: 60109.481 | J129: 0.064143062
A130: AE01 | B130: 6220 | C130: Warehouse and distribution | D130: OPEX | E130: 36 | F130: 35 | G130: 1 | H130: 0.97222222 | I130: 68364.475 | J130: 0.067800358
A131: AE01 | B131: 6230 | C131: Rent and facilities | D131: OPEX | E131: 35 | F131: 33 | G131: 2 | H131: 0.94285714 | I131: 37786.955 | J131: 0.064100868
A132: AE01 | B132: 6240 | C132: Professional fees | D132: OPEX | E132: 36 | F132: 33 | G132: 3 | H132: 0.91666667 | I132: 23056.89 | J132: 0.068421776
A133: AE01 | B133: 6250 | C133: IT and software | D133: OPEX | E133: 36 | F133: 33 | G133: 3 | H133: 0.91666667 | I133: 21395.29 | J133: 0.06383581
A134: AE01 | B134: 6260 | C134: Warranty provision | D134: OPEX | E134: 36 | F134: 36 | G134: 0 | H134: 1 | I134: 25638.725 | J134: 0.065668061
... A137: AE01 | B137: 7100 | C137: Interest expense | D137: BELOW_EBITDA | E137: 28 | F137: 28 | G137: 0 | H137: 1 | I137: 4917.8096 | J137: 0.067979651
A138: AE01 | B138: 7200 | C138: FX gain or loss | D138: BELOW_EBITDA | E138: 29 | F138: 11 | G138: 18 | H138: 0.62068966 | I138: 104.6917
A139: AE01 | B139: 8100 | C139: Income tax expense | D139: TAX | E139: 31 | F139: 29 | G139: 2 | H139: 0.93548387 | I139: 18873.104 | J139: 0.06465054
...

Sheet Gross Profit
A1: Gross profit and margin - three explicit treatments | K1: Back to Start Here
A2: USD, scale-adjusted (provisional). Gross profit = Revenue - COGS (GL 4100-4190 and 5100-5300). Sources: out_e1-e4.
A3: No treatment is the authoritative accounting answer. Discount account 4190 is negative on about 58% of its lines and positive on the rest, and 5120 is mixed too, so the sign convention is unresolved (R9). S1 = every amount signed as recorded. S2 = discounts forced to reduce revenue (-|4190|). S3 = discounts excluded (gross sales). Row sets: 'All eligible lines' (headline) and 'ROWS_ALL_NON_NEGATIVE' = lines where none of the available amount columns is negative; it is an all-non-negative population, NOT a genuinely sign-consistent one (zero amounts count as non-negative; all-negative, single-column-flip and mixed rows are outside it). The second row set is a sensitivity, not a correction.
A5: GP1. Gross profit by row set, treatment and year (out_e1)
A6: Gross margin % = gross profit / revenue, shown only when revenue > 0.
A7: Row set | B7: Treatment | C7: Period | D7: Lines (count) | E7: Revenue (USD) | F7: COGS (USD) | G7: Gross profit (USD) | H7: Gross margin %
A8: All eligible lines | B8: S1 - signed as recorded | C8: 2023 | D8: 15092 | E8: 61295631 | F8: 28820262 | G8: =E8-F8 -> 32475369 | H8: =IF(E8>0,G8/E8,"n/a") -> 0.5298154
A9: All eligible lines | B9: S1 - signed as recorded | C9: 2024 | D9: 14971 | E9: 70362584 | F9: 30243513 | G9: =E9-F9 -> 40119070 | H9: =IF(E9>0,G9/E9,"n/a") -> 0.5701762
A10: All eligible lines | B10: S1 - signed as recorded | C10: 2025 | D10: 14948 | E10: 70990788 | F10: 33744243 | G10: =E10-F10 -> 37246545 | H10: =IF(E10>0,G10/E10,"n/a") -> 0.5246673
A11: All eligible lines | B11: S1 - signed as recorded | C11: ALL YEARS | D11: 45011 | E11: 2.02649e+08 | F11: 92808018 | G11: =E11-F11 -> 1.0984098e+08 | H11: =IF(E11>0,G11/E11,"n/a") -> 0.54202578
A12: All eligible lines | B12: S2 - discount (4190) at absolute value | C12: 2023 | D12: 15092 | E12: 57208113 | F12: 28820262 | G12: =E12-F12 -> 28387851 | H12: =IF(E12>0,G12/E12,"n/a") -> 0.49622072
A13: All eligible lines | B13: S2 - discount (4190) at absolute value | C13: 2024 | D13: 14971 | E13: 66280235 | F13: 30243513 | G13: =E13-F13 -> 36036722 | H13: =IF(E13>0,G13/E13,"n/a") -> 0.54370239
A14: All eligible lines | B14: S2 - discount (4190) at absolute value | C14: 2025 | D14: 14948 | E14: 66312284 | F14: 33744243 | G14: =E14-F14 -> 32568041 | H14: =IF(E14>0,G14/E14,"n/a") -> 0.49113134
A15: All eligible lines | B15: S2 - discount (4190) at absolute value | C15: ALL YEARS | D15: 45011 | E15: 1.8980063e+08 | F15: 92808018 | G15: =E15-F15 -> 96992615 | H15: =IF(E15>0,G15/E15,"n/a") -> 0.51102366
A16: All eligible lines | B16: S3 - excluding discounts (4190) | C16: 2023 | D16: 15092 | E16: 61961255 | F16: 28820262 | G16: =E16-F16 -> 33140994 | H16: =IF(E16>0,G16/E16,"n/a") -> 0.5348664
A17: All eligible lines | B17: S3 - excluding discounts (4190) | C17: 2024 | D17: 14971 | E17: 71288869 | F17: 30243513 | G17: =E17-F17 -> 41045355 | H17: =IF(E17>0,G17/E17,"n/a") -> 0.57576107
A18: All eligible lines | B18: S3 - excluding discounts (4190) | C18: 2025 | D18: 14948 | E18: 71932361 | F18: 33744243 | G18: =E18-F18 -> 38188118 | H18: =IF(E18>0,G18/E18,"n/a") -> 0.53088926
A19: All eligible lines | B19: S3 - excluding discounts (4190) | C19: ALL YEARS | D19: 45011 | E19: 2.0518249e+08 | F19: 92808018 | G19: =E19-F19 -> 1.1237447e+08 | H19: =IF(E19>0,G19/E19,"n/a") -> 0.5476806
... A31: Lines with no negative available amount (NOT sign-consistent) | B31: S3 - excluding discounts (4190) | C31: ALL YEARS | D31: 26895 | E31: 1.6711147e+08 | F31: 84317375 | G31: =E31-F31 -> 82794099 | H31: =IF(E31>0,G31/E31,"n/a") -> 0.49544234
A34: GP2. Margin range at a glance - all years (links to GP1)
A35: How much does the headline margin depend on the discount treatment and the row set? Read it as a range with its labels, not as one number.
A36: Treatment | C36: GM % - all eligible lines | D36: GM % - no-negative-amount lines | E36: Gross profit (USD) - all eligible lines | F36: Gross profit (USD) - no-negative-amount lines
A37: S1 - signed as recorded | C37: ='Gross Profit'!$H$11 -> 0.54202578 | D37: ='Gross Profit'!$H$23 -> 0.50950906 | E37: ='Gross Profit'!$G$11 -> 1.0984098e+08 | F37: ='Gross Profit'!$G$23 -> 87586667
A38: S2 - discount (4190) at absolute value | C38: ='Gross Profit'!$H$15 -> 0.51102366 | D38: ='Gross Profit'!$H$27 -> 0.48054495 | E38: ='Gross Profit'!$G$15 -> 96992615 | F38: ='Gross Profit'!$G$27 -> 78001531
A39: S3 - excluding discounts (4190) | C39: ='Gross Profit'!$H$19 -> 0.5476806 | D39: ='Gross Profit'!$H$31 -> 0.49544234 | E39: ='Gross Profit'!$G$19 -> 1.1237447e+08 | F39: ='Gross Profit'!$G$31 -> 82794099
A51: GP3. Gross profit vs budget - same-sign lines, by treatment (out_e3, out_e4)
A52: Bridge: GP variance = revenue variance - COGS variance (a higher COGS than budget lowers gross profit). Margin gap in percentage points.
A53: Treatment | B53: Actual revenue (USD) | C53: Budget revenue (USD) | D53: Actual COGS (USD) | E53: Budget COGS (USD) | F53: Actual GP (USD) | G53: Budget GP (USD) | H53: GP variance (USD) | I53: Revenue variance (USD) | J53: COGS variance (USD) | K53: Bridge difference = GP var - (rev var - COGS var) | L53: Actual GM % | M53: Budget GM % | N53: Margin gap (percentage points)
A54: S1 - signed as recorded | B54: 1.9039672e+08 | C54: 1.9741975e+08 | D54: 87801326 | E54: 82505584 | F54: =B54-D54 -> 1.0259539e+08 | G54: =C54-E54 -> 1.1491417e+08 | H54: =F54-G54 -> -12318779 | I54: =B54-C54 -> -7023037.3 | J54: =D54-E54 -> 5295741.8 | K54: =H54-(I54-J54) -> 0 | L54: =IF(B54>0,F54/B54,"n/a") -> 0.53885063 | M54: =IF(C54>0,G54/C54,"n/a") -> 0.5820804 | N54: =(L54-M54)*100 -> -4.3229773
A55: S2 - discount (4190) at absolute value | B55: 1.7921536e+08 | C55: 1.8652988e+08 | D55: 87801326 | E55: 82505584 | F55: =B55-D55 -> 91414039 | G55: =C55-E55 -> 1.040243e+08 | H55: =F55-G55 -> -12610259 | I55: =B55-C55 -> -7314516.7 | J55: =D55-E55 -> 5295741.8 | K55: =H55-(I55-J55) -> 0 | L55: =IF(B55>0,F55/B55,"n/a") -> 0.51007925 | M55: =IF(C55>0,G55/C55,"n/a") -> 0.55768168 | N55: =(L55-M55)*100 -> -4.7602429
A56: S3 - excluding discounts (4190) | B56: 1.9287564e+08 | C56: 1.998386e+08 | D56: 87801326 | E56: 82505584 | F56: =B56-D56 -> 1.0507432e+08 | G56: =C56-E56 -> 1.1733301e+08 | H56: =F56-G56 -> -12258697 | I56: =B56-C56 -> -6962955 | J56: =D56-E56 -> 5295741.8 | K56: =H56-(I56-J56) -> 0 | L56: =IF(B56>0,F56/B56,"n/a") -> 0.54477754 | M56: =IF(C56>0,G56/C56,"n/a") -> 0.5871389 | N56: =(L56-M56)*100 -> -4.2361363
A59: GP4. Gross profit by entity (out_e2; all years)
A60: Filter by row set and treatment. Entity margins are comparable only within the same treatment and row set.
A61: Row set | B61: Treatment | C61: Entity | D61: Revenue (USD) | E61: COGS (USD) | F61: Gross profit (USD) | G61: Gross margin %
A62: All eligible lines | B62: S1 - signed as recorded | C62: AE01 | D62: 21148202 | E62: 8731913.5 | F62: =D62-E62 -> 12416288 | G62: =IF(D62>0,F62/D62,"n/a") -> 0.58710847
A63: All eligible lines | B63: S1 - signed as recorded | C63: DE01 | D63: 29549094 | E63: 15097025 | F63: =D63-E63 -> 14452069 | G63: =IF(D63>0,F63/D63,"n/a") -> 0.4890867
A64: All eligible lines | B64: S1 - signed as recorded | C64: GB01 | D64: 20503977 | E64: 9747172.4 | F64: =D64-E64 -> 10756805 | G64: =IF(D64>0,F64/D64,"n/a") -> 0.5246204
A65: All eligible lines | B65: S1 - signed as recorded | C65: IN01 | D65: 48348042 | E65: 21648388 | F65: =D65-E65 -> 26699654 | G65: =IF(D65>0,F65/D65,"n/a") -> 0.55223857
A66: All eligible lines | B66: S1 - signed as recorded | C66: SG01 | D66: 27763849 | E66: 13579996 | F66: =D66-E66 -> 14183853 | G66: =IF(D66>0,F66/D66,"n/a") -> 0.51087487
A67: All eligible lines | B67: S1 - signed as recorded | C67: US01 | D67: 55335838 | E67: 24003522 | F67: =D67-E67 -> 31332316 | G67: =IF(D67>0,F67/D67,"n/a") -> 0.56622105
A68: All eligible lines | B68: S2 - discount (4190) at absolute value | C68: AE01 | D68: 19684736 | E68: 8731913.5 | F68: =D68-E68 -> 10952823 | G68: =IF(D68>0,F68/D68,"n/a") -> 0.55641196
A69: All eligible lines | B69: S2 - discount (4190) at absolute value | C69: DE01 | D69: 27548162 | E69: 15097025 | F69: =D69-E69 -> 12451136 | G69: =IF(D69>0,F69/D69,"n/a") -> 0.45197703
A70: All eligible lines | B70: S2 - discount (4190) at absolute value | C70: GB01 | D70: 19180800 | E70: 9747172.4 | F70: =D70-E70 -> 9433627.2 | G70: =IF(D70>0,F70/D70,"n/a") -> 0.49182659
A71: All eligible lines | B71: S2 - discount (4190) at absolute value | C71: IN01 | D71: 45474864 | E71: 21648388 | F71: =D71-E71 -> 23826475 | G71: =IF(D71>0,F71/D71,"n/a") -> 0.52394825
A72: All eligible lines | B72: S2 - discount (4190) at absolute value | C72: SG01 | D72: 26010274 | E72: 13579996 | F72: =D72-E72 -> 12430278 | G72: =IF(D72>0,F72/D72,"n/a") -> 0.47789876
A73: All eligible lines | B73: S2 - discount (4190) at absolute value | C73: US01 | D73: 51901797 | E73: 24003522 | F73: =D73-E73 -> 27898275 | G73: =IF(D73>0,F73/D73,"n/a") -> 0.53752041
... A97: Lines with no negative available amount (NOT sign-consistent) | B97: S3 - excluding discounts (4190) | C97: US01 | D97: 46112024 | E97: 22585114 | F97: =D97-E97 -> 23526910 | G97: =IF(D97>0,F97/D97,"n/a") -> 0.51021205

Sheet Insights & Actions
A1: Financial insights and actions | D1: Back to Start Here
A2: Source: the corrected Phase 4 insight register (docs/PHASE4_INSIGHT_REGISTER.md, generated from the validated database). Ranked by materiality, persistence, confidence and actionability.
A3: Every insight separates OBSERVED FACT from HYPOTHESIS. Observed variance is not a saving: variance, financial exposure, a cause hypothesis and recoverable savings are kept apart. Confidence reflects synthetic, assumption-dependent data. Scores (1-3 per axis) are a project convention. Rows 'Check' compare figures recomputed from the database with the register text (formula-based, see Reconciliation).
A5: Ranking
A6: Total = materiality + persistence + confidence + actionability (each 1-3). Ties are ordered by the register's order.
A7: Rank / ID | B7: Headline | C7: Score (of 12) | D7: Confidence axis (1-3)
A8: #1 INS-01 | B8: The journal-status rule is the largest swing factor in the revenue and result headlines among the four assumptions tested (status, scale, sign, duplicates) | C8: 11 | D8: 2
A9: #2 INS-02 | B9: Lines whose forecast and actual have opposite signs (10% to 13% of lines) carry 89% to 91% of the absolute forecast error; whether they are data defects or legitimate entries is unresolved | C9: 11 | D9: 2
A10: #3 INS-03 | B10: Actuals sit a near-constant 3.6% below budget on revenue and 6.4% above budget on costs on same-sign lines in all 36 months, all 6 entities, all 5 divisions and every one of the 20 operating accounts (the all-lines view differs) | C10: 10 | D10: 2
A11: #4 INS-04 | B11: Gross profit is $12.3M below budget on same-sign lines: 57% of the gap is revenue below budget and 43% is COGS above budget; the margin gap holds under all three discount treatments | C11: 10 | D11: 2
A12: #5 INS-05 | B12: On a matched same-sign subset the forecast is closer to actuals than the budget; on all comparable lines the margin is 26.8% vs 29.3% revenue WAPE (forecast vs budget) and reverses for people costs, and neither view establishes forecast skill | C12: 10 | D12: 2
A13: #6 INS-06 | B13: Salary lines carry a near-constant rate per FTE within each entity; without a budgeted FTE plan and the budget's rate method, the people-cost variance cannot be split into rate and volume | C13: 10 | D13: 2
A14: #7 INS-07 | B14: Scale restoration moves the result proxy by $3.1M, and the larger (MEDIUM-confidence) tier cannot be verified against price | C14: 9 | D14: 2
A17: #1 INS-01 - The journal-status rule is the largest swing factor in the revenue and result headlines among the four assumptions tested (status, scale, sign, duplicates)
A18: 1. Insight ID and headline | B18: INS-01 - The journal-status rule is the largest swing factor in the revenue and result headlines among the four assumptions tested (status, scale, sign, duplicates)
A19: 2. Business question | B19: How much of the reported revenue, cost and result depends on which journal statuses are counted?
A20: 3. Period and population | B20: P&L lines passing every gate except the status gate: 136,330 lines, Jan 2023 - Dec 2025. Baseline (provisional rule R6) = Posted only: 58,340 lines (42.8%).
A21: 4. Quantified financial result (observed fact) | B21: Policy scenarios: revenue $202.65M (Posted only, baseline) vs $404.38M (all except Rejected) vs $471.58M (all statuses); result proxy $26.32M vs $49.16M vs $53.88M. Across these 3 policy scenarios the revenue headline moves by 133% of the baseline and the result proxy by 105%; the corresponding ranges for the scale, duplicate and sign factors (each over its own policy scenarios and baseline) are 4%, 1% and 19% of revenue. Partition diagnostic: the four non-Posted statuses hold near-equal volumes of lines (19,777, 19,302, 19,467, 19,444 for Pending, Parked, Rejected, blank) and of revenue ($67.6M, $67.0M, $67.2M, $67.1M); Posted holds 58,340 lines (42.8%, about three times any other status) and $202.6M.
A22: 5. Formula and metric definition | B22: Revenue = REVENUE section; cost = COGS + PEOPLE + OPEX; result proxy = revenue - cost (not a reported operating profit; D&A, below-EBITDA and tax excluded). USD, scale-adjusted (provisional), signs as recorded. Two kinds of scenario are kept apart: REPORTING-POLICY scenarios (Posted only = baseline, all except Rejected, all statuses) are the comparable alternatives that the swing ranking uses; STATUS-PARTITION diagnostics (Pending, Parked, Rejected and blank on their own) only show how the any-status population splits and are not alternative reporting policies.
A23: 6. Comparison / baseline | B23: Baseline = Posted-only population (rule R6) with the scale-adjusted amounts
A24: 7. Driver breakdown and contribution | B24: Reporting-policy scenarios (ranked) Scenario | Class | Lines | Revenue | Cost | Result proxy POSTED_ONLY (baseline) | BASELINE | 58,340 | $202.65M | $176.33M | $26.32M ALL_EXCEPT_REJECTED | POLICY_SCENARIO | 116,863 | $404.38M | $355.23M | $49.16M ALL_STATUSES | POLICY_SCENARIO | 136,330 | $471.58M | $417.70M | $53.88M Status-partition diagnostics (not ranked; the five statuses add up to the all-status population) Scenario | Class | Lines | Revenue | Cost | Result proxy POSTED_ONLY (baseline) | BASELINE | 58,340 | $202.65M | $176.33M | $26.32M PENDING_ONLY | STATUS_PARTITION_DIAGNOSTIC | 19,777 | $67.57M | $57.89M | $9.68M PARKED_ONLY | STATUS_PARTITION_DIAGNOSTIC | 19,302 | $67.04M | $61.73M | $5.31M REJECTED_ONLY | STATUS_PARTITION_DIAGNOSTIC | 19,467 | $67.19M | $62.47M | $4.72M BLANK_ONLY | STATUS_PARTITION_DIAGNOSTIC | 19,444 | $67.13M | $59.28M | $7.85M
A25: 8. Validation evidence / Phase 4 reference | B25: Single-status buckets partition the any-status population exactly (checks I03, I04); scenario classes are validated (I13-I15: the ranking uses only baseline + policy scenarios); all 15 scenarios recomputed in pandas from the CSV (cross-check X8xx) and the status range recomputed independently (X98_REV); Posted subset equals the eligible flag (L27).
A26: 9. Observed fact vs hypothesis | B26: OBSERVED: see field 4. HYPOTHESIS / INTERPRETATION: The split is almost exactly 3:1:1:1:1 (Posted = 42.8% of lines against 3/7 = 42.9%), and each non-Posted status carries about the same revenue, so status shows no visible link to line size or section. A genuine workflow would normally leave a Posted majority with small Pending/Parked tails and few Rejected lines. Whether Rejected lines belong in the books, and whether Parked/Pending are accruals or cut-off items, decides which of several very different P&Ls is 'the' P&L. The ranking measures how far each unresolved assumption can move the headline under the policies defined here; it is a sensitivity, not an estimate of error, and the ranges of different factors are not strictly like-for-like because each factor has its own baseline and its own set of policies. ALTERNATIVE EXPLANATIONS: (a) The extract is a union of several scenarios or versions that were all labelled by status by accident. (b) Status is assigned at random in the generator (the dataset is synthetic - provenance unverified). (c) Posting really is 43% complete at the extract date, in which case the all-status view overstates. None can be tested from the file.
A27: 10. Confidence level and reasons | B27: High that the dependency exists (arithmetic, reconciled). Low on which scenario is right: it needs the business definition of each status; the official journal-status rule is not chosen here. Limitation: the proxy omits D&A, below-EBITDA and tax.
A28: 11. Data limitations | B28: the proxy omits D&A, below-EBITDA and tax. Standing limits: synthetic extract with unverified provenance; Posted-only status rule (R6) and scale restoration (R7) are provisional; sign convention unresolved (R9); forecast has no version or as-of date.
A29: 12. Recommended action | B29: Before any report is published, obtain written definitions for Posted, Pending, Parked, Rejected and blank, and the cut-off rule for the extract. Until then show headline figures as a range (Posted-only to all-except-Rejected), never a point estimate.
... A33: 16. Follow-up KPI / validation step | B33: KPI : share of lines with a documented status definition = 100%; share of period-end lines not Posted. Monitoring: Re-run out_i1/out_i2 each close; alert when the Posted share of any-status lines (out_g1: posted_rows / any_rows) leaves the range observed over the 36 months.
A34: Back to ranking
A36: #2 INS-02 - Lines whose forecast and actual have opposite signs (10% to 13% of lines) carry 89% to 91% of the absolute forecast error; whether they are data defects or legitimate entries is unresolved
A37: 1. Insight ID and headline | B37: INS-02 - Lines whose forecast and actual have opposite signs (10% to 13% of lines) carry 89% to 91% of the absolute forecast error; whether they are data defects or legitimate entries is unresolved
A38: 2. Business question | B38: What drives the large forecast error, and what remains unresolved about it?
A39: 3. Period and population | B39: Eligible P&L lines with a forecast value: 53,543 (four operating sections).
A40: 4. Quantified financial result (observed fact) | B40: WAPE on all lines (scale-adjusted amounts, signs as recorded): revenue 26.6%, COGS 27.0%, people 29.3%, opex 27.9%. On same-sign non-zero lines only: 2.6%, 3.4%, 3.4%, 3.4%. 10.5% of revenue lines are opposite-sign but they carry 91.2% of the absolute revenue forecast error (total absolute revenue forecast error $63.93M); zero-involved lines carry 0.2% or less in every section. The shares come from the explicit four-category rule and are recomputed independently in pandas (X97).
A41: 5. Formula and metric definition | B41: Forecast error = Forecast - Actual. WAPE = sum|F-A| / sum|A|. Bias = sum(F-A) / sum|A|. Sign category of each (actual, forecast) pair: SAME_SIGN_NONZERO, OPPOSITE_SIGN_NONZERO (both non-zero, different signs), ZERO_INVOLVED (either amount is exactly 0) and MISSING_OR_UNAVAILABLE (empty here by construction). An opposite-sign pair is an observation, not a confirmed accounting error. No sign is flipped anywhere.
A42: 6. Comparison / baseline | B42: Baseline = same-sign lines (WAPE) vs all lines
A43: 7. Driver breakdown and contribution | B43: Section | Opposite-sign lines (share of lines) | Opposite-sign share of abs error | Same-sign share of abs error | Zero-involved share of abs error | WAPE all lines | WAPE same-sign lines only REVENUE | 10.5% | 91.2% | 8.6% | 0.21% | 26.6% | 2.6% COGS | 12.1% | 88.6% | 11.1% | 0.24% | 27.0% | 3.4% PEOPLE | 13.2% | 89.9% | 10.0% | 0.11% | 29.3% | 3.4% OPEX | 13.1% | 89.1% | 10.7% | 0.23% | 27.9% | 3.4%
A44: 8. Validation evidence / Phase 4 reference | B44: Category shares of rows and of error each sum to 1 and error attribution reconciles to total absolute error (C06, C07); the opposite-sign share is recomputed from fact_close (C09) and with the independent pandas category rule (X97); category counts for budget, forecast and prior year are recounted in pandas (X96); WAPE and bias recomputed in pandas (X30-X32). Variance bridge: all lines = same-sign + opposite-sign + zero-involved with difference 0.00 (B08).
A45: 9. Observed fact vs hypothesis | B45: OBSERVED: see field 4. HYPOTHESIS / INTERPRETATION: Observed (arithmetic): on all lines the forecast error is large; restricted to same-sign non-zero lines it is small. Concentration of error: opposite-sign lines (an association in this extract; no cause is established). The same category accounts for the difference between the all-lines and same-sign budget variances: people-cost variance is $0.04M on all lines but $2.29M on same-sign lines (opposite-sign lines contribute -$2.26M); revenue variance moves from -$4.67M to -$7.02M. Among eligible lines, 21.8% are flagged by the Phase 3 sign-pattern rule as a single-column sign flip (24.0% of absolute value) and 10.7% have local and USD amounts of opposite sign (a flag, not proof). Caution: the same-sign WAPE is a sensitivity chosen by the outcome (a line is kept because actual and forecast agree in sign, which mechanically removes the largest errors); it is not a measure of forecast skill. Unresolved (accounting): whether an opposite-sign pair is an error or a legitimate reversal, credit note or contra-account entry depends on the account-level sign convention, which is not verified (R9). Next investigation: take a sample of opposite-sign lines per account and compare them with source documents; ask the ledger owner for the sign convention by account. ALTERNATIVE EXPLANATIONS: (a) Some opposite-sign lines are legitimate credit notes, reversals or reclassifications - not testable without the sign convention (the sign convention is an unresolved Phase 1 rule, R9). (b) If the data were generated synthetically, sign inversions may have been injected independently per column, which would explain why differences appear in exactly one of the amount columns. (c) The forecast may be a late re-forecast (no version or as-of date exists), which changes what the error means.
A46: 10. Confidence level and reasons | B46: High on the arithmetic and on its independent recomputation. Low on the accounting interpretation: no validated sign convention exists. Forecast skill is neither proved nor disproved, because the extract has no forecast version or as-of date.
A47: 11. Data limitations | B47: Standing limits: synthetic extract with unverified provenance; Posted-only status rule (R6) and scale restoration (R7) are provisional; sign convention unresolved (R9); forecast has no version or as-of date.
A48: 12. Recommended action | B48: Do not report forecast accuracy from this extract. Investigate the opposite-sign lines by account against source documents and obtain the account-level sign convention (contra accounts such as 4190, reversal postings, credit notes). Only after the conventions are verified, decide whether a validation rule is needed; do not impose a universal 'actual, budget and forecast must share a sign' rule before then.
... A52: 16. Follow-up KPI / validation step | B52: KPI (monitoring statistic, not a defect rate): share of lines with opposite-sign actual and forecast (currently 10.5% of revenue lines). Monitoring: Each close: count of opposite-sign lines by account (out_b7, out_c2); investigate when a new account appears or the share moves outside the observed range.
A53: Back to ranking
A55: #3 INS-03 - Actuals sit a near-constant 3.6% below budget on revenue and 6.4% above budget on costs on same-sign lines in all 36 months, all 6 entities, all 5 divisions and every one of the 20 operating accounts (the all-lines view differs)
A56: 1. Insight ID and headline | B56: INS-03 - Actuals sit a near-constant 3.6% below budget on revenue and 6.4% above budget on costs on same-sign lines in all 36 months, all 6 entities, all 5 divisions and every one of the 20 operating accounts (the all-lines view differs)
A57: 2. Business question | B57: Where, and in which months, do actuals deviate from budget, and is the deviation concentrated anywhere?
A58: 3. Period and population | B58: Eligible lines with a budget value: 55,043; analysis on lines where actual and budget are both non-zero with the same sign (same-sign view), with the all-lines view (scale-adjusted amounts, signs as recorded) shown beside it.
A59: 4. Quantified financial result (observed fact) | B59: Revenue -$7.02M (-3.6%); COGS $5.30M (+6.4%); people $2.29M (+6.4%); opex $2.50M (+6.4%). The monthly % is on the same side of budget in 36 of 36 months for revenue (below) and 36 of 36 for COGS, 36 of 36 for people and 36 of 36 for opex (above), with a monthly standard deviation of only 0.16, 0.37, 0.53 and 0.33 percentage points (revenue, COGS, people, opex). On all lines (no sign filter) the variances are -2.4%, +5.8%, +0.1% and +4.9%. Same-side check on same-sign lines (revenue below budget, costs above): revenue 36/36 months, 6/6 entities, 5/5 divisions, 4/4 GL accounts; cogs 36/36 months, 6/6 entities, 5/5 divisions, 5/5 GL accounts; people 36/36 months, 6/6 entities, 5/5 divisions, 3/3 GL accounts; opex 36/36 months, 6/6 entities, 5/5 divisions, 8/8 GL accounts. The claim is limited to the four operating sections on same-sign lines; D&A, below-EBITDA and tax are not covered and the all-lines view does not show it.
A60: 5. Formula and metric definition | B60: Variance = Actual - Budget (USD). % = variance / ABS(net budget), published only when |net budget| >= 50% of gross budget (project convention; otherwise NULL). Net and gross shown. Revenue: negative = below budget. Costs are positive magnitudes: positive variance = spend above budget. No favourable/unfavourable label is attached.
A61: 6. Comparison / baseline | B61: Baseline = budget, same-sign lines; all-lines view alongside
A62: 7. Driver breakdown and contribution | B62: Section | Cells (entity x GL, >=100 lines) | Lowest cell % | Highest cell % | SD of cell % (points) | Division range | GL range (all lines of the GL) REVENUE | 18 | -3.6% | -3.3% | 0.08 | -3.6% to -3.5% | -3.5% to -2.5% COGS | 6 | +6.3% | +6.6% | 0.09 | +6.2% to +6.6% | +5.8% to +6.5% PEOPLE | 18 | +5.9% | +6.7% | 0.21 | +6.2% to +6.8% | +6.4% to +6.4% OPEX | 48 | +5.9% | +7.1% | 0.27 | +6.3% to +6.8% | +6.2% to +6.6%
A63: 8. Validation evidence / Phase 4 reference | B63: Variance recomputed per section in pandas (X20/X21) and in SQL (B01-B05); entity x GL, division and month tables each reconcile to the section totals (B09-B11); net-budget guard checked (B13); the top-10 cells overlap 8 of 10 between the all-lines and same-sign views (row_number with a tie-break gives exactly ten cells).
A64: 9. Observed fact vs hypothesis | B64: OBSERVED: see field 4. HYPOTHESIS / INTERPRETATION: A real operating deviation would differ by entity, product or month. This one does not: the cells sit within about one percentage point of the same figure per section (the discount account 4190 is the only visible exception, see the GL range) and the pattern repeats in all 36 months. That is what a top-down percentage adjustment of the budget (or a budget derived from actuals by a fixed factor) produces. It is an observation about the pattern, not a finding about operations. ALTERNATIVE EXPLANATIONS: (a) Synthetic data: budget is generated as actual x a section factor. (b) Budgets were genuinely set top-down, e.g. +3.7% revenue ambition and -6% cost reduction targets applied uniformly. (c) Budget was re-based on actuals after the fact. The file cannot separate these.
A65: 10. Confidence level and reasons | B65: High on the numbers; Medium-Low on any business reading. Limitation: the same-sign filter removes 11% to 13% of the lines of a section (opposite-sign and zero-involved lines); the budget field has no version or approval date.
A66: 11. Data limitations | B66: the same-sign filter removes 11% to 13% of the lines of a section (opposite-sign and zero-involved lines); the budget field has no version or approval date. Standing limits: synthetic extract with unverified provenance; Posted-only status rule (R6) and scale restoration (R7) are provisional; sign convention unresolved (R9); forecast has no version or as-of date.
A67: 12. Recommended action | B67: Do not assign variance to entities or accounts from this pattern: there is nothing to rank. Ask the budget owner how the budget was built (top-down factor or bottom-up) and its version history. If it was top-down, the useful action is a driver-based re-forecast of revenue and cost for the entities with the largest absolute exposure, listed in the driver table.
... A71: 16. Follow-up KPI / validation step | B71: KPI : dispersion (SD) of variance % across entity x GL cells - a value near zero flags a mechanical budget. Monitoring: Quarterly: recompute out_b2 and out_b5; investigate when the cell dispersion rises (a real operating difference emerging) or the monthly % crosses sides.
A72: Back to ranking
A74: #4 INS-04 - Gross profit is $12.3M below budget on same-sign lines: 57% of the gap is revenue below budget and 43% is COGS above budget; the margin gap holds under all three discount treatments
A75: 1. Insight ID and headline | B75: INS-04 - Gross profit is $12.3M below budget on same-sign lines: 57% of the gap is revenue below budget and 43% is COGS above budget; the margin gap holds under all three discount treatments
A76: 2. Business question | B76: How far is gross profit from budget and which side explains it?
A77: 3. Period and population | B77: Eligible lines with a budget where actual and budget are both non-zero with the same sign, revenue + COGS sections only (GL 4100-4190, 5100-5300). Revenue and COGS variances are each measured on their own section's same-sign lines (different line sets), so the gap is the published revenue variance minus the published COGS variance (reconciled to 0.00), not a like-for-like match of individual lines.
A78: 4. Quantified financial result (observed fact) | B78: GP variance -$12.32M (S1), -$12.61M (S2), -$12.26M (S3). Actual margin 53.9% vs budget 58.2% (S1); S2 51.0% vs 55.8%; S3 54.5% vs 58.7%. Revenue explains 57% of the S1 gap (-$7.02M), COGS 43% ($5.30M).
A79: 5. Formula and metric definition | B79: Gross profit = revenue - COGS. The discount account 4190 is negative on 58% of its eligible lines, so three treatments are shown: S1 signed as recorded, S2 discount at absolute value, S3 excluding discounts. Margin % = GP / revenue.
A80: 6. Comparison / baseline | B80: Baseline = budget gross profit under each of the three treatments
A81: 7. Driver breakdown and contribution | B81: Treatment | Actual margin | Budget margin | Margin gap (points) | GP variance | Revenue variance | COGS variance GP_S1_SIGNED_AS_RECORDED | 53.9% | 58.2% | -4.3 | -$12.32M | -$7.02M | $5.30M GP_S2_DISCOUNT_ABS | 51.0% | 55.8% | -4.8 | -$12.61M | -$7.31M | $5.30M GP_S3_EXCL_DISCOUNT | 54.5% | 58.7% | -4.2 | -$12.26M | -$6.96M | $5.30M
A82: 8. Validation evidence / Phase 4 reference | B82: Bridge GP variance = revenue variance - COGS variance closes to 0.00 for all treatments (E01); GP recomputed from the CSV in pandas for S1, S2 and S3 (X50-X52); account classification of 4100/4110/4120/4190 verified (E06).
A83: 9. Observed fact vs hypothesis | B83: OBSERVED: see field 4. HYPOTHESIS / INTERPRETATION: The margin level depends on the row set: all lines give 54.2%, rows with sign_flag ALL_NON_NEGATIVE (no available amount negative; not a sign-consistent population) give 51.0% (S1, actuals only). The gap to budget is measured on same-sign lines, where it stays between -4.8 and -4.2 points across the discount treatments. Because the revenue gap and the cost gap are each uniform (INS-03), the margin gap looks like a plan-calibration effect on both sides rather than a mix or price effect. ALTERNATIVE EXPLANATIONS: Price/volume/mix cannot be separated: the materials unit value equals the sales unit value for every product family (rejected finding R2 in the analysis report), so product-level unit economics are not usable. COGS sign mixing (5120 purchase price variance, mixed signs) could shift the COGS side.
A84: 10. Confidence level and reasons | B84: Medium. Level of margin: low (row-set dependent). Direction and size of the gap: medium-high.
A85: 11. Data limitations | B85: Standing limits: synthetic extract with unverified provenance; Posted-only status rule (R6) and scale restoration (R7) are provisional; sign convention unresolved (R9); forecast has no version or as-of date.
A86: 12. Recommended action | B86: Report gross margin only as a range with its treatment named. Ask the revenue accounting owner for the sign convention of 4190 and 5120. Re-base the GM% budget once the plan method is confirmed (INS-03).
... A90: 16. Follow-up KPI / validation step | B90: KPI : gross margin % vs budget with the treatment label. Monitoring: Monthly: out_e3 (treatments side by side). Flag when treatments disagree on the sign of the gap.
A91: Back to ranking
A93: #5 INS-05 - On a matched same-sign subset the forecast is closer to actuals than the budget; on all comparable lines the margin is 26.8% vs 29.3% revenue WAPE (forecast vs budget) and reverses for people costs, and neither view establishes forecast skill
A94: 1. Insight ID and headline | B94: INS-05 - On a matched same-sign subset the forecast is closer to actuals than the budget; on all comparable lines the margin is 26.8% vs 29.3% revenue WAPE (forecast vs budget) and reverses for people costs, and neither view establishes forecast skill
A95: 2. Business question | B95: Is the forecast more reliable than the budget on comparable populations, and is its error random or systematic?
A96: 3. Period and population | B96: Two populations, never mixed. (A) Matched same-sign subset: lines where actual, budget and forecast are all non-zero with the same sign (24,372 revenue lines) - chosen by outcome, so it removes the largest errors. (B) Comparable all-lines population: every eligible line with actual, budget and forecast present, any sign (29,131 revenue lines). The all-lines forecast population used in INS-02 (30,879 revenue lines) is larger because it does not require a budget.
A97: 4. Quantified financial result (observed fact) | B97: (A) Matched subset, revenue WAPE: forecast 2.6% vs budget 3.7% on 24,372 lines; COGS 3.4% vs 6.0%; people 3.3% vs 6.1%; opex 3.5% vs 6.1%. (B) Comparable all-lines population (any sign), WAPE forecast vs budget: revenue 26.8% vs 29.3% (29,131 lines); COGS 27.0% vs 29.2%; people 29.9% vs 29.0%; opex 28.0% vs 30.2%. Both measures are large on all lines (26.8% to 30.2%) because opposite-sign and zero-involved lines dominate the error; the matched-subset figures (2.6% to 6.1% for the four sections, forecast and budget) are small only because those lines are excluded. The forecast-minus-budget WAPE gap is -2.5 points for revenue, -2.2 COGS, +0.8 people and -2.2 opex (negative = forecast closer), so the ordering is not the same in every section. Revenue forecast is above actual in 12 of 12 quarters (bias +1.6%); COGS, people and opex are below actual in 12, 12 and 12 of 12 quarters (bias -2.5%, -2.5%, -2.5%). Result proxy on lines where actual, budget and forecast are all non-zero with the same sign over 3 years: actual $23.34M, forecast $30.80M, budget $38.35M.
A98: 5. Formula and metric definition | B98: WAPE and bias as defined in INS-02. Bias > 0 = forecast above actual. Quarterly bias per section (12 quarters).
A99: 6. Comparison / baseline | B99: Baseline = budget WAPE on the same matched lines
A100: 7. Driver breakdown and contribution | B100: Year | Revenue (base) | Actual result | Forecast result | Budget result 2023 | $50.56M | $4.88M | $7.19M | $9.49M 2024 | $59.34M | $10.73M | $13.27M | $15.89M 2025 | $58.65M | $7.73M | $10.33M | $12.97M 3 years | $168.55M | $23.34M | $30.80M | $38.35M
A101: 8. Validation evidence / Phase 4 reference | B101: Per-quarter bias persistence from out_c5, recomputed WAPE/bias in pandas (X30-X32); forecast and budget compared on the same lines (C6).
A102: 9. Observed fact vs hypothesis | B102: OBSERVED: see field 4. HYPOTHESIS / INTERPRETATION: On the matched same-sign subset the forecast sits about halfway between budget and actual, with revenue above and costs below actual in every quarter, so its result proxy is about 32% above actual over 3 years (arithmetic on that subset; no favourable/unfavourable label is attached). The sample shows a directional difference between forecast and actual, and it appears on a subset selected by outcome. Whether that is a stable forecasting bias, a late re-forecast, or an artefact of how the extract was built cannot be established here: the extract has no forecast version or as-of date, so true forecast performance and any appropriate correction can only be determined with dated forecast snapshots and a back-test. ALTERNATIVE EXPLANATIONS: No forecast version or date exists in the extract: the 'forecast' may be a late re-forecast that already knew part of the actuals, which would flatter its accuracy. The triple same-sign filter removes a large share of lines and selects lines by outcome.
A103: 10. Confidence level and reasons | B103: Medium for the arithmetic of each population; Low for any statement that the forecast is better than the budget in general: the populations give different margins, and the lack of version/timing prevents any conclusion about forecasting skill.
A104: 11. Data limitations | B104: Standing limits: synthetic extract with unverified provenance; Posted-only status rule (R6) and scale restoration (R7) are provisional; sign convention unresolved (R9); forecast has no version or as-of date.
A105: 12. Recommended action | B105: Obtain dated forecast snapshots (version and as-of date for each forecast). Only then back-test, on forecasts made before each period closed, whether the directional difference persists (observed in this sample: revenue +1.6%, COGS -2.5% of actual) and what adjustment, if any, would have improved WAPE. No correction is proposed from this extract.
... A109: 16. Follow-up KPI / validation step | B109: KPI : quarterly forecast bias by section (target not set here; baseline = values above). Monitoring: Once dated forecast snapshots exist: each quarter, publish forecast difference and WAPE on the same same-sign basis; flag two consecutive quarters on the same side.
A110: Back to ranking
A112: #6 INS-06 - Salary lines carry a near-constant rate per FTE within each entity; without a budgeted FTE plan and the budget's rate method, the people-cost variance cannot be split into rate and volume
A113: 1. Insight ID and headline | B113: INS-06 - Salary lines carry a near-constant rate per FTE within each entity; without a budgeted FTE plan and the budget's rate method, the people-cost variance cannot be split into rate and volume
A114: 2. Business question | B114: Can the people-cost variance be attributed to pay rate or to headcount volume?
A115: 3. Period and population | B115: Eligible salary lines (GL 6100) with a positive FTE value: 993 lines.
A116: 4. Quantified financial result (observed fact) | B116: Observed: 98.4% of lines are within 0.5% of the entity's median rate (lowest entity-year share 90.6%); the rates are AE01 4,800, DE01 6,400, GB01 6,100, IN01 2,200, SG01 5,200, US01 7,800 USD per FTE-month. Conditional scenario (assumes the budget used the same rate and the FTE field is complete): the same-sign salary variance would equal AE01 33, DE01 46, GB01 27, IN01 170, SG01 48, US01 49 excess FTE-months over 36 months, i.e. IN01 about 4.7 FTEs per month above plan.
A117: 5. Formula and metric definition | B117: Salary per FTE = |USD amount| / headcount_fte; share of lines within 0.5% of the entity median rate. Conditional scenario (explicit assumptions below): implied excess FTE-months = salary variance / entity rate.
A118: 6. Comparison / baseline | B118: Baseline = entity median salary rate per FTE-month
A119: 7. Driver breakdown and contribution | B119: Entity | Rate per FTE-month (USD) | Actual | Budget | Variance | Conditional: implied excess FTE-months | Conditional: average excess FTEs AE01 | 4,800 | $2.69M | $2.54M | $0.16M | 33 | 0.9 DE01 | 6,400 | $4.76M | $4.46M | $0.30M | 46 | 1.3 GB01 | 6,100 | $3.00M | $2.83M | $0.17M | 27 | 0.8 IN01 | 2,200 | $6.02M | $5.65M | $0.37M | 170 | 4.7 SG01 | 5,200 | $4.32M | $4.07M | $0.25M | 48 | 1.3 US01 | 7,800 | $6.33M | $5.94M | $0.38M | 49 | 1.4
A120: 8. Validation evidence / Phase 4 reference | B120: Median salary per FTE recomputed in pandas for IN01 2024 (X62); variance reconciles through entity x GL (B10). The FTE-month figures are arithmetic given the stated assumptions; they are not validated against any workforce plan.
A121: 9. Observed fact vs hypothesis | B121: OBSERVED: see field 4. HYPOTHESIS / INTERPRETATION: Observed fact: 98.4% of actual salary lines sit within 0.5% of the entity's median rate (lowest entity-year share 90.6%), which looks like an allocation or standard cost rather than observed payroll (hypothesis, not established). Neither a pay-rate effect nor a headcount effect is established or excluded by this extract. Hypothesis (not established): if the budget was built on the same rate, the variance would be a volume (headcount) effect. Rate versus volume cannot be separated without the budgeted FTE plan and the budget-rate method; a different budget rate would produce a rate variance. The same 6.4% overrun in each entity (INS-03) means this is not an IN01 problem: IN01 stands out in FTE terms only because its rate is the lowest. ALTERNATIVE EXPLANATIONS: The budget may be built on a different rate or a different headcount; the FTE field is populated on 93% of the eligible salary lines; headcount_fte is an attribute of the journal line, not a payroll record.
A122: 10. Confidence level and reasons | B122: Medium for the rate pattern (data property); Low for the FTE-month figures (conditional on the stated assumptions).
A123: 11. Data limitations | B123: Standing limits: synthetic extract with unverified provenance; Posted-only status rule (R6) and scale restoration (R7) are provisional; sign convention unresolved (R9); forecast has no version or as-of date.
...

Sheet Data Quality
A1: Data quality, exclusions and exceptions | I1: Back to Start Here
A2: Counts of lines unless stated; USD amounts are absolute as-reported or adjusted as labelled. Sources: out_i1-i10, out_a0, out_a5, out_a6, out_a7, out_a8, out_h1-h6.
A3: All figures are provisional (Posted-only, scale-adjusted). Flags are exposures, not corrections: flagged lines are retained in the populations (nothing is removed, flipped or repaired). The exposure tables show how many lines and how much absolute value each issue touches so the owner can prioritise. Balance-sheet lines are records of posted lines, NOT period-end balances, and no balance-sheet ratio is calculated.
A5: Q1. Where did all 152,682 source rows go? Primary exclusion reason (out_i9)
A6: Each source row has exactly one primary reason or is eligible (fixed precedence, rule R14). The total must equal the source row count.
A7: Primary reason | B7: Rows (count) | C7: Share of all rows | D7: Absolute as-reported USD
A8: 1_NON_POSTING_ROW | B8: 350 | C8: =B8/SUM($B$8:$B$15) -> 0.0022923462 | D8: 32701018
A9: 2_JUNK_ENTITY | B9: 204 | C9: =B9/SUM($B$8:$B$15) -> 0.0013361103
A10: 3_ENTITY_UNRESOLVABLE | B10: 16 | C10: =B10/SUM($B$8:$B$15) -> 0.00010479297
A11: 4_OUT_OF_SCOPE_STATEMENT | B11: 7125 | C11: =B11/SUM($B$8:$B$15) -> 0.046665619 | D11: 1.8216024e+09
A12: 5_STATUS_NOT_ELIGIBLE | B12: 82986 | C12: =B12/SUM($B$8:$B$15) -> 0.54352183 | D12: 6.5122806e+08
A13: 7_AMOUNT_MISSING | B13: 3637 | C13: =B13/SUM($B$8:$B$15) -> 0.023820752
A14: 8_SCALE_UNDECIDABLE | B14: 24 | C14: =B14/SUM($B$8:$B$15) -> 0.00015718945 | D14: 2369.3083
A15: ELIGIBLE | B15: 58340 | C15: =B15/SUM($B$8:$B$15) -> 0.38210136 | D15: 4.8478505e+08
A16: Total source rows | B16: =SUM($B$8:$B$15) -> 152682
A19: Q2. Exposure of the eligible P&L population to each data-quality flag (out_i8)
A20: Flags overlap, so rows must not be added across lines. Shares are of eligible rows and eligible absolute activity.
A21: Flag | B21: Eligible rows flagged (count) | C21: Absolute actual flagged (USD) | D21: Share of eligible rows | E21: Share of eligible absolute activity
A22: fx_zero: FX rate = 0 | B22: 952 | C22: 8170230.3 | D22: 0.016318135 | E22: 0.016164451
A23: fx_missing: FX rate missing | B23: 3004 | C23: 24654079 | D23: 0.051491258 | E23: 0.04877704
A24: usd_row_local_neq_usd: USD-currency row where local differs from USD | B24: 8622 | C24: 1.2089224e+08 | D24: 0.14778882 | E24: 0.23918011
A25: fx_usd_rate_not_one: USD-currency row with rate outside 1.000 +/- 0.001 | B25: 8623 | C25: 1.2003698e+08 | D25: 0.14780597 | E25: 0.23748802
A26: local_usd_sign_conflict | B26: 6249 | C26: 60688262 | D26: 0.10711347 | E26: 0.12006913
A27: sign_single_column_flip | B27: 12735 | C27: 1.2141833e+08 | D27: 0.21828934 | E27: 0.24022098
A28: sign_all_negative | B28: 7889 | C28: 25991476 | D28: 0.13522455 | E28: 0.051423022
A29: scale_restored | B29: 2374 | C29: 20675658 | D29: 0.040692492 | E29: 0.040905905
A30: scale_label_contradicted | B30: 1087 | C30: 8918763.8 | D30: 0.018632156 | E30: 0.017645392
A31: magnitude_outlier | B31: 91 | C31: 4303.0018 | D31: 0.0015598217 | E31: 8.5133048e-06
A32: dup_candidate_partial_agreement (flag_dup_candidate; tier CANDIDATE_COPY_PARTIAL_AGREEMENT) | B32: 0 | D32: 0
A33: dup_tier_field_match (same-sign or sign-conflict candidate copies) | B33: 598 | C33: 4785990.4 | D33: 0.010250257 | E33: 0.0094688772
A34: cost_center_missing | B34: 2664 | C34: 22806357 | D34: 0.045663353 | E34: 0.0451214
A37: Q3. Reliability of descriptive fields (out_a5): fill rate by section
A38: Verdict is the Phase 4 assessment. Quantity, customer segment and channel are populated on too few revenue lines to support price-volume-mix analysis.
A39: Field | B39: Section | C39: Eligible rows (count) | D39: Populated (count) | E39: Fill rate | F39: Distinct values (count) | G39: Phase 4 verdict
A40: channel | B40: BELOW_EBITDA | C40: 697 | D40: 26 | E40: =IF(C40>0,D40/C40,"n/a") -> 0.037302726 | F40: 2 | G40: UNSUITABLE
A41: channel | B41: COGS | C41: 12198 | D41: 10717 | E41: =IF(C41>0,D41/C41,"n/a") -> 0.87858665 | F41: 2 | G41: USABLE WITH BLANK BUCKET
A42: channel | B42: D&A | C42: 345 | D42: 12 | E42: =IF(C42>0,D42/C42,"n/a") -> 0.034782609 | F42: 2 | G42: UNSUITABLE
A43: channel | B43: OPEX | C43: 8645 | D43: 320 | E43: =IF(C43>0,D43/C43,"n/a") -> 0.037015616 | F43: 2 | G43: UNSUITABLE
A44: channel | B44: PEOPLE | C44: 3285 | D44: 118 | E44: =IF(C44>0,D44/C44,"n/a") -> 0.035920852 | F44: 2 | G44: UNSUITABLE
A45: channel | B45: REVENUE | C45: 32813 | D45: 32063 | E45: =IF(C45>0,D45/C45,"n/a") -> 0.97714321 | F45: 2 | G45: USABLE WITH BLANK BUCKET
A46: channel | B46: TAX | C46: 357 | D46: 15 | E46: =IF(C46>0,D46/C46,"n/a") -> 0.042016807 | F46: 2 | G46: UNSUITABLE
A47: cost_center_code | B47: BELOW_EBITDA | C47: 697 | D47: 667 | E47: =IF(C47>0,D47/C47,"n/a") -> 0.95695839 | F47: 1 | G47: USABLE WITH BLANK BUCKET
A48: cost_center_code | B48: COGS | C48: 12198 | D48: 11648 | E48: =IF(C48>0,D48/C48,"n/a") -> 0.95491064 | F48: 3 | G48: USABLE WITH BLANK BUCKET
A49: cost_center_code | B49: D&A | C49: 345 | D49: 328 | E49: =IF(C49>0,D49/C49,"n/a") -> 0.95072464 | F49: 2 | G49: USABLE WITH BLANK BUCKET
A50: cost_center_code | B50: OPEX | C50: 8645 | D50: 8202 | E50: =IF(C50>0,D50/C50,"n/a") -> 0.94875651 | F50: 6 | G50: USABLE WITH BLANK BUCKET
A51: cost_center_code | B51: PEOPLE | C51: 3285 | D51: 3130 | E51: =IF(C51>0,D51/C51,"n/a") -> 0.95281583 | F51: 5 | G51: USABLE WITH BLANK BUCKET
... A95: uom | B95: TAX | C95: 357 | D95: 10 | E95: =IF(C95>0,D95/C95,"n/a") -> 0.028011204 | F95: 3 | G95: UNSUITABLE
A97: Legend: green = RELIABLE fill; red = UNSUITABLE. ("UNRELIABLE" and "PARTIAL" are unshaded.) Verdict text is copied from Phase 4.
A100: Q4. How much does each unresolved rule move the headline? (out_i1, out_i2)
A101: Each factor is varied alone, others at baseline. Result proxy = revenue - COGS - People - Opex. BASELINE rows are the workbook's numbers; the swing is a range of plausible policies, not an error estimate. Status-partition rows are diagnostics, not policies.
A102: Factor | B102: Scenario | C102: Class | D102: Rows (count) | E102: Revenue (USD) | F102: Cost: COGS+People+Opex (USD) | G102: Result proxy (USD) | H102: Revenue vs baseline (%) | I102: Result proxy vs baseline (%)
A103: duplicates | B103: CANDIDATES_RETAINED (baseline) | C103: BASELINE | D103: 58340 | E103: 2.02649e+08 | F103: 1.7632976e+08 | G103: =E103-F103 -> 26319246 | H103: =E103/$E$119-1 -> 0 | I103: =G103/$G$119-1 -> 0
A104: duplicates | B104: EXCLUDE_ALL_COPY_CANDIDATES | C104: POLICY_SCENARIO | D104: 57742 | E104: 2.0101675e+08 | F104: 1.7453965e+08 | G104: =E104-F104 -> 26477100 | H104: =E104/$E$119-1 -> -0.0080545802 | I104: =G104/$G$119-1 -> 0.0059976689
A105: duplicates | B105: EXCLUDE_SAME_SIGN_CANDIDATES | C105: POLICY_SCENARIO | D105: 57977 | E105: 2.0155926e+08 | F105: 1.7540414e+08 | G105: =E105-F105 -> 26155113 | H105: =E105/$E$119-1 -> -0.0053774984 | I105: =G105/$G$119-1 -> -0.006236226
A106: scale | B106: ADJUSTED_ALL (baseline) | C106: BASELINE | D106: 58340 | E106: 2.02649e+08 | F106: 1.7632976e+08 | G106: =E106-F106 -> 26319246 | H106: =E106/$E$119-1 -> 0 | I106: =G106/$G$119-1 -> 0
A107: scale | B107: AS_REPORTED_PARSED (no restoration) | C107: POLICY_SCENARIO | D107: 58340 | E107: 1.9440178e+08 | F107: 1.688958e+08 | G107: =E107-F107 -> 25505982 | H107: =E107/$E$119-1 -> -0.04069709 | I107: =G107/$G$119-1 -> -0.030899988
A108: scale | B108: EXCLUDE_ALL_RESTORED_ROWS | C108: POLICY_SCENARIO | D108: 55966 | E108: 1.9439555e+08 | F108: 1.6888988e+08 | G108: =E108-F108 -> 25505662 | H108: =E108/$E$119-1 -> -0.040727843 | I108: =G108/$G$119-1 -> -0.030912143
A109: scale | B109: EXCLUDE_MEDIUM_CONFIDENCE_RESTORED | C109: POLICY_SCENARIO | D109: 56746 | E109: 2.0087807e+08 | F109: 1.7143367e+08 | G109: =E109-F109 -> 29444396 | H109: =E109/$E$119-1 -> -0.0087389283 | I109: =G109/$G$119-1 -> 0.11874011
A110: scale | B110: RESTORE_HIGH_CONFIDENCE_ONLY | C110: POLICY_SCENARIO | D110: 58340 | E110: 2.0087952e+08 | F110: 1.7143754e+08 | G110: =E110-F110 -> 29441984 | H110: =E110/$E$119-1 -> -0.008731739 | I110: =G110/$G$119-1 -> 0.11864845
A111: sign | B111: ALL_NON_NEGATIVE_ROWS_ONLY | C111: POLICY_SCENARIO | D111: 35520 | E111: 1.7190404e+08 | F111: 1.6028062e+08 | G111: =E111-F111 -> 11623423 | H111: =E111/$E$119-1 -> -0.15171533 | I111: =G111/$G$119-1 -> -0.55836795
A112: sign | B112: ALL_ROWS_SIGNS_AS_RECORDED (baseline) | C112: BASELINE | D112: 58340 | E112: 2.02649e+08 | F112: 1.7632976e+08 | G112: =E112-F112 -> 26319246 | H112: =E112/$E$119-1 -> 0 | I112: =G112/$G$119-1 -> 0
A113: sign | B113: EXCLUDE_SINGLE_COLUMN_SIGN_FLIPS | C113: POLICY_SCENARIO | D113: 45605 | E113: 1.6426882e+08 | F113: 1.4432502e+08 | G113: =E113-F113 -> 19943796 | H113: =E113/$E$119-1 -> -0.18939243 | I113: =G113/$G$119-1 -> -0.24223527
A114: status | B114: ALL_EXCEPT_REJECTED | C114: POLICY_SCENARIO | D114: 116863 | E114: 4.0438441e+08 | F114: 3.5522774e+08 | G114: =E114-F114 -> 49156670 | H114: =E114/$E$119-1 -> 0.99549176 | I114: =G114/$G$119-1 -> 0.86770814
... A120: status | B120: REJECTED_ONLY | C120: STATUS_PARTITION_DIAGNOSTIC | D120: 19467 | E120: 67193100 | F120: 62468586 | G120: =E120-F120 -> 4724513.9 | H120: =E120/$E$119-1 -> -0.6684262 | I120: =G120/$G$119-1 -> -0.82049205
A123: Factor (ranked by revenue swing) | B123: Scenarios (count) | C123: Min revenue (USD) | D123: Max revenue (USD) | E123: Revenue range % of baseline | F123: Min result proxy (USD) | G123: Max result proxy (USD) | H123: Result range % of baseline
A124: status | B124: 3 | C124: 2.02649e+08 | D124: 4.7157751e+08 | E124: 1.3270656 | F124: 26319246 | G124: 53881184 | H124: 1.0472161
A125: sign | B125: 3 | C125: 1.6426882e+08 | D125: 2.02649e+08 | E125: 0.18939243 | F125: 11623423 | G125: 26319246 | H125: 0.55836795
A126: scale | B126: 5 | C126: 1.9439555e+08 | D126: 2.02649e+08 | E126: 0.040727843 | F126: 25505662 | G126: 29444396 | H126: 0.14965225
A127: duplicates | B127: 3 | C127: 2.0101675e+08 | D127: 2.02649e+08 | E127: 0.0080545802 | F127: 26155113 | G127: 26477100 | H127: 0.012233895
A138: Q5. Scale restoration (rule R7): lines whose amounts were divided by 1,000 / 100,000 (out_i5, out_i4)
A139: Restoration is a provisional rule. HIGH/MEDIUM confidence tiers show how much of each section's absolute activity depends on it; 'undetermined' rows are left as reported.
A140: Section | B140: Confidence | C140: Decision | D140: Rows (count) | E140: Absolute adjusted (USD) | F140: Absolute as reported (USD) | G140: Share of section absolute activity
A141: Revenue | B141: HIGH | C141: DIVIDED_1E3 | D141: 319 | E141: 5300241.7 | F141: 5300.2417 | G141: 0.020823599
A142: Revenue | B142: HIGH | C142: DIVIDED_1E5 | D142: 58 | E142: 1834580 | F142: 18.3458 | G142: 0.007207701
A143: Revenue | B143: MEDIUM | C143: DIVIDED_1E5 | D143: 139 | E143: 467470 | F143: 4.6747 | G143: 0.0018365969
A144: Revenue | B144: MEDIUM | C144: DIVIDED_1E3 | D144: 801 | E144: 2271156.7 | F144: 2271.1567 | G144: 0.0089229243
A145: COGS | B145: HIGH | C145: DIVIDED_1E3 | D145: 356 | E145: 3092617.2 | F145: 3092.6172 | G145: 0.024161189
A146: COGS | B146: HIGH | C146: DIVIDED_1E5 | D146: 47 | E146: 604130 | F146: 6.0413 | G146: 0.0047197884
A147: COGS | B147: MEDIUM | C147: DIVIDED_1E3 | D147: 84 | E147: 1267603.9 | F147: 1267.6039 | G147: 0.0099032033
A148: COGS | B148: MEDIUM | C148: DIVIDED_1E5 | D148: 29 | E148: 473000 | F148: 4.73 | G148: 0.0036953304
A149: People costs | B149: MEDIUM | C149: DIVIDED_1E3 | D149: 125 | E149: 2314582.9 | F149: 2314.5829 | G149: 0.042165786
A150: People costs | B150: MEDIUM | C150: DIVIDED_1E5 | D150: 23 | E150: 397000 | F150: 3.97 | G150: 0.0072323256
A151: Operating expenses | B151: MEDIUM | C151: DIVIDED_1E5 | D151: 49 | E151: 479000 | F151: 4.79 | G151: 0.0078888356
A152: Operating expenses | B152: MEDIUM | C152: DIVIDED_1E3 | D152: 282 | E152: 1827316.9 | F152: 1827.3169 | G152: 0.030094786
... A158: Tax | B158: MEDIUM | C158: DIVIDED_1E5 | D158: 3 | E158: 41000 | F158: 0.41 | G158: 0.010826832
A160: Undetermined-scale rows by section | B160: Rows undetermined (count) | C160: Of which Posted (count) | D160: Absolute as reported (USD) | E160: If x1,000 (USD) | F160: If x100,000 (USD)
A161: BALANCE_SHEET | B161: 1 | C161: 1 | D161: 18633.51 | E161: 18633510 | F161: 1863351000
A162: BELOW_EBITDA | B162: 2 | C162: 0 | D162: 0 | E162: 0 | F162: 0
A163: COGS | B163: 6 | C163: 2 | D163: 1954.1985 | E163: 1954198.5 | F163: 195419850
A164: OPEX | B164: 4 | C164: 2 | D164: 1298.37 | E164: 1298370 | F164: 129837000
A165: REVENUE | B165: 60 | C165: 23 | D165: 599.3498 | E165: 599349.8 | F165: 59934980
A169: Q6. Duplicate-candidate exposure (out_i6, out_i7)
A170: document_no is not a unique key (R5). No two rows are identical in all source fields, so no line is removed. 'Field match' tiers are candidates only: they may be legitimate repeated postings.
A171: Duplicate tier | B171: Eligible rows (count) | C171: Absolute actual (USD) | D171: Share of eligible rows | E171: Share of eligible absolute
A172: UNIQUE_DOCUMENT_NO | B172: 55420 | C172: 4.8074015e+08 | D172: 0.94994858 | E172: 0.9511238
A173: GROUP_ANCHOR | B173: 2322 | C173: 19918207 | D173: 0.039801166 | E173: 0.039407319
A174: DUP_CANDIDATE_FIELD_MATCH_SAME_SIGN | B174: 363 | C174: 2607683.3 | D174: 0.006222146 | E174: 0.0051591897
A175: DUP_CANDIDATE_FIELD_MATCH_SIGN_CONFLICT | B175: 235 | C175: 2178307.1 | D175: 0.0040281111 | E175: 0.0043096874
A177: Exact-match test | B177: Groups with matches (count) | C177: Rows in matches (count)
A178: identical in all 42 source fields (row_id ignored) | B178: 0 | C178: 0
...

Sheet Reconciliation & QA
A1: Reconciliation and QA - every check is a live formula | I1: Back to Start Here
A2: Expected = recomputed independently from the Phase 4 analytical views (v_pl_actual, v_var_scn, v_fc_scn, v_gp_rows) or stated Phase 4 control totals. Workbook = the cell the sheet actually shows (green link). Difference and PASS/FAIL are Excel formulas.
A3: Tolerance: counts exact (0); USD amounts 0.5; percentages 0.000001. A check passes when |Difference| <= tolerance. Tolerances are blue inputs. The Python test suite additionally recalculates this workbook in LibreOffice and compares every cached value; Excel itself was not used to generate or open this file.
A5: Overall status: | B5: =IF(COUNTIF($H$10:$H$146,"FAIL")=0,"ALL "&COUNTA($H$10:$H$146)&" CHECKS PASS",COUNTIF($H$10:$H$146,"FAIL")&" CHECK(S) FAIL") -> ALL 137 CHECKS PASS
A6: Checks: | B6: =COUNTA($H$10:$H$146) -> 137
A7: Pass / Fail: | B7: =COUNTIF($H$10:$H$146,"PASS")&" / "&COUNTIF($H$10:$H$146,"FAIL") -> 137 / 0
A9: ID | B9: Area | C9: Check | D9: Expected (independent source) | E9: Workbook value | F9: Difference | G9: Tolerance | H9: Result
A10: R-01 | B10: Population | C10: Eligible P&L lines: Monthly P&L total vs v_pl_actual | D10: 58340 | E10: ='Monthly P&L'!$N$45 -> 58340 | F10: =ROUND(E10-D10,6) -> 0 | G10: 0 | H10: =IF(ABS(F10)<=G10,"PASS","FAIL") -> PASS
A11: R-02 | B11: Population | C11: All source rows: Data Quality waterfall total vs v_close | D11: 152682 | E11: ='Data Quality'!$B$16 -> 152682 | F11: =ROUND(E11-D11,6) -> 0 | G11: 0 | H11: =IF(ABS(F11)<=G11,"PASS","FAIL") -> PASS
A12: R-03 | B12: Population | C12: Eligible lines: GL activity total vs v_pl_actual | D12: 58340 | E12: ='GL & Cost Drivers'!$D$32 -> 58340 | F12: =ROUND(E12-D12,6) -> 0 | G12: 0 | H12: =IF(ABS(F12)<=G12,"PASS","FAIL") -> PASS
A13: R-03b | B13: Population | C13: Eligible lines: entity table total vs v_pl_actual | D13: 58340 | E13: ='Entity & Division'!$L$14 -> 58340 | F13: =ROUND(E13-D13,6) -> 0 | G13: 0 | H13: =IF(ABS(F13)<=G13,"PASS","FAIL") -> PASS
A14: R-04 | B14: Monthly P&L | C14: Revenue: 36-month total vs v_pl_actual | D14: 2.02649e+08 | E14: ='Monthly P&L'!$C$45 -> 2.02649e+08 | F14: =ROUND(E14-D14,6) -> -2e-06 | G14: 0.5 | H14: =IF(ABS(F14)<=G14,"PASS","FAIL") -> PASS
A15: R-05 | B15: Monthly P&L | C15: COGS: 36-month total vs v_pl_actual | D15: 92808018 | E15: ='Monthly P&L'!$D$45 -> 92808018 | F15: =ROUND(E15-D15,6) -> 0 | G15: 0.5 | H15: =IF(ABS(F15)<=G15,"PASS","FAIL") -> PASS
A16: R-06 | B16: Monthly P&L | C16: People costs: 36-month total vs v_pl_actual | D16: 39708939 | E16: ='Monthly P&L'!$G$45 -> 39708939 | F16: =ROUND(E16-D16,6) -> 0 | G16: 0.5 | H16: =IF(ABS(F16)<=G16,"PASS","FAIL") -> PASS
A17: R-07 | B17: Monthly P&L | C17: Operating expenses: 36-month total vs v_pl_actual | D17: 43812799 | E17: ='Monthly P&L'!$H$45 -> 43812799 | F17: =ROUND(E17-D17,6) -> 0 | G17: 0.5 | H17: =IF(ABS(F17)<=G17,"PASS","FAIL") -> PASS
A18: R-08 | B18: Monthly P&L | C18: D&A (depreciation, GL 6300): 36-month total vs v_pl_actual | D18: 1841552.1 | E18: ='Monthly P&L'!$K$45 -> 1841552.1 | F18: =ROUND(E18-D18,6) -> 0 | G18: 0.5 | H18: =IF(ABS(F18)<=G18,"PASS","FAIL") -> PASS
A19: R-09 | B19: Monthly P&L | C19: Below-EBITDA items: 36-month total vs v_pl_actual | D19: 595918.87 | E19: ='Monthly P&L'!$L$45 -> 595918.87 | F19: =ROUND(E19-D19,6) -> 0 | G19: 0.5 | H19: =IF(ABS(F19)<=G19,"PASS","FAIL") -> PASS
A20: R-10 | B20: Monthly P&L | C20: Tax: 36-month total vs v_pl_actual | D20: 2751000.7 | E20: ='Monthly P&L'!$M$45 -> 2751000.7 | F20: =ROUND(E20-D20,6) -> 0 | G20: 0.5 | H20: =IF(ABS(F20)<=G20,"PASS","FAIL") -> PASS
A21: R-11 | B21: Cross-sheet | C21: Revenue: entity table total = Monthly P&L total | D21: 2.02649e+08 | E21: ='Entity & Division'!$C$14 -> 2.02649e+08 | F21: =ROUND(E21-D21,6) -> -2e-06 | G21: 0.5 | H21: =IF(ABS(F21)<=G21,"PASS","FAIL") -> PASS
A22: R-12 | B22: Cross-sheet | C22: Revenue: division table total = Monthly P&L total | D22: 2.02649e+08 | E22: ='Entity & Division'!$C$25 -> 2.02649e+08 | F22: =ROUND(E22-D22,6) -> -2e-06 | G22: 0.5 | H22: =IF(ABS(F22)<=G22,"PASS","FAIL") -> PASS
A23: R-13-2023 | B23: Monthly P&L | C23: Revenue 2023: calendar-year row vs v_pl_actual | D23: 61295631 | E23: ='Monthly P&L'!$C$51 -> 61295631 | F23: =ROUND(E23-D23,6) -> 0 | G23: 0.5 | H23: =IF(ABS(F23)<=G23,"PASS","FAIL") -> PASS
A24: R-13-2024 | B24: Monthly P&L | C24: Revenue 2024: calendar-year row vs v_pl_actual | D24: 70362584 | E24: ='Monthly P&L'!$C$52 -> 70362584 | F24: =ROUND(E24-D24,6) -> 0 | G24: 0.5 | H24: =IF(ABS(F24)<=G24,"PASS","FAIL") -> PASS
A25: R-13-2025 | B25: Monthly P&L | C25: Revenue 2025: calendar-year row vs v_pl_actual | D25: 70990788 | E25: ='Monthly P&L'!$C$53 -> 70990788 | F25: =ROUND(E25-D25,6) -> 0 | G25: 0.5 | H25: =IF(ABS(F25)<=G25,"PASS","FAIL") -> PASS
A26: R-14-AE01 | B26: Entity | C26: Revenue AE01: entity table vs v_pl_actual | D26: 21148202 | E26: ='Entity & Division'!$C$8 -> 21148202 | F26: =ROUND(E26-D26,6) -> 0 | G26: 0.5 | H26: =IF(ABS(F26)<=G26,"PASS","FAIL") -> PASS
A27: R-14-DE01 | B27: Entity | C27: Revenue DE01: entity table vs v_pl_actual | D27: 29549094 | E27: ='Entity & Division'!$C$9 -> 29549094 | F27: =ROUND(E27-D27,6) -> 0 | G27: 0.5 | H27: =IF(ABS(F27)<=G27,"PASS","FAIL") -> PASS
A28: R-14-GB01 | B28: Entity | C28: Revenue GB01: entity table vs v_pl_actual | D28: 20503977 | E28: ='Entity & Division'!$C$10 -> 20503977 | F28: =ROUND(E28-D28,6) -> 0 | G28: 0.5 | H28: =IF(ABS(F28)<=G28,"PASS","FAIL") -> PASS
A29: R-14-IN01 | B29: Entity | C29: Revenue IN01: entity table vs v_pl_actual | D29: 48348042 | E29: ='Entity & Division'!$C$11 -> 48348042 | F29: =ROUND(E29-D29,6) -> 0 | G29: 0.5 | H29: =IF(ABS(F29)<=G29,"PASS","FAIL") -> PASS
A30: R-14-SG01 | B30: Entity | C30: Revenue SG01: entity table vs v_pl_actual | D30: 27763849 | E30: ='Entity & Division'!$C$12 -> 27763849 | F30: =ROUND(E30-D30,6) -> 0 | G30: 0.5 | H30: =IF(ABS(F30)<=G30,"PASS","FAIL") -> PASS
A31: R-14-US01 | B31: Entity | C31: Revenue US01: entity table vs v_pl_actual | D31: 55335838 | E31: ='Entity & Division'!$C$13 -> 55335838 | F31: =ROUND(E31-D31,6) -> 0 | G31: 0.5 | H31: =IF(ABS(F31)<=G31,"PASS","FAIL") -> PASS
A32: R-15-ss-REVENUE-A | B32: Budget vs Actual | C32: Revenue actual (same-sign) vs v_var_scn | D32: 1.9039672e+08 | E32: ='Budget vs Actual'!$C$10 -> 1.9039672e+08 | F32: =ROUND(E32-D32,6) -> 0 | G32: 0.5 | H32: =IF(ABS(F32)<=G32,"PASS","FAIL") -> PASS
A33: R-15-ss-REVENUE-B | B33: Budget vs Actual | C33: Revenue budget (same-sign) vs v_var_scn | D33: 1.9741975e+08 | E33: ='Budget vs Actual'!$D$10 -> 1.9741975e+08 | F33: =ROUND(E33-D33,6) -> 0 | G33: 0.5 | H33: =IF(ABS(F33)<=G33,"PASS","FAIL") -> PASS
A34: R-15-ss-REVENUE-N | B34: Budget vs Actual | C34: Revenue lines (same-sign) vs v_var_scn | D34: 27537 | E34: ='Budget vs Actual'!$B$10 -> 27537 | F34: =ROUND(E34-D34,6) -> 0 | G34: 0 | H34: =IF(ABS(F34)<=G34,"PASS","FAIL") -> PASS
A35: R-15-al-REVENUE-A | B35: Budget vs Actual | C35: Revenue actual (all lines) vs v_var_scn | D35: 1.9162786e+08 | E35: ='Budget vs Actual'!$C$22 -> 1.9162786e+08 | F35: =ROUND(E35-D35,6) -> -1e-06 | G35: 0.5 | H35: =IF(ABS(F35)<=G35,"PASS","FAIL") -> PASS
A36: R-15-al-REVENUE-B | B36: Budget vs Actual | C36: Revenue budget (all lines) vs v_var_scn | D36: 1.9629377e+08 | E36: ='Budget vs Actual'!$D$22 -> 1.9629377e+08 | F36: =ROUND(E36-D36,6) -> 0 | G36: 0.5 | H36: =IF(ABS(F36)<=G36,"PASS","FAIL") -> PASS
A37: R-15-al-REVENUE-N | B37: Budget vs Actual | C37: Revenue lines (all lines) vs v_var_scn | D37: 30953 | E37: ='Budget vs Actual'!$B$22 -> 30953 | F37: =ROUND(E37-D37,6) -> 0 | G37: 0 | H37: =IF(ABS(F37)<=G37,"PASS","FAIL") -> PASS
A38: R-15-ss-COGS-A | B38: Budget vs Actual | C38: COGS actual (same-sign) vs v_var_scn | D38: 87801326 | E38: ='Budget vs Actual'!$C$11 -> 87801326 | F38: =ROUND(E38-D38,6) -> 0 | G38: 0.5 | H38: =IF(ABS(F38)<=G38,"PASS","FAIL") -> PASS
A39: R-15-ss-COGS-B | B39: Budget vs Actual | C39: COGS budget (same-sign) vs v_var_scn | D39: 82505584 | E39: ='Budget vs Actual'!$D$11 -> 82505584 | F39: =ROUND(E39-D39,6) -> 0 | G39: 0.5 | H39: =IF(ABS(F39)<=G39,"PASS","FAIL") -> PASS
A40: R-15-ss-COGS-N | B40: Budget vs Actual | C40: COGS lines (same-sign) vs v_var_scn | D40: 10142 | E40: ='Budget vs Actual'!$B$11 -> 10142 | F40: =ROUND(E40-D40,6) -> 0 | G40: 0 | H40: =IF(ABS(F40)<=G40,"PASS","FAIL") -> PASS
A41: R-15-al-COGS-A | B41: Budget vs Actual | C41: COGS actual (all lines) vs v_var_scn | D41: 87563589 | E41: ='Budget vs Actual'!$C$23 -> 87563589 | F41: =ROUND(E41-D41,6) -> 0 | G41: 0.5 | H41: =IF(ABS(F41)<=G41,"PASS","FAIL") -> PASS
A42: R-15-al-COGS-B | B42: Budget vs Actual | C42: COGS budget (all lines) vs v_var_scn | D42: 82756590 | E42: ='Budget vs Actual'!$D$23 -> 82756590 | F42: =ROUND(E42-D42,6) -> 0 | G42: 0.5 | H42: =IF(ABS(F42)<=G42,"PASS","FAIL") -> PASS
A43: R-15-al-COGS-N | B43: Budget vs Actual | C43: COGS lines (all lines) vs v_var_scn | D43: 11517 | E43: ='Budget vs Actual'!$B$23 -> 11517 | F43: =ROUND(E43-D43,6) -> 0 | G43: 0 | H43: =IF(ABS(F43)<=G43,"PASS","FAIL") -> PASS
A44: R-15-ss-PEOPLE-A | B44: Budget vs Actual | C44: People costs actual (same-sign) vs v_var_scn | D44: 38264640 | E44: ='Budget vs Actual'!$C$12 -> 38264640 | F44: =ROUND(E44-D44,6) -> 0 | G44: 0.5 | H44: =IF(ABS(F44)<=G44,"PASS","FAIL") -> PASS
A45: R-15-ss-PEOPLE-B | B45: Budget vs Actual | C45: People costs budget (same-sign) vs v_var_scn | D45: 35971790 | E45: ='Budget vs Actual'!$D$12 -> 35971790 | F45: =ROUND(E45-D45,6) -> 0 | G45: 0.5 | H45: =IF(ABS(F45)<=G45,"PASS","FAIL") -> PASS
A46: R-15-ss-PEOPLE-N | B46: Budget vs Actual | C46: People costs lines (same-sign) vs v_var_scn | D46: 2721 | E46: ='Budget vs Actual'!$B$12 -> 2721 | F46: =ROUND(E46-D46,6) -> 0 | G46: 0 | H46: =IF(ABS(F46)<=G46,"PASS","FAIL") -> PASS
A47: R-15-al-PEOPLE-A | B47: Budget vs Actual | C47: People costs actual (all lines) vs v_var_scn | D47: 37123068 | E47: ='Budget vs Actual'!$C$24 -> 37123068 | F47: =ROUND(E47-D47,6) -> 0 | G47: 0.5 | H47: =IF(ABS(F47)<=G47,"PASS","FAIL") -> PASS
A48: R-15-al-PEOPLE-B | B48: Budget vs Actual | C48: People costs budget (all lines) vs v_var_scn | D48: 37083624 | E48: ='Budget vs Actual'!$D$24 -> 37083624 | F48: =ROUND(E48-D48,6) -> 0 | G48: 0.5 | H48: =IF(ABS(F48)<=G48,"PASS","FAIL") -> PASS
A49: R-15-al-PEOPLE-N | B49: Budget vs Actual | C49: People costs lines (all lines) vs v_var_scn | D49: 3101 | E49: ='Budget vs Actual'!$B$24 -> 3101 | F49: =ROUND(E49-D49,6) -> 0 | G49: 0 | H49: =IF(ABS(F49)<=G49,"PASS","FAIL") -> PASS
A50: R-15-ss-OPEX-A | B50: Budget vs Actual | C50: Operating expenses actual (same-sign) vs v_var_scn | D50: 41457348 | E50: ='Budget vs Actual'!$C$13 -> 41457348 | F50: =ROUND(E50-D50,6) -> 0 | G50: 0.5 | H50: =IF(ABS(F50)<=G50,"PASS","FAIL") -> PASS
A51: R-15-ss-OPEX-B | B51: Budget vs Actual | C51: Operating expenses budget (same-sign) vs v_var_scn | D51: 38958919 | E51: ='Budget vs Actual'!$D$13 -> 38958919 | F51: =ROUND(E51-D51,6) -> 0 | G51: 0.5 | H51: =IF(ABS(F51)<=G51,"PASS","FAIL") -> PASS
A52: R-15-ss-OPEX-N | B52: Budget vs Actual | C52: Operating expenses lines (same-sign) vs v_var_scn | D52: 7125 | E52: ='Budget vs Actual'!$B$13 -> 7125 | F52: =ROUND(E52-D52,6) -> 0 | G52: 0 | H52: =IF(ABS(F52)<=G52,"PASS","FAIL") -> PASS
A53: R-15-al-OPEX-A | B53: Budget vs Actual | C53: Operating expenses actual (all lines) vs v_var_scn | D53: 41160730 | E53: ='Budget vs Actual'!$C$25 -> 41160730 | F53: =ROUND(E53-D53,6) -> 0 | G53: 0.5 | H53: =IF(ABS(F53)<=G53,"PASS","FAIL") -> PASS
A54: R-15-al-OPEX-B | B54: Budget vs Actual | C54: Operating expenses budget (all lines) vs v_var_scn | D54: 39236310 | E54: ='Budget vs Actual'!$D$25 -> 39236310 | F54: =ROUND(E54-D54,6) -> 0 | G54: 0.5 | H54: =IF(ABS(F54)<=G54,"PASS","FAIL") -> PASS
A55: R-15-al-OPEX-N | B55: Budget vs Actual | C55: Operating expenses lines (all lines) vs v_var_scn | D55: 8153 | E55: ='Budget vs Actual'!$B$25 -> 8153 | F55: =ROUND(E55-D55,6) -> 0 | G55: 0 | H55: =IF(ABS(F55)<=G55,"PASS","FAIL") -> PASS
A56: R-15-ss-D&A-A | B56: Budget vs Actual | C56: D&A (depreciation, GL 6300) actual (same-sign) vs v_var_scn | D56: 1742110.1 | E56: ='Budget vs Actual'!$C$14 -> 1742110.1 | F56: =ROUND(E56-D56,6) -> 0 | G56: 0.5 | H56: =IF(ABS(F56)<=G56,"PASS","FAIL") -> PASS
A57: R-15-ss-D&A-B | B57: Budget vs Actual | C57: D&A (depreciation, GL 6300) budget (same-sign) vs v_var_scn | D57: 1638237.8 | E57: ='Budget vs Actual'!$D$14 -> 1638237.8 | F57: =ROUND(E57-D57,6) -> 0 | G57: 0.5 | H57: =IF(ABS(F57)<=G57,"PASS","FAIL") -> PASS
A58: R-15-ss-D&A-N | B58: Budget vs Actual | C58: D&A (depreciation, GL 6300) lines (same-sign) vs v_var_scn | D58: 292 | E58: ='Budget vs Actual'!$B$14 -> 292 | F58: =ROUND(E58-D58,6) -> 0 | G58: 0 | H58: =IF(ABS(F58)<=G58,"PASS","FAIL") -> PASS
A59: R-15-al-D&A-A | B59: Budget vs Actual | C59: D&A (depreciation, GL 6300) actual (all lines) vs v_var_scn | D59: 1762454.8 | E59: ='Budget vs Actual'!$C$26 -> 1762454.8 | F59: =ROUND(E59-D59,6) -> 0 | G59: 0.5 | H59: =IF(ABS(F59)<=G59,"PASS","FAIL") -> PASS
A60: R-15-al-D&A-B | B60: Budget vs Actual | C60: D&A (depreciation, GL 6300) budget (all lines) vs v_var_scn | D60: 1621481.1 | E60: ='Budget vs Actual'!$D$26 -> 1621481.1 | F60: =ROUND(E60-D60,6) -> 0 | G60: 0.5 | H60: =IF(ABS(F60)<=G60,"PASS","FAIL") -> PASS
A61: R-15-al-D&A-N | B61: Budget vs Actual | C61: D&A (depreciation, GL 6300) lines (all lines) vs v_var_scn | D61: 325 | E61: ='Budget vs Actual'!$B$26 -> 325 | F61: =ROUND(E61-D61,6) -> 0 | G61: 0 | H61: =IF(ABS(F61)<=G61,"PASS","FAIL") -> PASS
A62: R-15-ss-BELOW_EBITDA-A | B62: Budget vs Actual | C62: Below-EBITDA items actual (same-sign) vs v_var_scn | D62: 525074.46 | E62: ='Budget vs Actual'!$C$15 -> 525074.46 | F62: =ROUND(E62-D62,6) -> 0 | G62: 0.5 | H62: =IF(ABS(F62)<=G62,"PASS","FAIL") -> PASS
A63: R-15-ss-BELOW_EBITDA-B | B63: Budget vs Actual | C63: Below-EBITDA items budget (same-sign) vs v_var_scn | D63: 493909.02 | E63: ='Budget vs Actual'!$D$15 -> 493909.02 | F63: =ROUND(E63-D63,6) -> 0 | G63: 0.5 | H63: =IF(ABS(F63)<=G63,"PASS","FAIL") -> PASS
A64: R-15-ss-BELOW_EBITDA-N | B64: Budget vs Actual | C64: Below-EBITDA items lines (same-sign) vs v_var_scn | D64: 589 | E64: ='Budget vs Actual'!$B$15 -> 589 | F64: =ROUND(E64-D64,6) -> 0 | G64: 0 | H64: =IF(ABS(F64)<=G64,"PASS","FAIL") -> PASS
A65: R-15-al-BELOW_EBITDA-A | B65: Budget vs Actual | C65: Below-EBITDA items actual (all lines) vs v_var_scn | D65: 539704.35 | E65: ='Budget vs Actual'!$C$27 -> 539704.35 | F65: =ROUND(E65-D65,6) -> 0 | G65: 0.5 | H65: =IF(ABS(F65)<=G65,"PASS","FAIL") -> PASS
A66: R-15-al-BELOW_EBITDA-B | B66: Budget vs Actual | C66: Below-EBITDA items budget (all lines) vs v_var_scn | D66: 481316.27 | E66: ='Budget vs Actual'!$D$27 -> 481316.27 | F66: =ROUND(E66-D66,6) -> 0 | G66: 0.5 | H66: =IF(ABS(F66)<=G66,"PASS","FAIL") -> PASS
A67: R-15-al-BELOW_EBITDA-N | B67: Budget vs Actual | C67: Below-EBITDA items lines (all lines) vs v_var_scn | D67: 655 | E67: ='Budget vs Actual'!$B$27 -> 655 | F67: =ROUND(E67-D67,6) -> 0 | G67: 0 | H67: =IF(ABS(F67)<=G67,"PASS","FAIL") -> PASS
A68: R-15-ss-TAX-A | B68: Budget vs Actual | C68: Tax actual (same-sign) vs v_var_scn | D68: 2812303.9 | E68: ='Budget vs Actual'!$C$16 -> 2812303.9 | F68: =ROUND(E68-D68,6) -> 0 | G68: 0.5 | H68: =IF(ABS(F68)<=G68,"PASS","FAIL") -> PASS
A69: R-15-ss-TAX-B | B69: Budget vs Actual | C69: Tax budget (same-sign) vs v_var_scn | D69: 2645687.7 | E69: ='Budget vs Actual'!$D$16 -> 2645687.7 | F69: =ROUND(E69-D69,6) -> 0 | G69: 0.5 | H69: =IF(ABS(F69)<=G69,"PASS","FAIL") -> PASS
A70: R-15-ss-TAX-N | B70: Budget vs Actual | C70: Tax lines (same-sign) vs v_var_scn | D70: 294 | E70: ='Budget vs Actual'!$B$16 -> 294 | F70: =ROUND(E70-D70,6) -> 0 | G70: 0 | H70: =IF(ABS(F70)<=G70,"PASS","FAIL") -> PASS
A71: R-15-al-TAX-A | B71: Budget vs Actual | C71: Tax actual (all lines) vs v_var_scn | D71: 2715839.9 | E71: ='Budget vs Actual'!$C$28 -> 2715839.9 | F71: =ROUND(E71-D71,6) -> 0 | G71: 0.5 | H71: =IF(ABS(F71)<=G71,"PASS","FAIL") -> PASS
A72: R-15-al-TAX-B | B72: Budget vs Actual | C72: Tax budget (all lines) vs v_var_scn | D72: 2750950 | E72: ='Budget vs Actual'!$D$28 -> 2750950 | F72: =ROUND(E72-D72,6) -> 0 | G72: 0.5 | H72: =IF(ABS(F72)<=G72,"PASS","FAIL") -> PASS
A73: R-15-al-TAX-N | B73: Budget vs Actual | C73: Tax lines (all lines) vs v_var_scn | D73: 339 | E73: ='Budget vs Actual'!$B$28 -> 339 | F73: =ROUND(E73-D73,6) -> 0 | G73: 0 | H73: =IF(ABS(F73)<=G73,"PASS","FAIL") -> PASS
A74: R-16-REVENUE | B74: Budget vs Actual | C74: Revenue: all-lines = same-sign + opposite + zero-involved (bridge difference = 0) | D74: 0 | E74: ='Budget vs Actual'!$F$34 -> -7.4505806e-09 | F74: =ROUND(E74-D74,6) -> 0 | G74: 0.5 | H74: =IF(ABS(F74)<=G74,"PASS","FAIL") -> PASS
A75: R-16-COGS | B75: Budget vs Actual | C75: COGS: all-lines = same-sign + opposite + zero-involved (bridge difference = 0) | D75: 0 | E75: ='Budget vs Actual'!$F$35 -> -9.3132257e-10 | F75: =ROUND(E75-D75,6) -> 0 | G75: 0.5 | H75: =IF(ABS(F75)<=G75,"PASS","FAIL") -> PASS
A76: R-16-PEOPLE | B76: Budget vs Actual | C76: People costs: all-lines = same-sign + opposite + zero-involved (bridge difference = 0) | D76: 0 | E76: ='Budget vs Actual'!$F$36 -> -4.9039954e-09 | F76: =ROUND(E76-D76,6) -> 0 | G76: 0.5 | H76: =IF(ABS(F76)<=G76,"PASS","FAIL") -> PASS
A77: R-16-OPEX | B77: Budget vs Actual | C77: Operating expenses: all-lines = same-sign + opposite + zero-involved (bridge difference = 0) | D77: 0 | E77: ='Budget vs Actual'!$F$37 -> 9.5460564e-09 | F77: =ROUND(E77-D77,6) -> 0 | G77: 0.5 | H77: =IF(ABS(F77)<=G77,"PASS","FAIL") -> PASS
A78: R-17-ss-REVENUE-E | B78: Forecast | C78: Revenue net error (ss) vs v_fc_scn | D78: 3483312.7 | E78: ='Forecast & Prior Year'!$E$8 -> 3483312.7 | F78: =ROUND(E78-D78,6) -> -2e-06 | G78: 0.5 | H78: =IF(ABS(F78)<=G78,"PASS","FAIL") -> PASS
A79: R-17-ss-REVENUE-W | B79: Forecast | C79: Revenue WAPE (ss) vs v_fc_scn | D79: 0.02603759 | E79: ='Forecast & Prior Year'!$I$8 -> 0.02603759 | F79: =ROUND(E79-D79,6) -> 0 | G79: 1e-06 | H79: =IF(ABS(F79)<=G79,"PASS","FAIL") -> PASS
A80: R-17-ss-REVENUE-N | B80: Forecast | C80: Revenue lines (ss) vs v_fc_scn | D80: 27593 | E80: ='Forecast & Prior Year'!$B$8 -> 27593 | F80: =ROUND(E80-D80,6) -> 0 | G80: 0 | H80: =IF(ABS(F80)<=G80,"PASS","FAIL") -> PASS
A81: R-17-al-REVENUE-E | B81: Forecast | C81: Revenue net error (al) vs v_fc_scn | D81: 3556516.2 | E81: ='Forecast & Prior Year'!$E$20 -> 3556516.2 | F81: =ROUND(E81-D81,6) -> -2e-06 | G81: 0.5 | H81: =IF(ABS(F81)<=G81,"PASS","FAIL") -> PASS
A82: R-17-al-REVENUE-W | B82: Forecast | C82: Revenue WAPE (al) vs v_fc_scn | D82: 0.2659202 | E82: ='Forecast & Prior Year'!$I$20 -> 0.2659202 | F82: =ROUND(E82-D82,6) -> 0 | G82: 1e-06 | H82: =IF(ABS(F82)<=G82,"PASS","FAIL") -> PASS
A83: R-17-al-REVENUE-N | B83: Forecast | C83: Revenue lines (al) vs v_fc_scn | D83: 30879 | E83: ='Forecast & Prior Year'!$B$20 -> 30879 | F83: =ROUND(E83-D83,6) -> 0 | G83: 0 | H83: =IF(ABS(F83)<=G83,"PASS","FAIL") -> PASS
A84: R-17-ss-COGS-E | B84: Forecast | C84: COGS net error (ss) vs v_fc_scn | D84: -2663835.2 | E84: ='Forecast & Prior Year'!$E$9 -> -2663835.2 | F84: =ROUND(E84-D84,6) -> 0 | G84: 0.5 | H84: =IF(ABS(F84)<=G84,"PASS","FAIL") -> PASS
A85: R-17-ss-COGS-W | B85: Forecast | C85: COGS WAPE (ss) vs v_fc_scn | D85: 0.034262532 | E85: ='Forecast & Prior Year'!$I$9 -> 0.034262532 | F85: =ROUND(E85-D85,6) -> 0 | G85: 1e-06 | H85: =IF(ABS(F85)<=G85,"PASS","FAIL") -> PASS
A86: R-17-ss-COGS-N | B86: Forecast | C86: COGS lines (ss) vs v_fc_scn | D86: 10051 | E86: ='Forecast & Prior Year'!$B$9 -> 10051 | F86: =ROUND(E86-D86,6) -> 0 | G86: 0 | H86: =IF(ABS(F86)<=G86,"PASS","FAIL") -> PASS
A87: R-17-al-COGS-E | B87: Forecast | C87: COGS net error (al) vs v_fc_scn | D87: -2413633.4 | E87: ='Forecast & Prior Year'!$E$21 -> -2413633.4 | F87: =ROUND(E87-D87,6) -> 1e-06 | G87: 0.5 | H87: =IF(ABS(F87)<=G87,"PASS","FAIL") -> PASS
A88: R-17-al-COGS-W | B88: Forecast | C88: COGS WAPE (al) vs v_fc_scn | D88: 0.26995672 | E88: ='Forecast & Prior Year'!$I$21 -> 0.26995672 | F88: =ROUND(E88-D88,6) -> 0 | G88: 1e-06 | H88: =IF(ABS(F88)<=G88,"PASS","FAIL") -> PASS
A89: R-17-al-COGS-N | B89: Forecast | C89: COGS lines (al) vs v_fc_scn | D89: 11443 | E89: ='Forecast & Prior Year'!$B$21 -> 11443 | F89: =ROUND(E89-D89,6) -> 0 | G89: 0 | H89: =IF(ABS(F89)<=G89,"PASS","FAIL") -> PASS
A90: R-17-ss-PEOPLE-E | B90: Forecast | C90: People costs net error (ss) vs v_fc_scn | D90: -1134929.4 | E90: ='Forecast & Prior Year'!$E$10 -> -1134929.4 | F90: =ROUND(E90-D90,6) -> 0 | G90: 0.5 | H90: =IF(ABS(F90)<=G90,"PASS","FAIL") -> PASS
A91: R-17-ss-PEOPLE-W | B91: Forecast | C91: People costs WAPE (ss) vs v_fc_scn | D91: 0.033719035 | E91: ='Forecast & Prior Year'!$I$10 -> 0.033719035 | F91: =ROUND(E91-D91,6) -> 0 | G91: 1e-06 | H91: =IF(ABS(F91)<=G91,"PASS","FAIL") -> PASS
A92: R-17-ss-PEOPLE-N | B92: Forecast | C92: People costs lines (ss) vs v_fc_scn | D92: 2690 | E92: ='Forecast & Prior Year'!$B$10 -> 2690 | F92: =ROUND(E92-D92,6) -> 0 | G92: 0 | H92: =IF(ABS(F92)<=G92,"PASS","FAIL") -> PASS
A93: R-17-al-PEOPLE-E | B93: Forecast | C93: People costs net error (al) vs v_fc_scn | D93: -621737.97 | E93: ='Forecast & Prior Year'!$E$22 -> -621737.97 | F93: =ROUND(E93-D93,6) -> 0 | G93: 0.5 | H93: =IF(ABS(F93)<=G93,"PASS","FAIL") -> PASS
A94: R-17-al-PEOPLE-W | B94: Forecast | C94: People costs WAPE (al) vs v_fc_scn | D94: 0.29328126 | E94: ='Forecast & Prior Year'!$I$22 -> 0.29328126 | F94: =ROUND(E94-D94,6) -> 0 | G94: 1e-06 | H94: =IF(ABS(F94)<=G94,"PASS","FAIL") -> PASS
A95: R-17-al-PEOPLE-N | B95: Forecast | C95: People costs lines (al) vs v_fc_scn | D95: 3102 | E95: ='Forecast & Prior Year'!$B$22 -> 3102 | F95: =ROUND(E95-D95,6) -> 0 | G95: 0 | H95: =IF(ABS(F95)<=G95,"PASS","FAIL") -> PASS
A96: R-17-ss-OPEX-E | B96: Forecast | C96: Operating expenses net error (ss) vs v_fc_scn | D96: -1266594 | E96: ='Forecast & Prior Year'!$E$11 -> -1266594 | F96: =ROUND(E96-D96,6) -> 0 | G96: 0.5 | H96: =IF(ABS(F96)<=G96,"PASS","FAIL") -> PASS
A97: R-17-ss-OPEX-W | B97: Forecast | C97: Operating expenses WAPE (ss) vs v_fc_scn | D97: 0.034171866 | E97: ='Forecast & Prior Year'!$I$11 -> 0.034171866 | F97: =ROUND(E97-D97,6) -> 0 | G97: 1e-06 | H97: =IF(ABS(F97)<=G97,"PASS","FAIL") -> PASS
A98: R-17-ss-OPEX-N | B98: Forecast | C98: Operating expenses lines (ss) vs v_fc_scn | D98: 7048 | E98: ='Forecast & Prior Year'!$B$11 -> 7048 | F98: =ROUND(E98-D98,6) -> 0 | G98: 0 | H98: =IF(ABS(F98)<=G98,"PASS","FAIL") -> PASS
A99: R-17-al-OPEX-E | B99: Forecast | C99: Operating expenses net error (al) vs v_fc_scn | D99: -328049.77 | E99: ='Forecast & Prior Year'!$E$23 -> -328049.77 | F99: =ROUND(E99-D99,6) -> 0 | G99: 0.5 | H99: =IF(ABS(F99)<=G99,"PASS","FAIL") -> PASS
A100: R-17-al-OPEX-W | B100: Forecast | C100: Operating expenses WAPE (al) vs v_fc_scn | D100: 0.27873473 | E100: ='Forecast & Prior Year'!$I$23 -> 0.27873473 | F100: =ROUND(E100-D100,6) -> 0 | G100: 1e-06 | H100: =IF(ABS(F100)<=G100,"PASS","FAIL") -> PASS
A101: R-17-al-OPEX-N | B101: Forecast | C101: Operating expenses lines (al) vs v_fc_scn | D101: 8119 | E101: ='Forecast & Prior Year'!$B$23 -> 8119 | F101: =ROUND(E101-D101,6) -> 0 | G101: 0 | H101: =IF(ABS(F101)<=G101,"PASS","FAIL") -> PASS
A102: R-17b-REVENUE-N | B102: Forecast | C102: Revenue matched-subset lines vs v_pl_budget (sign_cat_ab and sign_cat_af both same-sign) | D102: 24372 | E102: ='Forecast & Prior Year'!$B$32 -> 24372 | F102: =ROUND(E102-D102,6) -> 0 | G102: 0 | H102: =IF(ABS(F102)<=G102,"PASS","FAIL") -> PASS
...

Sheet Definitions
A1: Definitions, assumptions and lineage | D1: Back to Start Here
A2: Every definition below is the Phase 4 definition. The rules register is parsed from docs/FINANCIAL_METRICS.md; nothing here upgrades a Proposed or Unresolved rule to Confirmed.
A3: PROVISIONAL: Posted-only eligibility (R6), scale restoration (R7), FX direction (R8), the variance-% convention (R10), the grain of budget/forecast/prior-year (summed per line) and the exclusion of junk entities (R4) are working conventions. Unresolved: the account sign convention (R9), the duplicate rule (R11) and consolidation/elimination (R12).
A5: D1. Rules register (R1-R14)
A6: Status labels: Confirmed = owner-stated or plain fact; Proposed-Needs Validation = candidate rule; Unresolved = the data does not settle it.
A7: Rule | B7: Rule text | C7: Status | D7: Basis
A8: R1 | B8: Amounts are text. Do not sum raw values. | C8: Confirmed | D8: Owner-stated; all 43 columns are text.
A9: R2 | B9: P&L flows and balance-sheet balances are never added together. | C9: Confirmed | D9: Owner-stated.
A10: R3 | B10: TOTAL, Subtotal, CHECK rows (identified by notes = subtotal row, 350 rows) are not postings and are excluded from all calculations. | C10: Confirmed (identification) | D10: All 350 rows carry non-posting labels in account_name or fs_line; every row with such a label is in the 350. The exclusion principle is owner-stated.
A11: R4 | B11: Rows for the junk entities TEST ENTITY, Do not use, xxx (173 rows) are excluded. | C11: Confirmed (owner-stated for TEST ENTITY); Proposed—Needs Validation for the other two names | D11: Not independently confirmed that Do not use and xxx are non-reporting.
A12: R5 | B12: document_no is not a unique posting key and repeated numbers are not automatically duplicates. | C12: Confirmed | D12: 4,260 numbers repeat over 8,540 rows; no two rows are identical apart from row_id.
A13: R6 | B13: Only approval_status values with an explicit treatment enter reported totals (section 5). | C13: Proposed—Needs Validation | D13: See section 5.
A14: R7 | B14: report_scale labels are not trusted; scale is decided per row by a written rule. | C14: Confirmed (labels unreliable, owner-stated); rule itself Unresolved | D14: Section 8.
A15: R8 | B15: FX direction is USD = local ÷ rate (local currency per 1 USD). | C15: Proposed—Needs Validation | D15: Section 9. Not final.
A16: R9 | B16: Account sign convention. | C16: Unresolved | D16: Section 6.
A17: R10 | B17: Variance = Actual − Budget; variance percent uses |Budget| as denominator. This is a proposed project convention, not an accounting standard. | C17: Proposed—Needs Validation | D17: Section 2.
A18: R11 | B18: Duplicate rule for journal lines. | C18: Unresolved | D18: Section 11.
... A21: R14 | B21: Every raw row gets exactly one primary exclusion reason or is eligible, using a fixed precedence. Secondary issues are separate flags. | C21: Proposed—Needs Validation | D21: Section 4.
B23: Rules parsed (count): | C23: =COUNTA($A$8:$A$21) -> 14
A24: Legend: red = Unresolved; amber = Proposed - needs validation; green = Confirmed.
A27: D2. Metric definitions
A28: Metric | B28: Definition | C28: Source | D28: Limit / status
A29: Actual / Budget / Forecast / Prior-year | B29: actual_usd_adj etc.: reported USD amounts after the per-row scale rule; signs as recorded; costs are positive magnitudes. | C29: Phase 4 views v_pl_* | D29: Provisional (R6, R7).
A30: Variance | B30: Actual - Budget (arithmetic difference). Never labelled favourable/adverse. | C30: FINANCIAL_METRICS s2 | D30: R10 convention; R9 sign convention unresolved.
A31: Variance % | B31: Variance / |net budget|, shown only when |net budget| >= 50% of the gross (absolute) budget; otherwise 'n/a (guard)'. | C31: Phase 4 safe_pct macro | D31: Project convention, not a standard.
A32: Same-sign basis | B32: Lines where actual and budget (or forecast) are both non-zero with the same sign. Primary basis for variance and forecast tables. | C32: Phase 4 sign_cat | D32: Excludes opposite-sign and zero-involved lines; those are shown in bridges.
A33: Forecast error | B33: Forecast - Actual. Positive = forecast above actual. | C33: FINANCIAL_METRICS s3 | D33: Observation only; no snapshot dates => no skill claim.
A34: WAPE | B34: Sum |Forecast - Actual| / Sum |Actual|. | C34: FINANCIAL_METRICS s3 | D34: Weights large lines more.
A35: Bias | B35: Sum (Forecast - Actual) / Sum |Actual|. | C35: FINANCIAL_METRICS s3 | D35: Directional, not a correction.
A36: Gross profit | B36: Revenue (GL 4100-4190) - COGS (GL 5100-5300). Three treatments of discounts: S1 signed as recorded, S2 discount at absolute value, S3 excluding discounts. | C36: Phase 4 v_gp_rows | D36: Sign convention unresolved; no treatment is authoritative.
A37: Gross margin % | B37: Gross profit / Revenue, only when revenue > 0. | C37: Phase 4
A38: Operating result proxy | B38: Revenue - COGS - People - Opex. NOT EBITDA / operating profit. D&A, below-EBITDA and tax shown as memo lines only. | C38: Phase 4 | D38: Sign treatment of D&A, FX gain/loss unverified.
A39: Eligible P&L line | B39: A P&L posting line that passes the exclusion waterfall (non-posting rows, junk entities, non-Posted status, unparseable values excluded). | C39: FINANCIAL_METRICS s4-5 | D39: R3, R4, R6, R14.
A40: Absolute activity | B40: Sum of |amount|; used for shares and concentration so offsetting signs do not net out. | C40: Phase 4
A41: Share of gross cell variance | B41: |cell variance| / sum of |cell variance| within the section. | C41: Phase 4 out_b2 | D41: Gross variance exposes offsets hidden in the net.
A44: D3. Remaining decisions for the owner (FINANCIAL_METRICS section 15)
A45: Each changes a headline number or its meaning. Until decided, the safe default is shown and affected lines are counted, not silently changed.
A46: 1 | B46: Meaning of blank approval_status, and whether about 43% eligible rows is intended.
A47: 2 | B47: Whether - in an amount means zero.
A48: 3 | B48: Sign treatment of discounts (4190) and FX gain or loss (7200).
A49: 4 | B49: The scale rule, after checking all amount columns.
A50: 5 | B50: FX direction and the 2,517 zero-rate rows.
A51: 6 | B51: Whether budget, forecast and prior year are summable per line.
A52: 7 | B52: The duplicate key.
A53: 8 | B53: Whether results are by entity or consolidated.
A56: D4. Assumptions made in this workbook
A57: 1. All amounts are USD after Phase 4's scale rule and are provisional; the extract is synthetic (NovaBridge Industries) and provenance/licence are unverified.
A58: 2. Budget, forecast and prior-year values are per-line amounts and are summed (supported by out_a0: 98% of multi-line cells hold different values); if they are repeated header values, every variance would change.
A59: 3. Posted-only is the reporting population. Pending, Parked, Rejected and blank statuses are excluded (INS-01 shows how much this matters).
A60: 4. Percent thresholds on this workbook (MoM highlight 10%, variance highlight 5%, guard 50%) are blue inputs: changing them changes the highlighting/guard only, not any total.
A61: 5. Tolerance on reconciliation checks: 0.5 USD for amounts, exact for counts. Floating-point differences below that are not material.
A62: 6. Calendar year = year of the posting period; the extract's fiscal year label is not used for totals.
A63: 7. No intercompany elimination, no FX re-translation, no duplicate removal, no sign flipping, no missing-as-zero.
A66: D5. Lineage: sheet -> Phase 4 source -> check
A67: Every number on a sheet traces to one of these Phase 4 tables; the Reconciliation & QA sheet tests the link.
A68: Sheet | B68: Phase 4 source tables | C68: Reconciliation checks
A69: Monthly P&L | B69: out_a1_pl_period_section | C69: R-01, R-02, R-04..R-10, R-13-2023..2025 (totals and population vs independent recompute from v_pl_actual / v_close)
A70: Budget vs Actual | B70: out_b1, out_b2, out_b3, out_b4, out_b7-b11 | C70: R-15-* and R-16-* (independent recompute from v_var_scn; bridge), R-24 (recomputed % = Phase 4 %), R-29 (budgeted lines)
A71: Forecast & Prior Year | B71: out_c1-c8, out_d1-d5; F3b from v_pl_budget | C71: R-17-* (v_fc_scn), R-17b-* (matched subset) and R-17c-* (comparable lines) recomputed from v_close; prior-year tables are not independently recomputed
A72: Entity & Division | B72: out_a2, out_a3, out_b2, out_b3, out_g5 | C72: R-03b (entity lines), R-11 (entity revenue), R-12 (division revenue), R-14-* (revenue per entity)
A73: GL & Cost Drivers | B73: out_a4, out_f1-f7, out_b2 | C73: R-03 (GL activity lines = eligible lines); GL cost Pareto and driver tables are not independently recomputed
A74: Gross Profit | B74: out_e1-e4 | C74: R-21-* (independent recompute from v_gp_rows), R-22 (S1 = Monthly P&L), R-23-* (bridge)
A75: Insights & Actions | B75: docs/PHASE4_INSIGHT_REGISTER.md + database figures | C75: R-25 (register figures found by formula; the register text itself is copied, not recomputed)
A76: Data Quality | B76: out_i1-i10, out_a0, out_a5-a8, out_h1-h6 | C76: R-02, R-26 (waterfall = all source rows; mapping consistent); other Data Quality tables are copied from Phase 4
A77: Executive Summary | B77: links to the sheets above | C77: no separate row: every headline is a link, and the Python tests compare each with its source cell
A78: Reconciliation & QA | B78: database views v_pl_*, v_var_scn, v_fc_scn, v_gp_rows | C78: self-checking
