Workbook

Sheet Summary
A1: Financial reconciliation - independent pandas reference vs SQL, Excel and dashboard
A2: Counts are live formulas over the 'Checks' sheet (COUNTIF on the status column). INFO rows are observations, not tests.
A4: Status | B4: Checks
A5: PASS | B5: =COUNTIF(Checks!$K$4:$K$634,A5) -> 620
A6: FAIL | B6: =COUNTIF(Checks!$K$4:$K$634,A6) -> 0
A7: BLOCKED | B7: =COUNTIF(Checks!$K$4:$K$634,A7) -> 0
A8: NOT TESTED | B8: =COUNTIF(Checks!$K$4:$K$634,A8) -> 3
A9: INFO | B9: =COUNTIF(Checks!$K$4:$K$634,A9) -> 8
A10: Total | B10: =SUM(B5:B9) -> 631

Sheet Checks
A1: All financial comparisons (same population, same documented definition on both sides)
A2: Tolerance: money 0.01 USD (one cent); ratios 1e-9; counts exact; dashboard display values at display precision. Table comparisons count the rows outside tolerance (expected 0).
A3: id | B3: area | C3: check | D3: population | E3: definition | F3: expected | G3: actual | H3: abs_diff | I3: rel_diff | J3: tolerance | K3: status | L3: explanation / evidence note | M3: evidence | N3: Recheck |diff| (formula) | O3: Recheck status (formula)
A4: F_A1.keys | B4: Independent financial recomputation vs SQL | C4: P&L by period x section (a1): same key set (rows only in one side) | D4: Posted eligible P&L (58,340) | E4: outer join on period_ym,section | F4: 0 | G4: 0 | H4: 0 | J4: 0 | K4: PASS | N4: =IF(AND(ISNUMBER(F4),ISNUMBER(G4)),ABS(G4-F4),"") -> 0 | O4: =IF(AND(ISNUMBER(N4),ISNUMBER(J4)),IF(N4<=J4,"PASS","FAIL"),"n/a") -> PASS
A5: F_A1.rows_eligible | B5: Independent financial recomputation vs SQL | C5: P&L by period x section (a1): rows_eligible (all 252 rows) | D5: Posted eligible P&L (58,340) | E5: sum of scale-adjusted actual; abs = sum |line| | F5: 0 | G5: 0 | H5: 0 | J5: 0 | K5: PASS | L5: max |SQL - reference| = 0; null-pattern mismatches 0 | N5: =IF(AND(ISNUMBER(F5),ISNUMBER(G5)),ABS(G5-F5),"") -> 0 | O5: =IF(AND(ISNUMBER(N5),ISNUMBER(J5)),IF(N5<=J5,"PASS","FAIL"),"n/a") -> PASS
A6: F_A1.actual_usd | B6: Independent financial recomputation vs SQL | C6: P&L by period x section (a1): actual_usd (all 252 rows) | D6: Posted eligible P&L (58,340) | E6: sum of scale-adjusted actual; abs = sum |line| | F6: 0 | G6: 0 | H6: 0 | J6: 0.01 | K6: PASS | L6: max |SQL - reference| = 9.31e-09; null-pattern mismatches 0 | N6: =IF(AND(ISNUMBER(F6),ISNUMBER(G6)),ABS(G6-F6),"") -> 0 | O6: =IF(AND(ISNUMBER(N6),ISNUMBER(J6)),IF(N6<=J6,"PASS","FAIL"),"n/a") -> PASS
A7: F_A1.abs_actual_usd | B7: Independent financial recomputation vs SQL | C7: P&L by period x section (a1): abs_actual_usd (all 252 rows) | D7: Posted eligible P&L (58,340) | E7: sum of scale-adjusted actual; abs = sum |line| | F7: 0 | G7: 0 | H7: 0 | J7: 0.01 | K7: PASS | L7: max |SQL - reference| = 1.68e-08; null-pattern mismatches 0 | N7: =IF(AND(ISNUMBER(F7),ISNUMBER(G7)),ABS(G7-F7),"") -> 0 | O7: =IF(AND(ISNUMBER(N7),ISNUMBER(J7)),IF(N7<=J7,"PASS","FAIL"),"n/a") -> PASS
A8: F_A1.actual_usd_as_reported_parsed | B8: Independent financial recomputation vs SQL | C8: P&L by period x section (a1): actual_usd_as_reported_parsed (all 252 rows) | D8: Posted eligible P&L (58,340) | E8: sum of scale-adjusted actual; abs = sum |line| | F8: 0 | G8: 0 | H8: 0 | J8: 0.01 | K8: PASS | L8: max |SQL - reference| = 8.38e-09; null-pattern mismatches 0 | N8: =IF(AND(ISNUMBER(F8),ISNUMBER(G8)),ABS(G8-F8),"") -> 0 | O8: =IF(AND(ISNUMBER(N8),ISNUMBER(J8)),IF(N8<=J8,"PASS","FAIL"),"n/a") -> PASS
A9: F_A2.keys | B9: Independent financial recomputation vs SQL | C9: P&L by entity x section (a2): same key set (rows only in one side) | D9: Posted eligible | E9: outer join on entity_code,section | F9: 0 | G9: 0 | H9: 0 | J9: 0 | K9: PASS | N9: =IF(AND(ISNUMBER(F9),ISNUMBER(G9)),ABS(G9-F9),"") -> 0 | O9: =IF(AND(ISNUMBER(N9),ISNUMBER(J9)),IF(N9<=J9,"PASS","FAIL"),"n/a") -> PASS
A10: F_A2.rows_eligible | B10: Independent financial recomputation vs SQL | C10: P&L by entity x section (a2): rows_eligible (all 42 rows) | D10: Posted eligible | F10: 0 | G10: 0 | H10: 0 | J10: 0 | K10: PASS | L10: max |SQL - reference| = 0; null-pattern mismatches 0 | N10: =IF(AND(ISNUMBER(F10),ISNUMBER(G10)),ABS(G10-F10),"") -> 0 | O10: =IF(AND(ISNUMBER(N10),ISNUMBER(J10)),IF(N10<=J10,"PASS","FAIL"),"n/a") -> PASS
A11: F_A2.actual_usd | B11: Independent financial recomputation vs SQL | C11: P&L by entity x section (a2): actual_usd (all 42 rows) | D11: Posted eligible | F11: 0 | G11: 0 | H11: 0 | J11: 0.01 | K11: PASS | L11: max |SQL - reference| = 1.27e-07; null-pattern mismatches 0 | N11: =IF(AND(ISNUMBER(F11),ISNUMBER(G11)),ABS(G11-F11),"") -> 0 | O11: =IF(AND(ISNUMBER(N11),ISNUMBER(J11)),IF(N11<=J11,"PASS","FAIL"),"n/a") -> PASS
A12: F_A2.abs_actual_usd | B12: Independent financial recomputation vs SQL | C12: P&L by entity x section (a2): abs_actual_usd (all 42 rows) | D12: Posted eligible | F12: 0 | G12: 0 | H12: 0 | J12: 0.01 | K12: PASS | L12: max |SQL - reference| = 9.69e-08; null-pattern mismatches 0 | N12: =IF(AND(ISNUMBER(F12),ISNUMBER(G12)),ABS(G12-F12),"") -> 0 | O12: =IF(AND(ISNUMBER(N12),ISNUMBER(J12)),IF(N12<=J12,"PASS","FAIL"),"n/a") -> PASS
A13: F_A2.share_of_section_abs | B13: Independent financial recomputation vs SQL | C13: P&L by entity x section (a2): share_of_section_abs (all 42 rows) | D13: Posted eligible | F13: 0 | G13: 0 | H13: 0 | J13: 1e-09 | K13: PASS | L13: max |SQL - reference| = 3.89e-16; null-pattern mismatches 0 | N13: =IF(AND(ISNUMBER(F13),ISNUMBER(G13)),ABS(G13-F13),"") -> 0 | O13: =IF(AND(ISNUMBER(N13),ISNUMBER(J13)),IF(N13<=J13,"PASS","FAIL"),"n/a") -> PASS
A14: F_A3.keys | B14: Independent financial recomputation vs SQL | C14: P&L by division x section (a3): same key set (rows only in one side) | D14: Posted eligible | E14: outer join on division,section | F14: 0 | G14: 0 | H14: 0 | J14: 0 | K14: PASS | N14: =IF(AND(ISNUMBER(F14),ISNUMBER(G14)),ABS(G14-F14),"") -> 0 | O14: =IF(AND(ISNUMBER(N14),ISNUMBER(J14)),IF(N14<=J14,"PASS","FAIL"),"n/a") -> PASS
A15: F_A3.rows_eligible | B15: Independent financial recomputation vs SQL | C15: P&L by division x section (a3): rows_eligible (all 35 rows) | D15: Posted eligible | F15: 0 | G15: 0 | H15: 0 | J15: 0 | K15: PASS | L15: max |SQL - reference| = 0; null-pattern mismatches 0 | N15: =IF(AND(ISNUMBER(F15),ISNUMBER(G15)),ABS(G15-F15),"") -> 0 | O15: =IF(AND(ISNUMBER(N15),ISNUMBER(J15)),IF(N15<=J15,"PASS","FAIL"),"n/a") -> PASS
A16: F_A3.actual_usd | B16: Independent financial recomputation vs SQL | C16: P&L by division x section (a3): actual_usd (all 35 rows) | D16: Posted eligible | F16: 0 | G16: 0 | H16: 0 | J16: 0.01 | K16: PASS | L16: max |SQL - reference| = 2.24e-07; null-pattern mismatches 0 | N16: =IF(AND(ISNUMBER(F16),ISNUMBER(G16)),ABS(G16-F16),"") -> 0 | O16: =IF(AND(ISNUMBER(N16),ISNUMBER(J16)),IF(N16<=J16,"PASS","FAIL"),"n/a") -> PASS
A17: F_A3.abs_actual_usd | B17: Independent financial recomputation vs SQL | C17: P&L by division x section (a3): abs_actual_usd (all 35 rows) | D17: Posted eligible | F17: 0 | G17: 0 | H17: 0 | J17: 0.01 | K17: PASS | L17: max |SQL - reference| = 2.01e-07; null-pattern mismatches 0 | N17: =IF(AND(ISNUMBER(F17),ISNUMBER(G17)),ABS(G17-F17),"") -> 0 | O17: =IF(AND(ISNUMBER(N17),ISNUMBER(J17)),IF(N17<=J17,"PASS","FAIL"),"n/a") -> PASS
A18: F_A3.share_of_section_abs | B18: Independent financial recomputation vs SQL | C18: P&L by division x section (a3): share_of_section_abs (all 35 rows) | D18: Posted eligible | F18: 0 | G18: 0 | H18: 0 | J18: 1e-09 | K18: PASS | L18: max |SQL - reference| = 8.33e-16; null-pattern mismatches 0 | N18: =IF(AND(ISNUMBER(F18),ISNUMBER(G18)),ABS(G18-F18),"") -> 0 | O18: =IF(AND(ISNUMBER(N18),ISNUMBER(J18)),IF(N18<=J18,"PASS","FAIL"),"n/a") -> PASS
A19: F_A4.keys | B19: Independent financial recomputation vs SQL | C19: P&L by GL account (a4): same key set (rows only in one side) | D19: Posted eligible | E19: outer join on gl_account | F19: 0 | G19: 0 | H19: 0 | J19: 0 | K19: PASS | N19: =IF(AND(ISNUMBER(F19),ISNUMBER(G19)),ABS(G19-F19),"") -> 0 | O19: =IF(AND(ISNUMBER(N19),ISNUMBER(J19)),IF(N19<=J19,"PASS","FAIL"),"n/a") -> PASS
A20: F_A4.rows_eligible | B20: Independent financial recomputation vs SQL | C20: P&L by GL account (a4): rows_eligible (all 24 rows) | D20: Posted eligible | F20: 0 | G20: 0 | H20: 0 | J20: 0 | K20: PASS | L20: max |SQL - reference| = 0; null-pattern mismatches 0 | N20: =IF(AND(ISNUMBER(F20),ISNUMBER(G20)),ABS(G20-F20),"") -> 0 | O20: =IF(AND(ISNUMBER(N20),ISNUMBER(J20)),IF(N20<=J20,"PASS","FAIL"),"n/a") -> PASS
A21: F_A4.actual_usd | B21: Independent financial recomputation vs SQL | C21: P&L by GL account (a4): actual_usd (all 24 rows) | D21: Posted eligible | F21: 0 | G21: 0 | H21: 0 | J21: 0.01 | K21: PASS | L21: max |SQL - reference| = 1.07e-06; null-pattern mismatches 0 | N21: =IF(AND(ISNUMBER(F21),ISNUMBER(G21)),ABS(G21-F21),"") -> 0 | O21: =IF(AND(ISNUMBER(N21),ISNUMBER(J21)),IF(N21<=J21,"PASS","FAIL"),"n/a") -> PASS
A22: F_A4.abs_actual_usd | B22: Independent financial recomputation vs SQL | C22: P&L by GL account (a4): abs_actual_usd (all 24 rows) | D22: Posted eligible | F22: 0 | G22: 0 | H22: 0 | J22: 0.01 | K22: PASS | L22: max |SQL - reference| = 5.96e-07; null-pattern mismatches 0 | N22: =IF(AND(ISNUMBER(F22),ISNUMBER(G22)),ABS(G22-F22),"") -> 0 | O22: =IF(AND(ISNUMBER(N22),ISNUMBER(J22)),IF(N22<=J22,"PASS","FAIL"),"n/a") -> PASS
A23: F_A4.share_of_total_abs | B23: Independent financial recomputation vs SQL | C23: P&L by GL account (a4): share_of_total_abs (all 24 rows) | D23: Posted eligible | F23: 0 | G23: 0 | H23: 0 | J23: 1e-09 | K23: PASS | L23: max |SQL - reference| = 9.99e-16; null-pattern mismatches 0 | N23: =IF(AND(ISNUMBER(F23),ISNUMBER(G23)),ABS(G23-F23),"") -> 0 | O23: =IF(AND(ISNUMBER(N23),ISNUMBER(J23)),IF(N23<=J23,"PASS","FAIL"),"n/a") -> PASS
A24: F_A4.share_rows_negative | B24: Independent financial recomputation vs SQL | C24: P&L by GL account (a4): share_rows_negative (all 24 rows) | D24: Posted eligible | F24: 0 | G24: 0 | H24: 0 | J24: 1e-09 | K24: PASS | L24: max |SQL - reference| = 9.71e-17; null-pattern mismatches 0 | N24: =IF(AND(ISNUMBER(F24),ISNUMBER(G24)),ABS(G24-F24),"") -> 0 | O24: =IF(AND(ISNUMBER(N24),ISNUMBER(J24)),IF(N24<=J24,"PASS","FAIL"),"n/a") -> PASS
A25: F_B0 | B25: Independent financial recomputation vs SQL | C25: Variance population rows (Posted eligible with budget) | F25: 55043 | G25: 55043 | H25: 0 | I25: 0 | J25: 0 | K25: PASS | N25: =IF(AND(ISNUMBER(F25),ISNUMBER(G25)),ABS(G25-F25),"") -> 0 | O25: =IF(AND(ISNUMBER(N25),ISNUMBER(J25)),IF(N25<=J25,"PASS","FAIL"),"n/a") -> PASS
A26: F_B1.keys | B26: Independent financial recomputation vs SQL | C26: Budget variance by section, 4 sign scenarios (b1): same key set (rows only in one side) | D26: Posted eligible with budget (55,043) | E26: outer join on scenario,section | F26: 0 | G26: 0 | H26: 0 | J26: 0 | K26: PASS | N26: =IF(AND(ISNUMBER(F26),ISNUMBER(G26)),ABS(G26-F26),"") -> 0 | O26: =IF(AND(ISNUMBER(N26),ISNUMBER(J26)),IF(N26<=J26,"PASS","FAIL"),"n/a") -> PASS
A27: F_B1.rows_in_scope | B27: Independent financial recomputation vs SQL | C27: Budget variance by section, 4 sign scenarios (b1): rows_in_scope (all 26 rows) | D27: Posted eligible with budget (55,043) | E27: variance = actual - budget; pct guarded: |net budget| >= 50% of sum |cell budget| | F27: 0 | G27: 0 | H27: 0 | J27: 0 | K27: PASS | L27: max |SQL - reference| = 0; null-pattern mismatches 0 | N27: =IF(AND(ISNUMBER(F27),ISNUMBER(G27)),ABS(G27-F27),"") -> 0 | O27: =IF(AND(ISNUMBER(N27),ISNUMBER(J27)),IF(N27<=J27,"PASS","FAIL"),"n/a") -> PASS
A28: F_B1.actual_usd | B28: Independent financial recomputation vs SQL | C28: Budget variance by section, 4 sign scenarios (b1): actual_usd (all 26 rows) | D28: Posted eligible with budget (55,043) | E28: variance = actual - budget; pct guarded: |net budget| >= 50% of sum |cell budget| | F28: 0 | G28: 0 | H28: 0 | J28: 0.01 | K28: PASS | L28: max |SQL - reference| = 3.87e-07; null-pattern mismatches 0 | N28: =IF(AND(ISNUMBER(F28),ISNUMBER(G28)),ABS(G28-F28),"") -> 0 | O28: =IF(AND(ISNUMBER(N28),ISNUMBER(J28)),IF(N28<=J28,"PASS","FAIL"),"n/a") -> PASS
A29: F_B1.budget_usd | B29: Independent financial recomputation vs SQL | C29: Budget variance by section, 4 sign scenarios (b1): budget_usd (all 26 rows) | D29: Posted eligible with budget (55,043) | E29: variance = actual - budget; pct guarded: |net budget| >= 50% of sum |cell budget| | F29: 0 | G29: 0 | H29: 0 | J29: 0.01 | K29: PASS | L29: max |SQL - reference| = 2.09e-07; null-pattern mismatches 0 | N29: =IF(AND(ISNUMBER(F29),ISNUMBER(G29)),ABS(G29-F29),"") -> 0 | O29: =IF(AND(ISNUMBER(N29),ISNUMBER(J29)),IF(N29<=J29,"PASS","FAIL"),"n/a") -> PASS
A30: F_B1.net_variance_usd | B30: Independent financial recomputation vs SQL | C30: Budget variance by section, 4 sign scenarios (b1): net_variance_usd (all 26 rows) | D30: Posted eligible with budget (55,043) | E30: variance = actual - budget; pct guarded: |net budget| >= 50% of sum |cell budget| | F30: 0 | G30: 0 | H30: 0 | J30: 0.01 | K30: PASS | L30: max |SQL - reference| = 8.85e-09; null-pattern mismatches 0 | N30: =IF(AND(ISNUMBER(F30),ISNUMBER(G30)),ABS(G30-F30),"") -> 0 | O30: =IF(AND(ISNUMBER(N30),ISNUMBER(J30)),IF(N30<=J30,"PASS","FAIL"),"n/a") -> PASS
A31: F_B1.gross_cell_variance_usd | B31: Independent financial recomputation vs SQL | C31: Budget variance by section, 4 sign scenarios (b1): gross_cell_variance_usd (all 26 rows) | D31: Posted eligible with budget (55,043) | E31: variance = actual - budget; pct guarded: |net budget| >= 50% of sum |cell budget| | F31: 0 | G31: 0 | H31: 0 | J31: 0.01 | K31: PASS | L31: max |SQL - reference| = 2.98e-08; null-pattern mismatches 0 | N31: =IF(AND(ISNUMBER(F31),ISNUMBER(G31)),ABS(G31-F31),"") -> 0 | O31: =IF(AND(ISNUMBER(N31),ISNUMBER(J31)),IF(N31<=J31,"PASS","FAIL"),"n/a") -> PASS
A32: F_B1.variance_pct_of_abs_budget | B32: Independent financial recomputation vs SQL | C32: Budget variance by section, 4 sign scenarios (b1): variance_pct_of_abs_budget (all 26 rows) | D32: Posted eligible with budget (55,043) | E32: variance = actual - budget; pct guarded: |net budget| >= 50% of sum |cell budget| | F32: 0 | G32: 0 | H32: 0 | J32: 1e-09 | K32: PASS | L32: max |SQL - reference| = 3.05e-16; null-pattern mismatches 0 | N32: =IF(AND(ISNUMBER(F32),ISNUMBER(G32)),ABS(G32-F32),"") -> 0 | O32: =IF(AND(ISNUMBER(N32),ISNUMBER(J32)),IF(N32<=J32,"PASS","FAIL"),"n/a") -> PASS
A33: F_B1.budget_netting_ratio | B33: Independent financial recomputation vs SQL | C33: Budget variance by section, 4 sign scenarios (b1): budget_netting_ratio (all 26 rows) | D33: Posted eligible with budget (55,043) | E33: variance = actual - budget; pct guarded: |net budget| >= 50% of sum |cell budget| | F33: 0 | G33: 0 | H33: 0 | J33: 1e-09 | K33: PASS | L33: max |SQL - reference| = 1.89e-15; null-pattern mismatches 0 | N33: =IF(AND(ISNUMBER(F33),ISNUMBER(G33)),ABS(G33-F33),"") -> 0 | O33: =IF(AND(ISNUMBER(N33),ISNUMBER(J33)),IF(N33<=J33,"PASS","FAIL"),"n/a") -> PASS
A34: F_B1.gross_variance_pct_of_abs_cell_budget | B34: Independent financial recomputation vs SQL | C34: Budget variance by section, 4 sign scenarios (b1): gross_variance_pct_of_abs_cell_budget (all 26 rows) | D34: Posted eligible with budget (55,043) | E34: variance = actual - budget; pct guarded: |net budget| >= 50% of sum |cell budget| | F34: 0 | G34: 0 | H34: 0 | J34: 1e-09 | K34: PASS | L34: max |SQL - reference| = 2.22e-15; null-pattern mismatches 0 | N34: =IF(AND(ISNUMBER(F34),ISNUMBER(G34)),ABS(G34-F34),"") -> 0 | O34: =IF(AND(ISNUMBER(N34),ISNUMBER(J34)),IF(N34<=J34,"PASS","FAIL"),"n/a") -> PASS
A35: F_B3.keys | B35: Independent financial recomputation vs SQL | C35: Budget variance by division x section (b3, amounts): same key set (rows only in one side) | D35: Posted eligible with budget | E35: outer join on scenario,division,section | F35: 0 | G35: 0 | H35: 0 | J35: 0 | K35: PASS | N35: =IF(AND(ISNUMBER(F35),ISNUMBER(G35)),ABS(G35-F35),"") -> 0 | O35: =IF(AND(ISNUMBER(N35),ISNUMBER(J35)),IF(N35<=J35,"PASS","FAIL"),"n/a") -> PASS
A36: F_B3.rows_in_scope | B36: Independent financial recomputation vs SQL | C36: Budget variance by division x section (b3, amounts): rows_in_scope (all 70 rows) | D36: Posted eligible with budget | F36: 0 | G36: 0 | H36: 0 | J36: 0 | K36: PASS | L36: max |SQL - reference| = 0; null-pattern mismatches 0 | N36: =IF(AND(ISNUMBER(F36),ISNUMBER(G36)),ABS(G36-F36),"") -> 0 | O36: =IF(AND(ISNUMBER(N36),ISNUMBER(J36)),IF(N36<=J36,"PASS","FAIL"),"n/a") -> PASS
A37: F_B3.actual_usd | B37: Independent financial recomputation vs SQL | C37: Budget variance by division x section (b3, amounts): actual_usd (all 70 rows) | D37: Posted eligible with budget | F37: 0 | G37: 0 | H37: 0 | J37: 0.01 | K37: PASS | L37: max |SQL - reference| = 1.94e-07; null-pattern mismatches 0 | N37: =IF(AND(ISNUMBER(F37),ISNUMBER(G37)),ABS(G37-F37),"") -> 0 | O37: =IF(AND(ISNUMBER(N37),ISNUMBER(J37)),IF(N37<=J37,"PASS","FAIL"),"n/a") -> PASS
A38: F_B3.budget_usd | B38: Independent financial recomputation vs SQL | C38: Budget variance by division x section (b3, amounts): budget_usd (all 70 rows) | D38: Posted eligible with budget | F38: 0 | G38: 0 | H38: 0 | J38: 0.01 | K38: PASS | L38: max |SQL - reference| = 9.69e-08; null-pattern mismatches 0 | N38: =IF(AND(ISNUMBER(F38),ISNUMBER(G38)),ABS(G38-F38),"") -> 0 | O38: =IF(AND(ISNUMBER(N38),ISNUMBER(J38)),IF(N38<=J38,"PASS","FAIL"),"n/a") -> PASS
A39: F_B3.variance_usd | B39: Independent financial recomputation vs SQL | C39: Budget variance by division x section (b3, amounts): variance_usd (all 70 rows) | D39: Posted eligible with budget | F39: 0 | G39: 0 | H39: 0 | J39: 0.01 | K39: PASS | L39: max |SQL - reference| = 5.59e-09; null-pattern mismatches 0 | N39: =IF(AND(ISNUMBER(F39),ISNUMBER(G39)),ABS(G39-F39),"") -> 0 | O39: =IF(AND(ISNUMBER(N39),ISNUMBER(J39)),IF(N39<=J39,"PASS","FAIL"),"n/a") -> PASS
A40: F_C1.keys | B40: Independent financial recomputation vs SQL | C40: Forecast error by section (c1): same key set (rows only in one side) | D40: Posted eligible with forecast (54,851) | E40: outer join on scenario,section | F40: 0 | G40: 0 | H40: 0 | J40: 0 | K40: PASS | N40: =IF(AND(ISNUMBER(F40),ISNUMBER(G40)),ABS(G40-F40),"") -> 0 | O40: =IF(AND(ISNUMBER(N40),ISNUMBER(J40)),IF(N40<=J40,"PASS","FAIL"),"n/a") -> PASS
A41: F_C1.rows_in_scope | B41: Independent financial recomputation vs SQL | C41: Forecast error by section (c1): rows_in_scope (all 26 rows) | D41: Posted eligible with forecast (54,851) | E41: error = forecast - actual (line); WAPE = sum|error| / sum|actual|; bias = sum error / sum|actual| | F41: 0 | G41: 0 | H41: 0 | J41: 0 | K41: PASS | L41: max |SQL - reference| = 0; null-pattern mismatches 0 | N41: =IF(AND(ISNUMBER(F41),ISNUMBER(G41)),ABS(G41-F41),"") -> 0 | O41: =IF(AND(ISNUMBER(N41),ISNUMBER(J41)),IF(N41<=J41,"PASS","FAIL"),"n/a") -> PASS
A42: F_C1.actual_usd | B42: Independent financial recomputation vs SQL | C42: Forecast error by section (c1): actual_usd (all 26 rows) | D42: Posted eligible with forecast (54,851) | E42: error = forecast - actual (line); WAPE = sum|error| / sum|actual|; bias = sum error / sum|actual| | F42: 0 | G42: 0 | H42: 0 | J42: 0.01 | K42: PASS | L42: max |SQL - reference| = 1.04e-06; null-pattern mismatches 0 | N42: =IF(AND(ISNUMBER(F42),ISNUMBER(G42)),ABS(G42-F42),"") -> 0 | O42: =IF(AND(ISNUMBER(N42),ISNUMBER(J42)),IF(N42<=J42,"PASS","FAIL"),"n/a") -> PASS
A43: F_C1.forecast_usd | B43: Independent financial recomputation vs SQL | C43: Forecast error by section (c1): forecast_usd (all 26 rows) | D43: Posted eligible with forecast (54,851) | E43: error = forecast - actual (line); WAPE = sum|error| / sum|actual|; bias = sum error / sum|actual| | F43: 0 | G43: 0 | H43: 0 | J43: 0.01 | K43: PASS | L43: max |SQL - reference| = 1.01e-06; null-pattern mismatches 0 | N43: =IF(AND(ISNUMBER(F43),ISNUMBER(G43)),ABS(G43-F43),"") -> 0 | O43: =IF(AND(ISNUMBER(N43),ISNUMBER(J43)),IF(N43<=J43,"PASS","FAIL"),"n/a") -> PASS
A44: F_C1.net_error_usd | B44: Independent financial recomputation vs SQL | C44: Forecast error by section (c1): net_error_usd (all 26 rows) | D44: Posted eligible with forecast (54,851) | E44: error = forecast - actual (line); WAPE = sum|error| / sum|actual|; bias = sum error / sum|actual| | F44: 0 | G44: 0 | H44: 0 | J44: 0.01 | K44: PASS | L44: max |SQL - reference| = 2.19e-08; null-pattern mismatches 0 | N44: =IF(AND(ISNUMBER(F44),ISNUMBER(G44)),ABS(G44-F44),"") -> 0 | O44: =IF(AND(ISNUMBER(N44),ISNUMBER(J44)),IF(N44<=J44,"PASS","FAIL"),"n/a") -> PASS
A45: F_C1.abs_error_usd | B45: Independent financial recomputation vs SQL | C45: Forecast error by section (c1): abs_error_usd (all 26 rows) | D45: Posted eligible with forecast (54,851) | E45: error = forecast - actual (line); WAPE = sum|error| / sum|actual|; bias = sum error / sum|actual| | F45: 0 | G45: 0 | H45: 0 | J45: 0.01 | K45: PASS | L45: max |SQL - reference| = 9.69e-08; null-pattern mismatches 0 | N45: =IF(AND(ISNUMBER(F45),ISNUMBER(G45)),ABS(G45-F45),"") -> 0 | O45: =IF(AND(ISNUMBER(N45),ISNUMBER(J45)),IF(N45<=J45,"PASS","FAIL"),"n/a") -> PASS
A46: F_C1.abs_actual_usd | B46: Independent financial recomputation vs SQL | C46: Forecast error by section (c1): abs_actual_usd (all 26 rows) | D46: Posted eligible with forecast (54,851) | E46: error = forecast - actual (line); WAPE = sum|error| / sum|actual|; bias = sum error / sum|actual| | F46: 0 | G46: 0 | H46: 0 | J46: 0.01 | K46: PASS | L46: max |SQL - reference| = 1.7e-06; null-pattern mismatches 0 | N46: =IF(AND(ISNUMBER(F46),ISNUMBER(G46)),ABS(G46-F46),"") -> 0 | O46: =IF(AND(ISNUMBER(N46),ISNUMBER(J46)),IF(N46<=J46,"PASS","FAIL"),"n/a") -> PASS
A47: F_C1.bias | B47: Independent financial recomputation vs SQL | C47: Forecast error by section (c1): bias (all 26 rows) | D47: Posted eligible with forecast (54,851) | E47: error = forecast - actual (line); WAPE = sum|error| / sum|actual|; bias = sum error / sum|actual| | F47: 0 | G47: 0 | H47: 0 | J47: 1e-09 | K47: PASS | L47: max |SQL - reference| = 1.67e-16; null-pattern mismatches 0 | N47: =IF(AND(ISNUMBER(F47),ISNUMBER(G47)),ABS(G47-F47),"") -> 0 | O47: =IF(AND(ISNUMBER(N47),ISNUMBER(J47)),IF(N47<=J47,"PASS","FAIL"),"n/a") -> PASS
A48: F_C1.wape | B48: Independent financial recomputation vs SQL | C48: Forecast error by section (c1): wape (all 26 rows) | D48: Posted eligible with forecast (54,851) | E48: error = forecast - actual (line); WAPE = sum|error| / sum|actual|; bias = sum error / sum|actual| | F48: 0 | G48: 0 | H48: 0 | J48: 1e-09 | K48: PASS | L48: max |SQL - reference| = 3.77e-15; null-pattern mismatches 0 | N48: =IF(AND(ISNUMBER(F48),ISNUMBER(G48)),ABS(G48-F48),"") -> 0 | O48: =IF(AND(ISNUMBER(N48),ISNUMBER(J48)),IF(N48<=J48,"PASS","FAIL"),"n/a") -> PASS
A49: F_D1.keys | B49: Independent financial recomputation vs SQL | C49: Actual vs prior-year column by year x section (d1): same key set (rows only in one side) | D49: Posted eligible with PY (54,923) | E49: outer join on scenario,period_year,section | F49: 0 | G49: 0 | H49: 0 | J49: 0 | K49: PASS | N49: =IF(AND(ISNUMBER(F49),ISNUMBER(G49)),ABS(G49-F49),"") -> 0 | O49: =IF(AND(ISNUMBER(N49),ISNUMBER(J49)),IF(N49<=J49,"PASS","FAIL"),"n/a") -> PASS
A50: F_D1.rows_in_scope | B50: Independent financial recomputation vs SQL | C50: Actual vs prior-year column by year x section (d1): rows_in_scope (all 42 rows) | D50: Posted eligible with PY (54,923) | E50: change = actual - prior_year column (the file's PY column, not a true YoY) | F50: 0 | G50: 0 | H50: 0 | J50: 0 | K50: PASS | L50: max |SQL - reference| = 0; null-pattern mismatches 0 | N50: =IF(AND(ISNUMBER(F50),ISNUMBER(G50)),ABS(G50-F50),"") -> 0 | O50: =IF(AND(ISNUMBER(N50),ISNUMBER(J50)),IF(N50<=J50,"PASS","FAIL"),"n/a") -> PASS
A51: F_D1.actual_usd | B51: Independent financial recomputation vs SQL | C51: Actual vs prior-year column by year x section (d1): actual_usd (all 42 rows) | D51: Posted eligible with PY (54,923) | E51: change = actual - prior_year column (the file's PY column, not a true YoY) | F51: 0 | G51: 0 | H51: 0 | J51: 0.01 | K51: PASS | L51: max |SQL - reference| = 3.2e-07; null-pattern mismatches 0 | N51: =IF(AND(ISNUMBER(F51),ISNUMBER(G51)),ABS(G51-F51),"") -> 0 | O51: =IF(AND(ISNUMBER(N51),ISNUMBER(J51)),IF(N51<=J51,"PASS","FAIL"),"n/a") -> PASS
A52: F_D1.prior_year_usd | B52: Independent financial recomputation vs SQL | C52: Actual vs prior-year column by year x section (d1): prior_year_usd (all 42 rows) | D52: Posted eligible with PY (54,923) | E52: change = actual - prior_year column (the file's PY column, not a true YoY) | F52: 0 | G52: 0 | H52: 0 | J52: 0.01 | K52: PASS | L52: max |SQL - reference| = 3.8e-07; null-pattern mismatches 0 | N52: =IF(AND(ISNUMBER(F52),ISNUMBER(G52)),ABS(G52-F52),"") -> 0 | O52: =IF(AND(ISNUMBER(N52),ISNUMBER(J52)),IF(N52<=J52,"PASS","FAIL"),"n/a") -> PASS
A53: F_D1.change_usd | B53: Independent financial recomputation vs SQL | C53: Actual vs prior-year column by year x section (d1): change_usd (all 42 rows) | D53: Posted eligible with PY (54,923) | E53: change = actual - prior_year column (the file's PY column, not a true YoY) | F53: 0 | G53: 0 | H53: 0 | J53: 0.01 | K53: PASS | L53: max |SQL - reference| = 2.61e-08; null-pattern mismatches 0 | N53: =IF(AND(ISNUMBER(F53),ISNUMBER(G53)),ABS(G53-F53),"") -> 0 | O53: =IF(AND(ISNUMBER(N53),ISNUMBER(J53)),IF(N53<=J53,"PASS","FAIL"),"n/a") -> PASS
A54: F_D1.change_pct_of_abs_py | B54: Independent financial recomputation vs SQL | C54: Actual vs prior-year column by year x section (d1): change_pct_of_abs_py (all 42 rows) | D54: Posted eligible with PY (54,923) | E54: change = actual - prior_year column (the file's PY column, not a true YoY) | F54: 0 | G54: 0 | H54: 0 | J54: 1e-09 | K54: PASS | L54: max |SQL - reference| = 9.58e-16; null-pattern mismatches 0 | N54: =IF(AND(ISNUMBER(F54),ISNUMBER(G54)),ABS(G54-F54),"") -> 0 | O54: =IF(AND(ISNUMBER(N54),ISNUMBER(J54)),IF(N54<=J54,"PASS","FAIL"),"n/a") -> PASS
A55: F_E1.keys | B55: Independent financial recomputation vs SQL | C55: Gross profit S1/S2/S3 x rowset x year (e1): same key set (rows only in one side) | D55: Posted eligible REVENUE + COGS | E55: outer join on rowset,treatment,period | F55: 0 | G55: 0 | H55: 0 | J55: 0 | K55: PASS | N55: =IF(AND(ISNUMBER(F55),ISNUMBER(G55)),ABS(G55-F55),"") -> 0 | O55: =IF(AND(ISNUMBER(N55),ISNUMBER(J55)),IF(N55<=J55,"PASS","FAIL"),"n/a") -> PASS
A56: F_E1.rows_in_scope | B56: Independent financial recomputation vs SQL | C56: Gross profit S1/S2/S3 x rowset x year (e1): rows_in_scope (all 24 rows) | D56: Posted eligible REVENUE + COGS | E56: S1 signed as recorded; S2 GL 4190 discount forced negative (-|x|); S3 GL 4190 excluded (0) | F56: 0 | G56: 0 | H56: 0 | J56: 0 | K56: PASS | L56: max |SQL - reference| = 0; null-pattern mismatches 0 | N56: =IF(AND(ISNUMBER(F56),ISNUMBER(G56)),ABS(G56-F56),"") -> 0 | O56: =IF(AND(ISNUMBER(N56),ISNUMBER(J56)),IF(N56<=J56,"PASS","FAIL"),"n/a") -> PASS
A57: F_E1.revenue_usd | B57: Independent financial recomputation vs SQL | C57: Gross profit S1/S2/S3 x rowset x year (e1): revenue_usd (all 24 rows) | D57: Posted eligible REVENUE + COGS | E57: S1 signed as recorded; S2 GL 4190 discount forced negative (-|x|); S3 GL 4190 excluded (0) | F57: 0 | G57: 0 | H57: 0 | J57: 0.01 | K57: PASS | L57: max |SQL - reference| = 4.17e-07; null-pattern mismatches 0 | N57: =IF(AND(ISNUMBER(F57),ISNUMBER(G57)),ABS(G57-F57),"") -> 0 | O57: =IF(AND(ISNUMBER(N57),ISNUMBER(J57)),IF(N57<=J57,"PASS","FAIL"),"n/a") -> PASS
A58: F_E1.cogs_usd | B58: Independent financial recomputation vs SQL | C58: Gross profit S1/S2/S3 x rowset x year (e1): cogs_usd (all 24 rows) | D58: Posted eligible REVENUE + COGS | E58: S1 signed as recorded; S2 GL 4190 discount forced negative (-|x|); S3 GL 4190 excluded (0) | F58: 0 | G58: 0 | H58: 0 | J58: 0.01 | K58: PASS | L58: max |SQL - reference| = 1.79e-07; null-pattern mismatches 0 | N58: =IF(AND(ISNUMBER(F58),ISNUMBER(G58)),ABS(G58-F58),"") -> 0 | O58: =IF(AND(ISNUMBER(N58),ISNUMBER(J58)),IF(N58<=J58,"PASS","FAIL"),"n/a") -> PASS
A59: F_E1.gross_profit_usd | B59: Independent financial recomputation vs SQL | C59: Gross profit S1/S2/S3 x rowset x year (e1): gross_profit_usd (all 24 rows) | D59: Posted eligible REVENUE + COGS | E59: S1 signed as recorded; S2 GL 4190 discount forced negative (-|x|); S3 GL 4190 excluded (0) | F59: 0 | G59: 0 | H59: 0 | J59: 0.01 | K59: PASS | L59: max |SQL - reference| = 5.66e-07; null-pattern mismatches 0 | N59: =IF(AND(ISNUMBER(F59),ISNUMBER(G59)),ABS(G59-F59),"") -> 0 | O59: =IF(AND(ISNUMBER(N59),ISNUMBER(J59)),IF(N59<=J59,"PASS","FAIL"),"n/a") -> PASS
A60: F_E1.gross_margin_pct | B60: Independent financial recomputation vs SQL | C60: Gross profit S1/S2/S3 x rowset x year (e1): gross_margin_pct (all 24 rows) | D60: Posted eligible REVENUE + COGS | E60: S1 signed as recorded; S2 GL 4190 discount forced negative (-|x|); S3 GL 4190 excluded (0) | F60: 0 | G60: 0 | H60: 0 | J60: 1e-09 | K60: PASS | L60: max |SQL - reference| = 2.66e-15; null-pattern mismatches 0 | N60: =IF(AND(ISNUMBER(F60),ISNUMBER(G60)),ABS(G60-F60),"") -> 0 | O60: =IF(AND(ISNUMBER(N60),ISNUMBER(J60)),IF(N60<=J60,"PASS","FAIL"),"n/a") -> PASS
A61: F_E2 | B61: Independent financial recomputation vs SQL | C61: S1, S2, S3 gross profit are distinct values (not silently merged) | F61: 3 | G61: 3 | H61: 0 | I61: 0 | J61: 0 | K61: PASS | L61: {"GP_S1_SIGNED_AS_RECORDED": 109840984.25, "GP_S2_DISCOUNT_ABS": 96992614.53, "GP_S3_EXCL_DISCOUNT": 112374467.17} | N61: =IF(AND(ISNUMBER(F61),ISNUMBER(G61)),ABS(G61-F61),"") -> 0 | O61: =IF(AND(ISNUMBER(N61),ISNUMBER(J61)),IF(N61<=J61,"PASS","FAIL"),"n/a") -> PASS
A62: F_E3 | B62: Independent financial recomputation vs SQL | C62: Discount GL 4190 sign profile (why S1/S2/S3 differ) | G62: 10820 | K62: INFO | L62: positive 4568, negative 6239, zero 13 | N62: =IF(AND(ISNUMBER(F62),ISNUMBER(G62)),ABS(G62-F62),"") | O62: =IF(AND(ISNUMBER(N62),ISNUMBER(J62)),IF(N62<=J62,"PASS","FAIL"),"n/a") -> n/a
A63: F_F1.keys | B63: Independent financial recomputation vs SQL | C63: Cost by GL with Pareto share and rank (f1): same key set (rows only in one side) | D63: Posted eligible COGS+PEOPLE+OPEX+D&A | E63: outer join on gl_account,section | F63: 0 | G63: 0 | H63: 0 | J63: 0 | K63: PASS | N63: =IF(AND(ISNUMBER(F63),ISNUMBER(G63)),ABS(G63-F63),"") -> 0 | O63: =IF(AND(ISNUMBER(N63),ISNUMBER(J63)),IF(N63<=J63,"PASS","FAIL"),"n/a") -> PASS
A64: F_F1.rows_eligible | B64: Independent financial recomputation vs SQL | C64: Cost by GL with Pareto share and rank (f1): rows_eligible (all 17 rows) | D64: Posted eligible COGS+PEOPLE+OPEX+D&A | E64: abs-activity basis | F64: 0 | G64: 0 | H64: 0 | J64: 0 | K64: PASS | L64: max |SQL - reference| = 0; null-pattern mismatches 0 | N64: =IF(AND(ISNUMBER(F64),ISNUMBER(G64)),ABS(G64-F64),"") -> 0 | O64: =IF(AND(ISNUMBER(N64),ISNUMBER(J64)),IF(N64<=J64,"PASS","FAIL"),"n/a") -> PASS
A65: F_F1.actual_signed_usd | B65: Independent financial recomputation vs SQL | C65: Cost by GL with Pareto share and rank (f1): actual_signed_usd (all 17 rows) | D65: Posted eligible COGS+PEOPLE+OPEX+D&A | E65: abs-activity basis | F65: 0 | G65: 0 | H65: 0 | J65: 0.01 | K65: PASS | L65: max |SQL - reference| = 1.64e-07; null-pattern mismatches 0 | N65: =IF(AND(ISNUMBER(F65),ISNUMBER(G65)),ABS(G65-F65),"") -> 0 | O65: =IF(AND(ISNUMBER(N65),ISNUMBER(J65)),IF(N65<=J65,"PASS","FAIL"),"n/a") -> PASS
A66: F_F1.actual_abs_usd | B66: Independent financial recomputation vs SQL | C66: Cost by GL with Pareto share and rank (f1): actual_abs_usd (all 17 rows) | D66: Posted eligible COGS+PEOPLE+OPEX+D&A | E66: abs-activity basis | F66: 0 | G66: 0 | H66: 0 | J66: 0.01 | K66: PASS | L66: max |SQL - reference| = 2.53e-07; null-pattern mismatches 0 | N66: =IF(AND(ISNUMBER(F66),ISNUMBER(G66)),ABS(G66-F66),"") -> 0 | O66: =IF(AND(ISNUMBER(N66),ISNUMBER(J66)),IF(N66<=J66,"PASS","FAIL"),"n/a") -> PASS
A67: F_F1.share_of_cost_abs | B67: Independent financial recomputation vs SQL | C67: Cost by GL with Pareto share and rank (f1): share_of_cost_abs (all 17 rows) | D67: Posted eligible COGS+PEOPLE+OPEX+D&A | E67: abs-activity basis | F67: 0 | G67: 0 | H67: 0 | J67: 1e-09 | K67: PASS | L67: max |SQL - reference| = 6.66e-16; null-pattern mismatches 0 | N67: =IF(AND(ISNUMBER(F67),ISNUMBER(G67)),ABS(G67-F67),"") -> 0 | O67: =IF(AND(ISNUMBER(N67),ISNUMBER(J67)),IF(N67<=J67,"PASS","FAIL"),"n/a") -> PASS
A68: F_F1.cumulative_share | B68: Independent financial recomputation vs SQL | C68: Cost by GL with Pareto share and rank (f1): cumulative_share (all 17 rows) | D68: Posted eligible COGS+PEOPLE+OPEX+D&A | E68: abs-activity basis | F68: 0 | G68: 0 | H68: 0 | J68: 1e-09 | K68: PASS | L68: max |SQL - reference| = 6.66e-16; null-pattern mismatches 0 | N68: =IF(AND(ISNUMBER(F68),ISNUMBER(G68)),ABS(G68-F68),"") -> 0 | O68: =IF(AND(ISNUMBER(N68),ISNUMBER(J68)),IF(N68<=J68,"PASS","FAIL"),"n/a") -> PASS
A69: F_F1.rank_by_abs | B69: Independent financial recomputation vs SQL | C69: Cost by GL with Pareto share and rank (f1): rank_by_abs (all 17 rows) | D69: Posted eligible COGS+PEOPLE+OPEX+D&A | E69: abs-activity basis | F69: 0 | G69: 0 | H69: 0 | J69: 0.01 | K69: PASS | L69: max |SQL - reference| = 0; null-pattern mismatches 0 | N69: =IF(AND(ISNUMBER(F69),ISNUMBER(G69)),ABS(G69-F69),"") -> 0 | O69: =IF(AND(ISNUMBER(N69),ISNUMBER(J69)),IF(N69<=J69,"PASS","FAIL"),"n/a") -> PASS
A70: F_F2.keys | B70: Independent financial recomputation vs SQL | C70: Cost concentration: top1/top3 share, HHI (f2): same key set (rows only in one side) | D70: Posted eligible cost sections | E70: outer join on dimension | F70: 0 | G70: 0 | H70: 0 | J70: 0 | K70: PASS | N70: =IF(AND(ISNUMBER(F70),ISNUMBER(G70)),ABS(G70-F70),"") -> 0 | O70: =IF(AND(ISNUMBER(N70),ISNUMBER(J70)),IF(N70<=J70,"PASS","FAIL"),"n/a") -> PASS
A71: F_F2.members | B71: Independent financial recomputation vs SQL | C71: Cost concentration: top1/top3 share, HHI (f2): members (all 4 rows) | D71: Posted eligible cost sections | E71: HHI = sum(share^2) | F71: 0 | G71: 0 | H71: 0 | J71: 0.01 | K71: PASS | L71: max |SQL - reference| = 0; null-pattern mismatches 0 | N71: =IF(AND(ISNUMBER(F71),ISNUMBER(G71)),ABS(G71-F71),"") -> 0 | O71: =IF(AND(ISNUMBER(N71),ISNUMBER(J71)),IF(N71<=J71,"PASS","FAIL"),"n/a") -> PASS
A72: F_F2.top1_share | B72: Independent financial recomputation vs SQL | C72: Cost concentration: top1/top3 share, HHI (f2): top1_share (all 4 rows) | D72: Posted eligible cost sections | E72: HHI = sum(share^2) | F72: 0 | G72: 0 | H72: 0 | J72: 1e-09 | K72: PASS | L72: max |SQL - reference| = 7.77e-16; null-pattern mismatches 0 | N72: =IF(AND(ISNUMBER(F72),ISNUMBER(G72)),ABS(G72-F72),"") -> 0 | O72: =IF(AND(ISNUMBER(N72),ISNUMBER(J72)),IF(N72<=J72,"PASS","FAIL"),"n/a") -> PASS
A73: F_F2.top3_share | B73: Independent financial recomputation vs SQL | C73: Cost concentration: top1/top3 share, HHI (f2): top3_share (all 4 rows) | D73: Posted eligible cost sections | E73: HHI = sum(share^2) | F73: 0 | G73: 0 | H73: 0 | J73: 1e-09 | K73: PASS | L73: max |SQL - reference| = 4.44e-16; null-pattern mismatches 0 | N73: =IF(AND(ISNUMBER(F73),ISNUMBER(G73)),ABS(G73-F73),"") -> 0 | O73: =IF(AND(ISNUMBER(N73),ISNUMBER(J73)),IF(N73<=J73,"PASS","FAIL"),"n/a") -> PASS
A74: F_F2.hhi | B74: Independent financial recomputation vs SQL | C74: Cost concentration: top1/top3 share, HHI (f2): hhi (all 4 rows) | D74: Posted eligible cost sections | E74: HHI = sum(share^2) | F74: 0 | G74: 0 | H74: 0 | J74: 1e-09 | K74: PASS | L74: max |SQL - reference| = 4.44e-16; null-pattern mismatches 0 | N74: =IF(AND(ISNUMBER(F74),ISNUMBER(G74)),ABS(G74-F74),"") -> 0 | O74: =IF(AND(ISNUMBER(N74),ISNUMBER(J74)),IF(N74<=J74,"PASS","FAIL"),"n/a") -> PASS
A75: F_F2.equal_share_benchmark | B75: Independent financial recomputation vs SQL | C75: Cost concentration: top1/top3 share, HHI (f2): equal_share_benchmark (all 4 rows) | D75: Posted eligible cost sections | E75: HHI = sum(share^2) | F75: 0 | G75: 0 | H75: 0 | J75: 1e-09 | K75: PASS | L75: max |SQL - reference| = 5.55e-17; null-pattern mismatches 0 | N75: =IF(AND(ISNUMBER(F75),ISNUMBER(G75)),ABS(G75-F75),"") -> 0 | O75: =IF(AND(ISNUMBER(N75),ISNUMBER(J75)),IF(N75<=J75,"PASS","FAIL"),"n/a") -> PASS
A76: F_F2m | B76: Independent financial recomputation vs SQL | C76: Concentration top-1 member identical in every dimension | F76: 0 | G76: 0 | H76: 0 | J76: 0 | K76: PASS | L76: {"legal_entity": "US01", "division": "Consumer Durables", "gl_account": "5100", "cost_center (opex+people)": "CC410"} | N76: =IF(AND(ISNUMBER(F76),ISNUMBER(G76)),ABS(G76-F76),"") -> 0 | O76: =IF(AND(ISNUMBER(N76),ISNUMBER(J76)),IF(N76<=J76,"PASS","FAIL"),"n/a") -> PASS
A77: F_I1.keys | B77: Independent financial recomputation vs SQL | C77: Status / scale / duplicate / sign scenarios (i1): same key set (rows only in one side) | D77: any-status P&L population (136,330) or its Posted part | E77: outer join on factor,scenario | F77: 0 | G77: 0 | H77: 0 | J77: 0 | K77: PASS | N77: =IF(AND(ISNUMBER(F77),ISNUMBER(G77)),ABS(G77-F77),"") -> 0 | O77: =IF(AND(ISNUMBER(N77),ISNUMBER(J77)),IF(N77<=J77,"PASS","FAIL"),"n/a") -> PASS
A78: F_I1.rows_in_scope | B78: Independent financial recomputation vs SQL | C78: Status / scale / duplicate / sign scenarios (i1): rows_in_scope (all 18 rows) | D78: any-status P&L population (136,330) or its Posted part | E78: revenue = REVENUE; cost = COGS+PEOPLE+OPEX; proxy = revenue - cost | F78: 0 | G78: 0 | H78: 0 | J78: 0 | K78: PASS | L78: max |SQL - reference| = 0; null-pattern mismatches 0 | N78: =IF(AND(ISNUMBER(F78),ISNUMBER(G78)),ABS(G78-F78),"") -> 0 | O78: =IF(AND(ISNUMBER(N78),ISNUMBER(J78)),IF(N78<=J78,"PASS","FAIL"),"n/a") -> PASS
A79: F_I1.revenue_usd | B79: Independent financial recomputation vs SQL | C79: Status / scale / duplicate / sign scenarios (i1): revenue_usd (all 18 rows) | D79: any-status P&L population (136,330) or its Posted part | E79: revenue = REVENUE; cost = COGS+PEOPLE+OPEX; proxy = revenue - cost | F79: 0 | G79: 0 | H79: 0 | J79: 0.01 | K79: PASS | L79: max |SQL - reference| = 4.23e-06; null-pattern mismatches 0 | N79: =IF(AND(ISNUMBER(F79),ISNUMBER(G79)),ABS(G79-F79),"") -> 0 | O79: =IF(AND(ISNUMBER(N79),ISNUMBER(J79)),IF(N79<=J79,"PASS","FAIL"),"n/a") -> PASS
A80: F_I1.cost_usd | B80: Independent financial recomputation vs SQL | C80: Status / scale / duplicate / sign scenarios (i1): cost_usd (all 18 rows) | D80: any-status P&L population (136,330) or its Posted part | E80: revenue = REVENUE; cost = COGS+PEOPLE+OPEX; proxy = revenue - cost | F80: 0 | G80: 0 | H80: 0 | J80: 0.01 | K80: PASS | L80: max |SQL - reference| = 1.61e-06; null-pattern mismatches 0 | N80: =IF(AND(ISNUMBER(F80),ISNUMBER(G80)),ABS(G80-F80),"") -> 0 | O80: =IF(AND(ISNUMBER(N80),ISNUMBER(J80)),IF(N80<=J80,"PASS","FAIL"),"n/a") -> PASS
A81: F_I1.result_proxy_usd | B81: Independent financial recomputation vs SQL | C81: Status / scale / duplicate / sign scenarios (i1): result_proxy_usd (all 18 rows) | D81: any-status P&L population (136,330) or its Posted part | E81: revenue = REVENUE; cost = COGS+PEOPLE+OPEX; proxy = revenue - cost | F81: 0 | G81: 0 | H81: 0 | J81: 0.01 | K81: PASS | L81: max |SQL - reference| = 3.52e-06; null-pattern mismatches 0 | N81: =IF(AND(ISNUMBER(F81),ISNUMBER(G81)),ABS(G81-F81),"") -> 0 | O81: =IF(AND(ISNUMBER(N81),ISNUMBER(J81)),IF(N81<=J81,"PASS","FAIL"),"n/a") -> PASS
A82: F_I2 | B82: Independent financial recomputation vs SQL | C82: Five journal statuses partition the any-status population exactly | F82: 136330 | G82: 136330 | H82: 0 | I82: 0 | J82: 0 | K82: PASS | N82: =IF(AND(ISNUMBER(F82),ISNUMBER(G82)),ABS(G82-F82),"") -> 0 | O82: =IF(AND(ISNUMBER(N82),ISNUMBER(J82)),IF(N82<=J82,"PASS","FAIL"),"n/a") -> PASS
A83: F_I3 | B83: Independent financial recomputation vs SQL | C83: Non-Posted rows inside the Posted P&L population (must be 0) | F83: 0 | G83: 0 | H83: 0 | J83: 0 | K83: PASS | N83: =IF(AND(ISNUMBER(F83),ISNUMBER(G83)),ABS(G83-F83),"") -> 0 | O83: =IF(AND(ISNUMBER(N83),ISNUMBER(J83)),IF(N83<=J83,"PASS","FAIL"),"n/a") -> PASS
A84: F_I5.keys | B84: Independent financial recomputation vs SQL | C84: Scale-restored exposure (i5): same key set (rows only in one side) | D84: Posted eligible restored rows (2,374) | E84: outer join on section,scale_confidence,scale_decision | F84: 0 | G84: 0 | H84: 0 | J84: 0 | K84: PASS | N84: =IF(AND(ISNUMBER(F84),ISNUMBER(G84)),ABS(G84-F84),"") -> 0 | O84: =IF(AND(ISNUMBER(N84),ISNUMBER(J84)),IF(N84<=J84,"PASS","FAIL"),"n/a") -> PASS
A85: F_I5.rows_n | B85: Independent financial recomputation vs SQL | C85: Scale-restored exposure (i5): rows_n (all 18 rows) | D85: Posted eligible restored rows (2,374) | F85: 0 | G85: 0 | H85: 0 | J85: 0 | K85: PASS | L85: max |SQL - reference| = 0; null-pattern mismatches 0 | N85: =IF(AND(ISNUMBER(F85),ISNUMBER(G85)),ABS(G85-F85),"") -> 0 | O85: =IF(AND(ISNUMBER(N85),ISNUMBER(J85)),IF(N85<=J85,"PASS","FAIL"),"n/a") -> PASS
A86: F_I5.abs_adjusted_usd | B86: Independent financial recomputation vs SQL | C86: Scale-restored exposure (i5): abs_adjusted_usd (all 18 rows) | D86: Posted eligible restored rows (2,374) | F86: 0 | G86: 0 | H86: 0 | J86: 0.01 | K86: PASS | L86: max |SQL - reference| = 1.86e-09; null-pattern mismatches 0 | N86: =IF(AND(ISNUMBER(F86),ISNUMBER(G86)),ABS(G86-F86),"") -> 0 | O86: =IF(AND(ISNUMBER(N86),ISNUMBER(J86)),IF(N86<=J86,"PASS","FAIL"),"n/a") -> PASS
A87: F_I5.abs_as_reported_usd | B87: Independent financial recomputation vs SQL | C87: Scale-restored exposure (i5): abs_as_reported_usd (all 18 rows) | D87: Posted eligible restored rows (2,374) | F87: 0 | G87: 0 | H87: 0 | J87: 0.01 | K87: PASS | L87: max |SQL - reference| = 1.36e-12; null-pattern mismatches 0 | N87: =IF(AND(ISNUMBER(F87),ISNUMBER(G87)),ABS(G87-F87),"") -> 0 | O87: =IF(AND(ISNUMBER(N87),ISNUMBER(J87)),IF(N87<=J87,"PASS","FAIL"),"n/a") -> PASS
A88: F_I5.share_of_section_abs_activity | B88: Independent financial recomputation vs SQL | C88: Scale-restored exposure (i5): share_of_section_abs_activity (all 18 rows) | D88: Posted eligible restored rows (2,374) | F88: 0 | G88: 0 | H88: 0 | J88: 1e-09 | K88: PASS | L88: max |SQL - reference| = 1.6e-16; null-pattern mismatches 0 | N88: =IF(AND(ISNUMBER(F88),ISNUMBER(G88)),ABS(G88-F88),"") -> 0 | O88: =IF(AND(ISNUMBER(N88),ISNUMBER(J88)),IF(N88<=J88,"PASS","FAIL"),"n/a") -> PASS
A89: F_I6 | B89: Independent financial recomputation vs SQL | C89: Headline (Posted, adjusted): revenue / cost / result proxy | K89: INFO | L89: {"revenue": 202649002.15, "cost_cogs_people_opex": 176329755.99, "result_proxy": 26319246.16, "rows": 58340} | N89: =IF(AND(ISNUMBER(F89),ISNUMBER(G89)),ABS(G89-F89),"") | O89: =IF(AND(ISNUMBER(N89),ISNUMBER(J89)),IF(N89<=J89,"PASS","FAIL"),"n/a") -> n/a
A90: F_I7 | B90: Independent financial recomputation vs SQL | C90: Result proxy depends on scale rule: AS_REPORTED vs ADJUSTED difference (USD) | F90: 0 | G90: 0 | H90: 0 | J90: 0 | K90: PASS | L90: adjusted 26,319,246.16 vs as-reported 25,505,981.78: disclosed sensitivity, not an error | N90: =IF(AND(ISNUMBER(F90),ISNUMBER(G90)),ABS(G90-F90),"") -> 0 | O90: =IF(AND(ISNUMBER(N90),ISNUMBER(J90)),IF(N90<=J90,"PASS","FAIL"),"n/a") -> PASS
A91: S00 | B91: SQL layer (canonical DuckDB, read-only) | C91: Canonical DuckDB SHA-256 equals the hash recorded in Phase 6 payload | F91: 1 | G91: 1 | H91: 0 | I91: 0 | J91: 0 | K91: PASS | N91: =IF(AND(ISNUMBER(F91),ISNUMBER(G91)),ABS(G91-F91),"") -> 0 | O91: =IF(AND(ISNUMBER(N91),ISNUMBER(J91)),IF(N91<=J91,"PASS","FAIL"),"n/a") -> PASS
A92: S01 | B92: SQL layer (canonical DuckDB, read-only) | C92: fact_close rows | F92: 152682 | G92: 152682 | H92: 0 | I92: 0 | J92: 0 | K92: PASS | N92: =IF(AND(ISNUMBER(F92),ISNUMBER(G92)),ABS(G92-F92),"") -> 0 | O92: =IF(AND(ISNUMBER(N92),ISNUMBER(J92)),IF(N92<=J92,"PASS","FAIL"),"n/a") -> PASS
A93: S02 | B93: SQL layer (canonical DuckDB, read-only) | C93: fact_close columns | F93: 192 | G93: 192 | H93: 0 | I93: 0 | J93: 0 | K93: PASS | N93: =IF(AND(ISNUMBER(F93),ISNUMBER(G93)),ABS(G93-F93),"") -> 0 | O93: =IF(AND(ISNUMBER(N93),ISNUMBER(J93)),IF(N93<=J93,"PASS","FAIL"),"n/a") -> PASS
A94: S03 | B94: SQL layer (canonical DuckDB, read-only) | C94: fact_close row_id unique (grain = one source row) | F94: 0 | G94: 0 | H94: 0 | J94: 0 | K94: PASS | N94: =IF(AND(ISNUMBER(F94),ISNUMBER(G94)),ABS(G94-F94),"") -> 0 | O94: =IF(AND(ISNUMBER(N94),ISNUMBER(J94)),IF(N94<=J94,"PASS","FAIL"),"n/a") -> PASS
A95: S04 | B95: SQL layer (canonical DuckDB, read-only) | C95: v_close row count = fact_close (LEFT JOIN to dim_account does not multiply rows) | F95: 152682 | G95: 152682 | H95: 0 | I95: 0 | J95: 0 | K95: PASS | N95: =IF(AND(ISNUMBER(F95),ISNUMBER(G95)),ABS(G95-F95),"") -> 0 | O95: =IF(AND(ISNUMBER(N95),ISNUMBER(J95)),IF(N95<=J95,"PASS","FAIL"),"n/a") -> PASS
A96: S05 | B96: SQL layer (canonical DuckDB, read-only) | C96: dim_account has one row per GL account | F96: 0 | G96: 0 | H96: 0 | J96: 0 | K96: PASS | N96: =IF(AND(ISNUMBER(F96),ISNUMBER(G96)),ABS(G96-F96),"") -> 0 | O96: =IF(AND(ISNUMBER(N96),ISNUMBER(J96)),IF(N96<=J96,"PASS","FAIL"),"n/a") -> PASS
A97: S06 | B97: SQL layer (canonical DuckDB, read-only) | C97: Posting rows with a GL but no section (unmapped account_group -> NULL section) | F97: 0 | G97: 0 | H97: 0 | J97: 0 | K97: PASS | N97: =IF(AND(ISNUMBER(F97),ISNUMBER(G97)),ABS(G97-F97),"") -> 0 | O97: =IF(AND(ISNUMBER(N97),ISNUMBER(J97)),IF(N97<=J97,"PASS","FAIL"),"n/a") -> PASS
A98: S07 | B98: SQL layer (canonical DuckDB, read-only) | C98: v_pl_actual rows | F98: 58340 | G98: 58340 | H98: 0 | I98: 0 | J98: 0 | K98: PASS | N98: =IF(AND(ISNUMBER(F98),ISNUMBER(G98)),ABS(G98-F98),"") -> 0 | O98: =IF(AND(ISNUMBER(N98),ISNUMBER(J98)),IF(N98<=J98,"PASS","FAIL"),"n/a") -> PASS
A99: S08 | B99: SQL layer (canonical DuckDB, read-only) | C99: v_pl_actual_any_status rows | F99: 136330 | G99: 136330 | H99: 0 | I99: 0 | J99: 0 | K99: PASS | N99: =IF(AND(ISNUMBER(F99),ISNUMBER(G99)),ABS(G99-F99),"") -> 0 | O99: =IF(AND(ISNUMBER(N99),ISNUMBER(J99)),IF(N99<=J99,"PASS","FAIL"),"n/a") -> PASS
A100: S09 | B100: SQL layer (canonical DuckDB, read-only) | C100: v_pl_actual contains only Posted status | F100: 0 | G100: 0 | H100: 0 | J100: 0 | K100: PASS | N100: =IF(AND(ISNUMBER(F100),ISNUMBER(G100)),ABS(G100-F100),"") -> 0 | O100: =IF(AND(ISNUMBER(N100),ISNUMBER(J100)),IF(N100<=J100,"PASS","FAIL"),"n/a") -> PASS
...

Sheet Reference_headline
A1: Independent reference: headline (Posted eligible, scale-adjusted, USD)
A2: revenue = REVENUE section; cost = COGS + PEOPLE + OPEX; result proxy = revenue - cost (not EBITDA).
A3: metric | B3: value
A4: revenue | B4: 2.02649e+08
A5: cost_cogs_people_opex | B5: 1.7632976e+08
A6: result_proxy | B6: 26319246
A7: rows | B7: 58340

Sheet Reference_GP
A1: Independent reference: gross profit S1 / S2 / S3
A3: rowset | B3: treatment | C3: period | D3: rows_in_scope | E3: revenue_usd | F3: cogs_usd | G3: gross_profit_usd | H3: gross_margin_pct
A4: ROWS_ALL | B4: GP_S1_SIGNED_AS_RECORDED | C4: 2023 | D4: 15092 | E4: 61295631 | F4: 28820262 | G4: 32475369 | H4: 0.5298154
A5: ROWS_ALL | B5: GP_S1_SIGNED_AS_RECORDED | C5: 2024 | D5: 14971 | E5: 70362584 | F5: 30243513 | G5: 40119070 | H5: 0.5701762
A6: ROWS_ALL | B6: GP_S1_SIGNED_AS_RECORDED | C6: 2025 | D6: 14948 | E6: 70990788 | F6: 33744243 | G6: 37246545 | H6: 0.5246673
A7: ROWS_ALL | B7: GP_S1_SIGNED_AS_RECORDED | C7: ALL YEARS | D7: 45011 | E7: 2.02649e+08 | F7: 92808018 | G7: 1.0984098e+08 | H7: 0.54202578
A8: ROWS_ALL | B8: GP_S2_DISCOUNT_ABS | C8: 2023 | D8: 15092 | E8: 57208113 | F8: 28820262 | G8: 28387851 | H8: 0.49622072
A9: ROWS_ALL | B9: GP_S2_DISCOUNT_ABS | C9: 2024 | D9: 14971 | E9: 66280235 | F9: 30243513 | G9: 36036722 | H9: 0.54370239
A10: ROWS_ALL | B10: GP_S2_DISCOUNT_ABS | C10: 2025 | D10: 14948 | E10: 66312284 | F10: 33744243 | G10: 32568041 | H10: 0.49113134
A11: ROWS_ALL | B11: GP_S2_DISCOUNT_ABS | C11: ALL YEARS | D11: 45011 | E11: 1.8980063e+08 | F11: 92808018 | G11: 96992615 | H11: 0.51102366
A12: ROWS_ALL | B12: GP_S3_EXCL_DISCOUNT | C12: 2023 | D12: 15092 | E12: 61961255 | F12: 28820262 | G12: 33140994 | H12: 0.5348664
A13: ROWS_ALL | B13: GP_S3_EXCL_DISCOUNT | C13: 2024 | D13: 14971 | E13: 71288869 | F13: 30243513 | G13: 41045355 | H13: 0.57576107
A14: ROWS_ALL | B14: GP_S3_EXCL_DISCOUNT | C14: 2025 | D14: 14948 | E14: 71932361 | F14: 33744243 | G14: 38188118 | H14: 0.53088926
A15: ROWS_ALL | B15: GP_S3_EXCL_DISCOUNT | C15: ALL YEARS | D15: 45011 | E15: 2.0518249e+08 | F15: 92808018 | G15: 1.1237447e+08 | H15: 0.5476806
... A27: ROWS_ALL_NON_NEGATIVE | B27: GP_S3_EXCL_DISCOUNT | C27: ALL YEARS | D27: 26895 | E27: 1.6711147e+08 | F27: 84317375 | G27: 82794099 | H27: 0.49544234

Sheet Reference_CostCentre
A1: Independent reference: people + opex by cost centre
A3: cc | B3: rows | C3: abs_usd | D3: signed_usd
A4: (blank) | B4: 598 | C4: 5761461.1 | D4: 4380482.4
A5: CC110 | B5: 613 | C5: 10327568 | D5: 6917045.5
A6: CC210 | B6: 2051 | C6: 20018762 | D6: 14768890
A7: CC240 | B7: 1351 | C7: 9841493.3 | D7: 7155579.3
A8: CC310 | B8: 1355 | C8: 9334274.2 | D8: 6548033.7
A9: CC410 | B9: 1978 | C9: 20287905 | D9: 14920508
A10: CC510 | B10: 2043 | C10: 20117761 | D10: 14679087
A11: CC610 | B11: 1941 | C11: 19921936 | D11: 14152113

Sheet Reference_Status
A1: Independent reference: journal status diagnostic (any-status P&L population, 136,330 lines)
A3: status | B3: lines | C3: abs_actual_usd
A4: Posted | B4: 58340 | C4: 5.0544435e+08
A5: Pending | B5: 19777 | C5: 1.7049955e+08
A6: Rejected | B6: 19467 | C6: 1.7093226e+08
A7: (blank) | B7: 19444 | C7: 1.6983345e+08
A8: Parked | B8: 19302 | C8: 1.7081047e+08
